Workbook
Name Cash: FCFF!$G$32
Name tax: [1]DCF!$D$26
Name WACC: [2]WACC!$O$19

Sheet FCFF
J2: Scenario | K2: Base
B3: Sysco Valuation Model
B4: Year Ended June 2025) | D4: Actuals | G4: Forecasts
B5: Year | C5: ='Income Statement'!F8 -> JUN '22 | D5: ='Income Statement'!E8 -> JUN '23 | E5: ='Income Statement'!D8 -> JUN '24 | F5: ='Income Statement'!C8 -> JUN '25 | G5: JUN'26 | H5: JUN'27 | I5: JUNE'28 | J5: JUN'29 | K5: JUN'30
B6: Sales | C6: ='All financial statements 21-25'!C10 -> 68636.146 | D6: ='All financial statements 21-25'!D10 -> 76324.675 | E6: ='All financial statements 21-25'!E10 -> 78844 | F6: ='All financial statements 21-25'!F10 -> 81370 | G6: =G61 -> 84624.8 | H6: =H61 -> 96432.916 | I6: =I61 -> 108412.4 | J6: =J61 -> 113290.96 | K6: =K61 -> 118389.05
B7: COGS | C7: =-'All financial statements 21-25'!C11 -> -56421.622 | D7: =-'All financial statements 21-25'!D11 -> -62474.678 | E7: =-'All financial statements 21-25'!E11 -> -65092 | F7: =-'All financial statements 21-25'!F11 -> -67332 | G7: =G66 -> -69680.842 | H7: =H66 -> -79303.753 | I7: =I66 -> -89017.769 | J7: =J66 -> -93034.818 | K7: =K66 -> -97232.635
B8: Gross Profit | C8: =C7+C6 -> 12214.524 | D8: =D7+D6 -> 13849.997 | E8: =E7+E6 -> 13752 | F8: =F7+F6 -> 14038 | G8: =G7+G6 -> 14943.958 | H8: =H7+H6 -> 17129.163 | I8: =I7+I6 -> 19394.628 | J8: =J7+J6 -> 20256.137 | K8: =K7+K6 -> 21156.413
B9: R&D | G9: =F57 -> 0.032037948 | H9: =G57 -> 0.04 | I9: =H57 -> 0.045 | J9: =I57 -> 0.045 | K9: =J57 -> 0.045
B10: SG&A | C10: =-'All financial statements 21-25'!C17 -> -9784.725 | D10: =-'All financial statements 21-25'!D17 -> -10708.566 | E10: =-'All financial statements 21-25'!E17 -> -10270 | F10: =-'All financial statements 21-25'!F17 -> -10526 | G10: =G69 -> -11001.224 | H10: =H69 -> -12536.279 | I10: =I69 -> -14093.612 | J10: =J69 -> -14727.824 | K10: =K69 -> -15390.576
B11: EBITDA | C11: =C8+C9+C10 -> 2429.799 | D11: =D8+D9+D10 -> 3141.431 | E11: =E8+E9+E10 -> 3482 | F11: =F8+F9+F10 -> 3512 | G11: =G8+G9+G10 -> 3942.7664 | H11: =H8+H9+H10 -> 4592.9235 | I11: =I8+I9+I10 -> 5301.0617 | J11: =J8+J9+J10 -> 5528.3575 | K11: =K8+K9+K10 -> 5765.8815
B12: Depreciation | C12: =-'All financial statements 21-25'!C130 -> -880.933 | D12: =-'All financial statements 21-25'!D130 -> -888.677 | E12: =-'All financial statements 21-25'!E130 -> -997 | F12: =-'All financial statements 21-25'!F130 -> -1086 | G12: =-G94 -> -1060.9548 | H12: =-H94 -> -1208.995 | I12: =-I94 -> -1359.1837 | J12: =-J94 -> -1420.347 | K12: =-K94 -> -1484.2626
B13: EBIT | C13: =C11+C12 -> 1548.866 | D13: =D11+D12 -> 2252.754 | E13: =E11+E12 -> 2485 | F13: =F11+F12 -> 2426 | G13: =G11+G12 -> 2881.8116 | H13: =H11+H12 -> 3383.9285 | I13: =I11+I12 -> 3941.878 | J13: =J11+J12 -> 4108.0105 | K13: =K11+K12 -> 4281.619
B14: EBIT % Sales | C14: =C13/C6 -> 0.022566331 | D14: =D13/D6 -> 0.029515409 | E14: =E13/E6 -> 0.031517934 | F14: =F13/F6 -> 0.029814428 | G14: =G13/G6 -> 0.034053984 | H14: =H13/H6 -> 0.035091011 | I14: =I13/I6 -> 0.03636003 | J14: =J13/J6 -> 0.03626071 | K14: =K13/K6 -> 0.036165668
B15: EBIT * (1-t) | C15: =C13*(1-'All financial statements 21-25'!C33) -> 1204.8214 | D15: =D13*(1-'All financial statements 21-25'!D33) -> 1744.8729 | E15: =E13*(1-'All financial statements 21-25'!E33) -> 1894.0253 | F15: =F13*(1-'All financial statements 21-25'!F33) -> 1836.3263 | G15: =G13*(1-24%) -> 2190.1768 | H15: =H13*(1-24%) -> 2571.7857 | I15: =I13*(1-24%) -> 2995.8273 | J15: =J13*(1-24%) -> 3122.088 | K15: =K13*(1-24%) -> 3254.0304 | L15: <--Flat tax rate of 24% based on Syscos guidance
B16: Add back: Depreciation | C16: =-C12 -> 880.933 | D16: =-D12 -> 888.677 | E16: =-E12 -> 997 | F16: =-F12 -> 1086 | G16: =-G12 -> 1060.9548 | H16: =-H12 -> 1208.995 | I16: =-I12 -> 1359.1837 | J16: =-J12 -> 1420.347 | K16: =-K12 -> 1484.2626
B17: Less: Capex | C17: ='All financial statements 21-25'!C144 -> -632.802 | D17: ='All financial statements 21-25'!D144 -> -793.325 | E17: ='All financial statements 21-25'!E144 -> -832 | F17: ='All financial statements 21-25'!F144 -> -906 | G17: =G91 -> -904.94633 | H17: =H91 -> -1031.218 | I17: =I91 -> -1159.3221 | J17: =J91 -> -1211.4916 | K17: =K91 -> -1266.0087
B18: Less: Assets from Acquisitions | C18: ='All financial statements 21-25'!C146 -> -1281.137 | D18: ='All financial statements 21-25'!D146 -> -37.384 | E18: ='All financial statements 21-25'!E146 -> -1210 | F18: ='All financial statements 21-25'!F146 -> -40 | G18: 0 | H18: -1000 | I18: -40 | J18: -1000 | K18: -40 | L18: *Very conservative assuption based on $1B cash paid for Jetro acquisition to in 2027. Not likely they will be making any large aquistions for next few years after the 1B but estimating based on historical trend to be conservative
B19: Less: Change in NWC | C19: =-'All financial statements 21-25'!C135 -> 615.998 | D19: =-'All financial statements 21-25'!D135 -> 234.534 | E19: =-'All financial statements 21-25'!E135 -> 158 | F19: =-'All financial statements 21-25'!F135 -> 576 | G19: =-G88 -> -122.09899 | H19: =-H88 -> -311.87439 | I19: =-I88 -> -316.40047 | J19: =-J88 -> -128.85182 | K19: =-K88 -> -134.65016
B20: FCFF | C20: =SUM(C15:C19) -> 787.81344 | D20: =SUM(D15:D19) -> 2037.3749 | E20: =SUM(E15:E19) -> 1007.0253 | F20: =SUM(F15:F19) -> 2552.3263 | G20: =SUM(G15:G19) -> 2224.0863 | H20: =SUM(H15:H19) -> 1437.6883 | I20: =SUM(I15:I19) -> 2839.2884 | J20: =SUM(J15:J19) -> 2202.0915 | K20: =SUM(K15:K19) -> 3297.6341
F22: 45809 | G22: 46174 | H22: 46539 | I22: 46905 | J22: 47270 | K22: 47635
B23: Total Free Cash Flow (Perpetuity) | F23: 0 | G23: =G20*(12-MONTH(F22))/12 -> 1112.0431 | H23: =H20 -> 1437.6883 | I23: =I20 -> 2839.2884 | J23: =J20 -> 2202.0915 | K23: =K20+L32 -> 79767.353
B24: Total Cash Flow (Exit Multiple) | G24: =G23 -> 1112.0431 | H24: =H20 -> 1437.6883 | I24: =I20 -> 2839.2884 | J24: =J20 -> 2202.0915 | K24: =K20+L38 -> 67159.616
B27: WACC | C27: =WACC!AI18 -> 0.061899619
B28: Tax Rate | C28: 0.24 | D28: *expected to be approximately 23.5% to 24.0% in fiscal 2026. - this statement was in the ammual report | J28: Terminal Value: Perpetuity Method
F29: Perpetuity | H29: Exit Multiple
C30: Sum of DFCFs | F30: =XNPV(C27,F23:K23,F22:K22) -> 65490.316 | H30: =XNPV(C27,G24:K24,G22:K22) -> 59630.531 | J30: Terminal Growth Rate | L30: 0.018 | M30: <-- Based on the CBO's Budget and Economic Outlook 2025 to 2035 US GDP Growth Rate
J31: FCFF 2031 | L31: =K20*(1+L30) -> 3356.9915
C32: Enterprise value | F32: =F30 -> 65490.316 | H32: =H30 -> 59630.531 | J32: Terminal Value (2030) | L32: =L31/(C27-L30) -> 76469.719
C33: Current Cash and Investments | F33: ='All financial statements 21-25'!F60 -> 1071 | H33: =F33 -> 1071
C34: Current Debt | F34: ='All financial statements 21-25'!F92+'All financial statements 21-25'!F99 -> 14494 | H34: =F34 -> 14494 | J34: Terminal Value: Exit EBITDA Multiple
C35: Net Debt | F35: =F34-F33 -> 13423 | H35: =F35 -> 13423
J36: Exit Year EBITDA (2031) | L36: =K11*(1+L30) -> 5869.6674
C37: Equity value | F37: =F32-F35 -> 52067.316 | H37: =H32-H35 -> 46207.531 | J37: Multiple | L37: 10.88 | M37: <-- Use SYY EV/EBITDA Multiple from comps tab
J38: Terminal Value (2030) | L38: =L36*L37 -> 63861.981
C39: Number of shares (million) | F39: 478.93 | H39: =F39 -> 478.93 | I39: *Mkt Cap from factset
C40: Fair value/share | F40: =F37/F39 -> 108.71592 | H40: =H37/H39 -> 96.480762
C42: Current Market Price | F42: 73.24
C43: Recommendation | F43: =IF(F40>(1.25*F42),"Strong Buy",IF(AND(F40>(F42*1.1),F40<(F42*1.25)),"Buy",IF(AND(F40>0.9*F42,F40<1.1*F40),"HOLD","SELL"))) -> Strong Buy
E45: Growth Rate
D46: =F40 -> 108.71592 | E46: 0.01 | F46: =E46+0.5% -> 0.015 | G46: =F46+0.5% -> 0.02 | H46: =G46+0.5% -> 0.025 | I46: =H46+0.5% -> 0.03
C47: WACC | D47: 0.055 | E47: 109.1234 | F47: 124.5601 | G47: 144.40728 | H47: 170.87019 | I47: 207.91826
D48: =D47+0.5% -> 0.06 | E48: 94.513859 | F48: 106.6317 | G48: 121.77899 | H48: 141.25409 | I48: 167.22088
D49: =D48+0.5% -> 0.065 | E49: 82.576095 | F49: 92.305681 | G49: 104.1974 | H49: 119.06204 | I49: 138.17373
D50: =D49+0.5% -> 0.07 | E50: 72.641801 | F50: 80.599195 | G50: 90.148068 | H50: 101.81891 | I50: 116.40747
D51: =D50+0.5% -> 0.075 | E51: 64.248316 | F51: 70.857014 | G51: 78.667294 | H51: 88.039629 | I51: 99.494706
D52: =D51+0.5% -> 0.08 | E52: 57.065177 | F52: 62.625531 | G52: 69.11261 | H52: 76.779159 | I52: 85.979017
L54: Comments
C55: 2022 | D55: =C55+1 -> 2023 | E55: =D55+1 -> 2024 | F55: =E55+1 -> 2025 | G55: =F55+1 -> 2026 | H55: =G55+1 -> 2027 | I55: =H55+1 -> 2028 | J55: =I55+1 -> 2029 | K55: =J55+1 -> 2030
A56: Sales | B56: Sysco sales | C56: =C6 -> 68636.146 | D56: =D6 -> 76324.675 | E56: =E6 -> 78844 | F56: =F6 -> 81370 | G56: =F56*(1+G57) -> 84624.8 | H56: =G56*(1+H57) -> 88432.916 | I56: =H56*(1+I57) -> 92412.397 | J56: =I56*(1+J57) -> 96570.955 | K56: =J56*(1+K57) -> 100916.65
B57: Sysco sales growth | D57: =D56/C56-1 -> 0.11201866 | E57: =E56/D56-1 -> 0.033008002 | F57: =F56/E56-1 -> 0.032037948 | G57: ='Sales breakdown'!B21 -> 0.04 | H57: ='Sales breakdown'!C21 -> 0.045 | I57: ='Sales breakdown'!D21 -> 0.045 | J57: ='Sales breakdown'!E21 -> 0.045 | K57: ='Sales breakdown'!F21 -> 0.045 | L57: <-- based on management guidance
B58: ='Sales breakdown'!A22 -> Jetro sales added ($M) | C58: 0 | D58: 0 | E58: 0 | F58: 0 | G58: 0 | H58: ='Sales breakdown'!C22 -> 8000 | I58: ='Sales breakdown'!D22 -> 16000 | J58: ='Sales breakdown'!E22 -> 16720 | K58: ='Sales breakdown'!F22 -> 17472.4 | L58: <-- $Deal expected to close by Q3 of 2027 (March 2027) so about half a year of Jetro rev in 2027 $8B for 2027, full $16B in 2028 then 4% growth
B59: Jetro sales growth | J59: =J58/I58-1 -> 0.045 | K59: =K58/J58-1 -> 0.045
B60: Total sales growth | D60: =D61/C61-1 -> 0.11201866 | E60: =E61/D61-1 -> 0.033008002 | F60: =F61/E61-1 -> 0.032037948 | G60: =G61/F61-1 -> 0.04 | H60: =H61/G61-1 -> 0.13953494 | I60: =I61/H61-1 -> 0.12422606 | J60: =J61/I61-1 -> 0.045 | K60: =K61/J61-1 -> 0.045 | L60: CAGR | M60: =_xlfn.RRI(5,F61,K61) -> 0.07787759
B61: Net sales | C61: =C56+C58 -> 68636.146 | D61: =D56+D58 -> 76324.675 | E61: =E56+E58 -> 78844 | F61: =F56+F58 -> 81370 | G61: =G56+G58 -> 84624.8 | H61: =H56+H58 -> 96432.916 | I61: =I56+I58 -> 108412.4 | J61: =J56+J58 -> 113290.96 | K61: =K56+K58 -> 118389.05
A63: COGS | B63: Gross COGS | C63: =C7 -> -56421.622 | D63: =D7 -> -62474.678 | E63: =E7 -> -65092 | F63: =F7 -> -67332 | G63: =G61*G64 -> -69680.842 | H63: =H61*H64 -> -79403.753 | I63: =I61*I64 -> -89267.769 | J63: =J61*J64 -> -93284.818 | K63: =K61*K64 -> -97482.635
B64: Gross COGS % sales | C64: =C63/C61 -> -0.82203948 | D64: =D63/D61 -> -0.81853841 | E64: =E63/E61 -> -0.82557963 | F64: =F63/F61 -> -0.82747942 | G64: =AVERAGE(C64:F64) -> -0.82340923 | H64: =G64 -> -0.82340923 | I64: =H64 -> -0.82340923 | J64: =I64 -> -0.82340923 | K64: =J64 -> -0.82340923 | L64: Use historical average
B65: Less: Synergy Savings (m) | C65: 0 | D65: 0 | E65: 0 | F65: 0 | G65: 0 | H65: 100 | I65: 250 | J65: 250 | K65: 250 | L65: <--Synergy savings based on company guidance
B66: Net COGS | C66: =C63+C65 -> -56421.622 | D66: =D63+D65 -> -62474.678 | E66: =E63+E65 -> -65092 | F66: =F63+F65 -> -67332 | G66: =G63+G65 -> -69680.842 | H66: =H63+H65 -> -79303.753 | I66: =I63+I65 -> -89017.769 | J66: =J63+J65 -> -93034.818 | K66: =K63+K65 -> -97232.635
B67: Net COGS % Sales | C67: =-C66/C61 -> 0.82203948 | D67: =-D66/D61 -> 0.81853841 | E67: =-E66/E61 -> 0.82557963 | F67: =-F66/F61 -> 0.82747942 | G67: =-G66/G61 -> 0.82340923 | H67: =-H66/H61 -> 0.82237224 | I67: =-I66/I61 -> 0.82110322 | J67: =-J66/J61 -> 0.82120253 | K67: =-K66/K61 -> 0.82129755
A69: Operating Expenses | B69: Selling, General and Adminstrative Expenses (exc depreciation) | C69: =C10 -> -9784.725 | D69: =D10 -> -10708.566 | E69: =E10 -> -10270 | F69: =F10 -> -10526 | G69: =-G61*G70 -> -11001.224 | H69: =-H61*H70 -> -12536.279 | I69: =-I61*I70 -> -14093.612 | J69: =-J61*J70 -> -14727.824 | K69: =-K61*K70 -> -15390.576
B70: SG&A as % of Sales | C70: =-C69/C61 -> 0.14255936 | D70: =-D69/D61 -> 0.14030281 | E70: =-E69/E61 -> 0.13025722 | F70: =-F69/F61 -> 0.12935971 | G70: 0.13 | H70: =G70 -> 0.13 | I70: =H70 -> 0.13 | J70: =I70 -> 0.13 | K70: =J70 -> 0.13 | L70: Last 2 years of historical
B72: Operating current assets and Liabilities
A73: Working Capital Items | B73: I. Accounts Receivables | C73: ='All financial statements 21-25'!C63 -> 4838.912 | D73: ='All financial statements 21-25'!D63 -> 5091.97 | E73: ='All financial statements 21-25'!E63 -> 5324 | F73: ='All financial statements 21-25'!F63 -> 5502 | G73: =G61*G74 -> 5722.08 | H73: =H61*H74 -> 6520.5101 | I73: =I61*I74 -> 7330.5273 | J73: =J61*J74 -> 7660.4011 | K73: =K61*K74 -> 8005.1191
B74: AR % of Sales | D74: =D73/D61 -> 0.066714598 | E74: =E73/E61 -> 0.067525747 | F74: =F73/F61 -> 0.067617058 | G74: =F74 -> 0.067617058 | H74: =G74 -> 0.067617058 | I74: =H74 -> 0.067617058 | J74: =I74 -> 0.067617058 | K74: =J74 -> 0.067617058 | L74: last year rate/ historical
B75: Investment | D75: =D73-C73 -> 253.058 | E75: =E73-D73 -> 232.03 | F75: =F73-E73 -> 178 | G75: =G73-F73 -> 220.08 | H75: =H73-G73 -> 798.43006 | I75: =I73-H73 -> 810.01728 | J75: =J73-I73 -> 329.87373 | K75: =K73-J73 -> 344.71805
B76: II. Inventory | C76: ='All financial statements 21-25'!C67 -> 4437.498 | D76: ='All financial statements 21-25'!D67 -> 4480.812 | E76: ='All financial statements 21-25'!E67 -> 4678 | F76: ='All financial statements 21-25'!F67 -> 5053 | G76: =G61*G77 -> 5255.12 | H76: =H61*H77 -> 5988.3928 | I76: =I61*I77 -> 6732.3073 | J76: =J61*J77 -> 7035.2611 | K76: =K61*K77 -> 7351.8479
B77: Inventory as % of Sales | D77: =D76/D61 -> 0.058707253 | E77: =E76/E61 -> 0.059332352 | F77: =F76/F61 -> 0.062099054 | G77: =F77 -> 0.062099054 | H77: =G77 -> 0.062099054 | I77: =H77 -> 0.062099054 | J77: =I77 -> 0.062099054 | K77: =J77 -> 0.062099054 | L77: =L74 -> last year rate/ historical
B78: Investment | D78: =D76-C76 -> 43.314 | E78: =E76-D76 -> 197.188 | F78: =F76-E76 -> 375 | G78: =G76-F76 -> 202.12 | H78: =H76-G76 -> 733.27283 | I78: =I76-H76 -> 743.91445 | J78: =J76-I76 -> 302.95383 | K78: =K76-J76 -> 316.58675
B79: III. Other Current Assets | C79: ='All financial statements 21-25'!C69 -> 303.789 | D79: ='All financial statements 21-25'!D69 -> 284.566 | E79: ='All financial statements 21-25'!E69 -> 323 | F79: ='All financial statements 21-25'!F69 -> 338 | G79: =G61*G80 -> 351.52 | H79: =H61*H80 -> 400.56932 | I79: =I61*I80 -> 450.33047 | J79: =J61*J80 -> 470.59534 | K79: =K61*K80 -> 491.77213
B80: Other as % of Sales | D80: =D79/D61 -> 0.0037283618 | E80: =E79/E61 -> 0.0040966973 | F80: =F79/F61 -> 0.0041538651 | G80: =F80 -> 0.0041538651 | H80: =G80 -> 0.0041538651 | I80: =H80 -> 0.0041538651 | J80: =I80 -> 0.0041538651 | K80: =J80 -> 0.0041538651 | L80: historical average
B81: Investment | D81: =D79-C79 -> -19.223 | E81: =E79-D79 -> 38.434 | F81: =F79-E79 -> 15 | G81: =G79-F79 -> 13.52 | H81: =H79-G79 -> 49.04932 | I81: =I79-H79 -> 49.761148 | J81: =J79-I79 -> 20.264871 | K81: =K79-J79 -> 21.17679
B82: IV. Accounts Payables | C82: ='All financial statements 21-25'!C93 -> 5752.958 | D82: ='All financial statements 21-25'!D93 -> 6025.757 | E82: ='All financial statements 21-25'!E93 -> 6290 | F82: ='All financial statements 21-25'!F93 -> 6512 | G82: =G61*G83 -> 6734.901 | H82: =H61*H83 -> 7674.655 | I82: =I61*I83 -> 8628.0471 | J82: =J61*J83 -> 9016.3093 | K82: =K61*K83 -> 9422.0432
B83: AP as % of Sales | D83: =D82/D61 -> 0.078949003 | E83: =E82/E61 -> 0.079777789 | F83: =F82/F61 -> 0.080029495 | G83: =AVERAGE(D83:F83) -> 0.079585429 | H83: =G83 -> 0.079585429 | I83: =H83 -> 0.079585429 | J83: =I83 -> 0.079585429 | K83: =J83 -> 0.079585429 | L83: =L80 -> historical average
B84: Investment | D84: =-(D82-C82) -> -272.799 | E84: =-(E82-D82) -> -264.243 | F84: =-(F82-E82) -> -222 | G84: =-(G82-F82) -> -222.90101 | H84: =-(H82-G82) -> -939.75398 | I84: =-(I82-H82) -> -953.39215 | J84: =-(J82-I82) -> -388.26212 | K84: =-(K82-J82) -> -405.73392
B85: V. Other current Liabilities | C85: ='All financial statements 21-25'!C95 -> 2270.753 | D85: ='All financial statements 21-25'!D95 -> 2251.181 | E85: ='All financial statements 21-25'!E95 -> 2226 | F85: ='All financial statements 21-25'!F95 -> 2268 | G85: =G61*G86 -> 2358.72 | H85: =H61*H86 -> 2687.8438 | I85: =I61*I86 -> 3021.7441 | J85: =J61*J86 -> 3157.7226 | K85: =K61*K86 -> 3299.8201
B86: other CL as % of Sales | D86: =D85/D61 -> 0.0294948 | E86: =E85/E61 -> 0.028232966 | F86: =F85/F61 -> 0.02787268 | G86: =F86 -> 0.02787268 | H86: =G86 -> 0.02787268 | I86: =H86 -> 0.02787268 | J86: =I86 -> 0.02787268 | K86: =J86 -> 0.02787268 | L86: =L83 -> historical average
B87: Investment | D87: =-(D85-C85) -> 19.572 | E87: =-(E85-D85) -> 25.181 | F87: =-(F85-E85) -> -42 | G87: =-(G85-F85) -> -90.72 | H87: =-(H85-G85) -> -329.12384 | I87: =-(I85-H85) -> -333.90025 | J87: =-(J85-I85) -> -135.97848 | K87: =-(K85-J85) -> -142.09752
B88: Change in NWC | D88: =SUM(D75+D78+D81+D84+D87) -> 23.922 | E88: =SUM(E75+E78+E81+E84+E87) -> 228.59 | F88: =SUM(F75+F78+F81+F84+F87) -> 304 | G88: =SUM(G75+G78+G81+G84+G87) -> 122.09899 | H88: =SUM(H75+H78+H81+H84+H87) -> 311.87439 | I88: =SUM(I75+I78+I81+I84+I87) -> 316.40047 | J88: =SUM(J75+J78+J81+J84+J87) -> 128.85182 | K88: =SUM(K75+K78+K81+K84+K87) -> 134.65016
A91: Capex | B91: I. Capex | C91: =C17 -> -632.802 | D91: =D17 -> -793.325 | E91: =E17 -> -832 | F91: =F17 -> -906 | G91: =G61*G93 -> -904.94633 | H91: =H61*H93 -> -1031.218 | I91: =I61*I93 -> -1159.3221 | J91: =J61*J93 -> -1211.4916 | K91: =K61*K93 -> -1266.0087
B92: % Capex Growth | D92: =D91/C91-1 -> 0.25367018 | E92: =E91/D91-1 -> 0.048750512 | F92: =F91/E91-1 -> 0.088942308 | G92: =G91/F91-1 -> -0.0011629936 | H92: =H91/G91-1 -> 0.13953494 | I92: =I91/H91-1 -> 0.12422606 | J92: =J91/I91-1 -> 0.045 | K92: =K91/J91-1 -> 0.045
B93: Annual Capex as % of Sales | D93: =D91/D61 -> -0.010394083 | E93: =E91/E61 -> -0.010552483 | F93: =F91/F61 -> -0.011134325 | G93: =AVERAGE(D93:F93) -> -0.01069363 | H93: =G93 -> -0.01069363 | I93: =H93 -> -0.01069363 | J93: =I93 -> -0.01069363 | K93: =J93 -> -0.01069363 | L93: <--use average
B94: II. Depreciation & Amortization (Non-Cash Charges) | C94: =-C12 -> 880.933 | D94: =-D12 -> 888.677 | E94: =-E12 -> 997 | F94: =-F12 -> 1086 | G94: =-G91*G96 -> 1060.9548 | H94: =-H91*H96 -> 1208.995 | I94: =-I91*I96 -> 1359.1837 | J94: =-J91*J96 -> 1420.347 | K94: =-K91*K96 -> 1484.2626
B95: Depreciation as % of Sales | C95: =C94/C61 -> 0.012834826 | D95: =D94/D61 -> 0.011643377 | E95: =E94/E61 -> 0.012645223 | F95: =F94/F61 -> 0.013346442 | G95: =AVERAGE(C95:F95) -> 0.012617467 | H95: =AVERAGE(D95:G95) -> 0.012563128 | I95: =AVERAGE(E95:H95) -> 0.012793065 | J95: =AVERAGE(F95:I95) -> 0.012830026 | K95: =AVERAGE(G95:J95) -> 0.012700921
B96: Depreciation as % of Capex | C96: =C94/-C91 -> 1.3921148 | D96: =D94/-D91 -> 1.1201929 | E96: =E94/-E91 -> 1.1983173 | F96: =F94/-F91 -> 1.1986755 | G96: =AVERAGE(D96:F96) -> 1.1723952 | H96: =G96 -> 1.1723952 | I96: =H96 -> 1.1723952 | J96: =I96 -> 1.1723952 | K96: =J96 -> 1.1723952 | L96: <--Inconcisent historical trend, so use average of last 3 years

Sheet Sales breakdown
A1: SYY-US
A2: Sales
B3: JUN '21 | C3: JUN '22 | D3: JUN '23 | E3: JUN '24 | F3: JUN '25
A4: Total | B4: 51297.843 | C4: 68636.146 | D4: 76324.675 | E4: 78844 | F4: 81370
A5: United States Foodservice | B5: 35724.843 | C5: 48520.562 | D5: 53682.894 | E5: 55339 | F5: 56965
A6: International Foodservice | B6: 8350.638 | C6: 11787.449 | D6: 13559.61 | E6: 14561 | F6: 14905
A7: Sygma | B7: 6498.601 | C7: 7245.824 | D7: 7843.111 | E7: 7768 | F7: 8410
A8: Other | B8: 723.761 | C8: 1082.311 | D8: 1239.06 | E8: 1176 | F8: 1090
A9: Historical Segments | B9: - | C9: - | D9: - | E9: - | F9: -
A11: Growth (%)
B12: JUN '21 | C12: JUN '22 | D12: JUN '23 | E12: JUN '24 | F12: JUN '25
A13: Total | C13: =C4/B4-1 -> 0.33799283 | D13: =D4/C4-1 -> 0.11201866 | E13: =E4/D4-1 -> 0.033008002 | F13: =F4/E4-1 -> 0.032037948
A14: United States Foodservice | C14: =C5/B5-1 -> 0.35817425 | D14: =D5/C5-1 -> 0.10639473 | E14: =E5/D5-1 -> 0.03084979 | F14: =F5/E5-1 -> 0.029382533
A15: International Foodservice | C15: =C6/B6-1 -> 0.41156269 | D15: =D6/C6-1 -> 0.15034305 | E15: =E6/D6-1 -> 0.073850944 | F15: =F6/E6-1 -> 0.023624751
A16: Sygma | C16: =C7/B7-1 -> 0.11498213 | D16: =D7/C7-1 -> 0.082431895 | E16: =E7/D7-1 -> -0.0095766846 | F16: =F7/E7-1 -> 0.082646756
A17: Other | C17: =C8/B8-1 -> 0.49539834 | D17: =D8/C8-1 -> 0.14482806 | E17: =E8/D8-1 -> -0.050893419 | F17: =F8/E8-1 -> -0.073129252
A18: Historical Segments | B18: - | C18: - | D18: - | E18: - | F18: -
A20: Assumptions | B20: FY26 | C20: FY27 | D20: FY28 | E20: FY29 | F20: FY30
A21: Sysco Organic sales growth | B21: 0.04 | C21: 0.045 | D21: 0.045 | E21: 0.045 | F21: 0.045 | G21: *sales growth of approximately 3% to 5% to approximately $84 billion to $85 billion in 2026
A22: Jetro sales added ($M) | B22: 0 | C22: 8000 | D22: 16000 | E22: =D22*(1+E21) -> 16720 | F22: =E22*(1+F21) -> 17472.4 | G22: *based on management and then 4% growth

Sheet WACC
C2: Attempt 1: | W2: WACC FOR MODEL
F5: Market risk premium | Z5: Market risk premium
F6: =F41 -> 0.05 | Z6: =Z41 -> 0.05
C8: Cost | I8: Company risk premium | W8: Cost | AC8: Company risk premium
I9: =F11*F6 -> 0.0345 | AC9: =Z11*Z6 -> 0.036508621
C10: of | F10: Company Beta | N10: Capital | W10: of | Z10: Levered company Beta | AH10: Capital
F11: =F39 -> 0.69 | N11: structure | Z11: =Z39 -> 0.73017241 | AH11: structure
C12: equity | W12: equity
N13: we | AH13: we
L14: Cost of Equity | N14: =1-N21 -> 0.70128576 | AF14: Cost of Equity | AH14: =1-AH21 -> 0.47927589
L15: =I9+F18 -> 0.0745 | O15: BEFORE CONSIDERING ACQUISITION | AF15: =AC9+Z18 -> 0.076508621 | AI15: WACC FOR ACQUSITION
F17: Risk free rate | O17: WACC | Z17: Risk free rate | AI17: WACC
F18: =F38 -> 0.04 | O18: =(N14*L15)+(N21*L21) -> 0.061497604 | Z18: =Z38 -> 0.04 | AI18: =(AH14*AF15)+(AH21*AF21) -> 0.061899619
I20: Cost of Debt | L20: Net cost of debt | AC20: Cost of Debt | AF20: Net cost of debt
I21: =F40 -> 0.040223541 | L21: =I21*(1-F30) -> 0.030972126 | N21: =F42/(F42+(F43*F44)) -> 0.29871424 | AC21: =Z40 -> 0.063754545 | AF21: =AC21*(1-Z30) -> 0.048453455 | AH21: =Z42/(Z42+Z43*Z44) -> 0.52072411
N22: wd | AH22: fix
C23: Cost | W23: Cost
C25: of | W25: of
C27: debt | W27: debt
F29: Marginal tax rate | Z29: Marginal tax rate
F30: =F37 -> 0.23 | Z30: =Z37 -> 0.24
J31: YTM or risk free+ default spread
C36: KEY ASSUMPTIONS | W36: KEY ASSUMPTIONS
C37: Marginal tax rate | F37: =tax -> 0.23 | W37: Marginal tax rate | Z37: =24% -> 0.24
C38: Risk free rate(2) | F38: 0.04 | W38: Risk free rate(2) | Z38: 0.04
C39: Beta | F39: 0.69 | W39: Beta | Z39: =AH54 -> 0.73017241
C40: Cost of Debt kd | F40: =B77/F42 -> 0.040223541 | W40: Cost of Debt kd | Z40: 0.063754545
C41: Market Premium | F41: 0.05 | W41: Market Premium | Z41: 0.05
C42: Current Debt | F42: =B63+B70 -> 14494 | W42: Current Debt | Z42: =14970+22000 -> 36970
C43: Stock Price | F43: 71.16 | W43: Stock Price | Z43: 71.16
C44: Shares Outstanding (millions) | F44: 478.18 | W44: Shares Outstanding (millions) | Z44: 478.18
AG48: Levered Beta
AG49: Unlevered Beta | AH49: 0.55
AG50: Debt/equity before acqusition | AH50: =0.3/0.7 -> 0.42857143
AG51: Tax Rate | AH51: 0.24
AG52: B(levered)=B(UnL)(1+D/E(1-tax)) | AH52: =AH49/((1+(AH50*(1-AH51)))) -> 0.41487069
AG53: Debt/equity after acqusition | AH53: =0.5/0.5 -> 1
AG54: Levered Beta | AH54: =AH52*(1+AH53*(1-AH51)) -> 0.73017241
U55: August 5, 2025, Moody’s Investors Service has assigned us an unsecured debt credit rating of Baa1 and a ratings outlook of “stable." Standard & Poor’s has assigned us an unsecured debt credit rating of BBB and a ratings outlook of “stable." Fitch Ratings Inc. has assigned us an unsecured debt credit rating of BBB and a ratings outlook of “stable.
A60: Balance Sheet
A61: Liabilities & Shareholders' Equity
A62: Current
A63: ST Debt & Curr. Portion LT Debt | B63: 1085 | C63: 594 | D63: 161.601 | E63: 686.301 | F63: 597.582 | G63: 1651.561 | H63: 41.279 | I63: 786.505 | J63: 534.013 | K63: 98.472 | L63: 5050.052 | M63: 375.752 | N63: 248.933 | O63: 254.65 | P63: 389.006 | Q63: 7.97 | R63: 9.163 | S63: 4.896 | T63: 22.468 | U63: 135.565 | V63: 474.931 | W63: 236.667 | X63: 122.769 | Y63: 80.114 | Z63: 53.907 | AA63: 51.067 | AB63: 33.864 | AC63: 157.253 | AD63: 27.552 | AE63: 22.324
A64: Accounts Payable | B64: 6512 | C64: 6290 | D64: 6025.757 | E64: 5752.958 | F64: 4884.781 | G64: 3447.065 | H64: 4314.62 | I64: 4136.482 | J64: 3971.112 | K64: 2935.982 | L64: 2881.953 | M64: 2831.028 | N64: 2463.494 | O64: 2209.469 | P64: 2183.417 | Q64: 1953.092 | R64: 1856.887 | S64: 2048.759 | T64: 1981.19 | U64: 1891.357 | V64: 1795.824 | W64: 1742.578 | X64: 1637.505 | Y64: 1349.33 | Z64: 1271.817 | AA64: 1186.721 | AB64: 1013.302 | AC64: 849.159 | AD64: 827.593 | AE64: 779.124
A65: Income Tax Payable | B65: 51 | C65: 131 | D65: 101.894 | E65: 40.042 | F65: 22.644 | G65: 2.938 | H65: 17.343 | I65: 56.793 | J65: 14.54 | K65: 110.69 | N65: 0 | O65: 50.316 | P65: 146.083 | Q65: 178.022 | R65: 486.348 | S65: 527.796 | T65: 488.849 | U65: 453.7 | V65: 444.533 | W65: 422.419 | X65: 316.404 | Y65: 41.596 | Z65: 123.332 | AA65: 17.914 | AB65: 6.103 | AC65: 25.523 | AD65: 17.741 | AE65: 23.33
A66: Other Current Liabilities | B66: 2268 | C66: 2226 | D66: 2251.181 | E66: 2270.753 | F66: 1814.837 | G66: 1616.289 | H66: 1729.941 | I66: 1608.966 | J66: 1576.221 | K66: 1289.312 | L66: 1467.61 | M66: 1160.85 | N66: 1036.855 | O66: 909.144 | P66: 856.569 | Q66: 870.114 | R66: 797.756 | S66: 917.892 | T66: 922.582 | U66: 745.781 | V66: 742.282 | W66: 724.97 | X66: 624.451 | Y66: 768.317 | Z66: 640.839 | AA66: 527.233 | AB66: 374.271 | AC66: 292.255 | AD66: 240.928 | AE66: 212.746
A67: Miscellaneous Current Liabilities | B67: 2268 | C67: 2226 | D67: 2251.181 | E67: 2270.753 | F67: 1814.837 | G67: 1616.289 | H67: 1729.941 | I67: 1608.966 | J67: 1576.221 | K67: 1289.312 | L67: 1467.61 | M67: 1160.85 | N67: 1036.855 | O67: 909.144 | P67: 856.569 | Q67: 870.114 | R67: 797.756 | S67: 917.892 | T67: 922.582 | U67: 745.781 | V67: 742.282 | W67: 724.97 | X67: 624.451 | Y67: 768.317 | Z67: 640.839 | AA67: 527.233 | AB67: 374.271 | AC67: 292.255 | AD67: 240.928 | AE67: 212.746
A68: Total Current Liabilities | B68: 9916 | C68: 9241 | D68: 8540.433 | E68: 8750.054 | F68: 7319.844 | G68: 6717.853 | H68: 6103.183 | I68: 6588.746 | J68: 6095.886 | K68: 4434.456 | L68: 9399.615 | M68: 4367.63 | N68: 3749.282 | O68: 3423.579 | P68: 3575.075 | Q68: 3009.198 | R68: 3150.154 | S68: 3499.343 | T68: 3415.089 | U68: 3226.403 | V68: 3457.57 | W68: 3126.634 | X68: 2701.129 | Y68: 2239.357 | Z68: 2089.895 | AA68: 1782.935 | AB68: 1427.54 | AC68: 1324.19 | AD68: 1113.814 | AE68: 1037.524
A69: Long-Term
A70: Long-Term Debt | B70: 13409 | C70: 12351 | D70: 11004.266 | E70: 10703.348 | F70: 11222.665 | G70: 13425.981 | H70: 8122.058 | I70: 7540.765 | J70: 7660.877 | K70: 7336.93 | L70: 2271.825 | M70: 2384.167 | N70: 2639.986 | O70: 2763.688 | P70: 2279.517 | Q70: 2472.662 | R70: 2467.486 | S70: 1975.435 | T70: 1758.227 | U70: 1627.127 | V70: 956.177 | W70: 1231.493 | X70: 1249.467 | Y70: 1176.307 | Z70: 961.421 | AA70: 1023.642 | AB70: 997.717 | AC70: 867.017 | AD70: 685.62 | AE70: 581.734
A71: Long-Term Debt excl Lease Obligations | B71: 11973 | C71: 11206 | D71: 10088.11 | E71: 9879.706 | F71: 10536.902 | G71: 12833.543 | H71: 8122.058 | I71: 7540.765 | J71: 7660.877 | K71: 7336.93 | L71: 2271.825 | M71: 2384.167 | N71: 2639.986 | O71: 2763.688 | P71: 2279.517 | Q71: 2472.662 | R71: 2467.486 | S71: 1975.435 | T71: 1758.227 | U71: 1627.127 | V71: 956.177 | W71: 1200.36 | X71: 1215.939 | Y71: 1171.608 | Z71: 961.421 | AA71: 1023.642 | AB71: 997.717 | AC71: 867.017 | AD71: 685.62 | AE71: 581.734
A72: Capital and Operating Lease Obligations | B72: 1436 | C72: 1145 | D72: 916.156 | E72: 823.642 | F72: 685.763 | G72: 592.438 | H72: 0 | I72: 0 | J72: 0 | K72: 0 | L72: 0 | M72: 0 | N72: 0 | O72: 0 | P72: 0 | Q72: 0 | R72: 0 | S72: 0 | T72: 0 | U72: 0 | V72: 0 | W72: 31.133 | X72: 33.528 | Y72: 4.699 | Z72: 0 | AA72: 0 | AB72: 0 | AC72: 0 | AD72: 0 | AE72: 0
A76: Income Statement
A77: Interest Expense | B77: 583 | C77: 588 | D77: 578 | E77: 500 | F77: 470 | G77: 505 | H77: 340 | I77: 274 | J77: 314 | K77: 291 | L77: 220 | M77: 130 | N77: 134 | O77: 132 | P77: 121 | Q77: 127 | R77: 136 | S77: 116 | T77: 112 | U77: 105 | V77: 109 | W77: 75 | X77: 70 | Y77: 72 | Z77: 63 | AA77: 72 | AB77: 71 | AC77: 73 | AD77: 58 | AE77: 47 | AF77: 41

Sheet DDM (only div)
A1: Equity Valuation: Dividend Discount Model
B2: ='Income Statement'!C8 -> JUN '25 | C2: ='Income Statement'!D8 -> JUN '24 | D2: ='Income Statement'!E8 -> JUN '23 | E2: ='Income Statement'!F8 -> JUN '22 | F2: ='Income Statement'!G8 -> JUN '21 | G2: ='Income Statement'!H8 -> JUN '20 | H2: ='Income Statement'!I8 -> JUN '19 | I2: ='Income Statement'!J8 -> JUN '18 | ... AE2: ='Income Statement'!AF8 -> JUN '96
A3: DPS | B3: ='Income Statement'!C54 -> 2.07 | C3: ='Income Statement'!D54 -> 2.01 | D3: ='Income Statement'!E54 -> 1.97 | E3: ='Income Statement'!F54 -> 1.9 | F3: ='Income Statement'!G54 -> 1.82 | G3: ='Income Statement'!H54 -> 1.74 | H3: ='Income Statement'!I54 -> 1.53 | I3: ='Income Statement'!J54 -> 1.41 | ... AE3: ='Income Statement'!AF54 -> 0.125
A4: Div Payout ratio | B4: ='Income Statement'!C55/100 -> 0.55467724 | C4: ='Income Statement'!D55/100 -> 0.51725469 | D4: ='Income Statement'!E55/100 -> 0.56728194 | E4: ='Income Statement'!F55/100 -> 0.71874409 | F4: ='Income Statement'!G55/100 -> 1.7829154 | G4: ='Income Statement'!H55/100 -> 4.1428571 | H4: ='Income Statement'!I55/100 -> 0.478125 | I4: ='Income Statement'!J55/100 -> 0.52222222 | ... AE4: ='Income Statement'!AF55/100 -> 0.32894737
A5: Return on Equity (in %) | B5: 99.078591 | C5: 101.06958 | D5: 104.40493 | E5: 92.585743 | F5: 38.665481 | G5: 11.770679 | H5: 66.843036 | I5: 58.536316 | J5: 38.985799 | K5: 21.730898 | L5: 13.047939 | M5: 17.813884 | N5: 20.096023 | O5: 23.888207 | P5: 27.002492 | Q5: 32.429464 | R5: 30.791545 | S5: 33.081715 | T5: 31.626156 | U5: 29.117952 | V5: 36.122288 | W5: 38.10193 | X5: 35.93492 | Y5: 31.775411 | Z5: 30.544209 | AA5: 28.451714 | AB5: 26.025356 | AC5: 23.561135 | AD5: 21.044676 | AE5: 19.240998
A6: Div growth rate | B6: =(B3/C3)-1 -> 0.029850746 | C6: =(C3/D3)-1 -> 0.020304569 | D6: =(D3/E3)-1 -> 0.036842105 | E6: =(E3/F3)-1 -> 0.043956044 | F6: =(F3/G3)-1 -> 0.045977011 | G6: =(G3/H3)-1 -> 0.1372549 | H6: =(H3/I3)-1 -> 0.085106383 | I6: =(I3/J3)-1 -> 0.084615385 | ... AD6: =(AD3/AE3)-1 -> 0.16
A8: ROE | B8: =B5/100 -> 0.99078591 | C8: =C5/100 -> 1.0106958 | D8: =D5/100 -> 1.0440493 | E8: =E5/100 -> 0.92585743 | F8: =F5/100 -> 0.38665481 | G8: =G5/100 -> 0.11770679 | H8: =H5/100 -> 0.66843036 | I8: =I5/100 -> 0.58536316 | ... AE8: =AE5/100 -> 0.19240998
A10: Historical Stats on Common Equity Returns (30 years)
B11: Mean | C11: Median | D11: Min | E11: Max | G11: *look at data from past 10 years
A12: =A4 -> Div Payout ratio | B12: =AVERAGE(B4:AE4) -> 0.67029618 | C12: =MEDIAN(B4:AE4) -> 0.50737107 | D12: =MIN(B4:AE4) -> 0.30681818 | E12: =MAX(B4:AE4) -> 4.1428571
A13: =A5 -> Return on Equity (in %) | B13: =AVERAGE(B8:AE8) -> 0.39445636 | C13: =MEDIAN(B8:AE8) -> 0.3120885 | D13: =MIN(B8:AE8) -> 0.11770679 | E13: =MAX(B8:AE8) -> 1.0440493
A14: =A6 -> Div growth rate | B14: =AVERAGE(B6:AE6) -> 0.10367724 | C14: =MEDIAN(B6:AE6) -> 0.085106383 | D14: =MIN(B6:AE6) -> 0.020304569 | E14: =MAX(B6:AE6) -> 0.25925926
A16: Historical Stats on Common Equity Returns (last 10 years about with out outliers)
B17: Mean | C17: Median | D17: Min | E17: Max
A18: =A12 -> Div Payout ratio | B18: =AVERAGE(B4,C4,D4,E4,H4,I4,J4,K4,M4,N4) -> 0.61258239 | C18: =MEDIAN(B4,C4,D4,E4,H4,I4,J4,K4,M4,N4) -> 0.59614097 | D18: =MIN(B4,C4,D4,E4,H4,I4,J4,K4,M4,N4) -> 0.478125 | E18: =MAX(B4,C4,D4,E4,H4,I4,J4,K4,M4,N4) -> 0.75
A19: =A13 -> Return on Equity (in %) | B19: =AVERAGE(B8,C8,D8,E8,F8,H8,I8,J8,K8,L8,M8,N8) -> 0.56071518 | C19: =MEDIAN(B8,C8,D8,E8,F8,H8,I8,J8,K8,L8,M8,N8) -> 0.48761057 | D19: =MEDIAN(C8,D8,E8,F8,G8,I8,J8,K8,L8,M8,N8,O8) -> 0.31276844 | E19: =MEDIAN(D8,E8,F8,G8,H8,J8,K8,L8,M8,N8,O8,P8) -> 0.2544535
A20: =A14 -> Div growth rate | B20: =AVERAGE(B6,C6,D6,E6,F6,H6,I6,J6,K6,L6,M6,N6) -> 0.045448173 | C20: =MEDIAN(B6,C6,D6,E6,F6,H6,I6,J6,K6,L6,M6,N6) -> 0.037112641 | D20: =MIN(B6,C6,D6,E6,F6,H6,I6,J6,K6,L6,M6,N6) -> 0.020304569 | E20: =MAX(B6,C6,D6,E6,F6,H6,I6,J6,K6,L6,M6,N6) -> 0.085106383
A22: Indicated annual div yield | B22: 2.16 | C22: *from factset
A24: Sustainable Growth Rate of Dividends
A25: CACR of DPS | B25: =_xlfn.RRI(29,AE3,B3) -> 0.10163205
A26: Sustainable Growth Rate | B26: =B27*(1-B28) -> 0.13005377
A27: ROE | B27: =B13 -> 0.39445636
A28: =A12 -> Div Payout ratio | B28: =B12 -> 0.67029618
A29: 1 yr div growth | B29: 0.064
A31: Required Rate of Return (CAPM) | B31: =B33+(B32*B34) -> 0.07746569
A32: beta | B32: =WACC!AH54 -> 0.73017241 | C32: Levered beta calculated from WACC tab
A33: risk free | B33: 0.0449 | C33: 30 Year treausre bond
A34: market premium | B34: 0.0446 | C34: *US from website: https://pages.stern.nyu.edu/~adamodar/New_Home_Page/datafile/ctryprem.html
M35: *investors who care about div and div yield this is a good investment
A36: Cost of equity | B36: 0.0765 | C36: *using cost of equity from WACC calculations
A38: Terminal growth rate | B38: 0.044 | C38: *avg growth rate over past 10 yrs
A40: g | B40: 0.03 | C40: =B40 -> 0.03 | D40: 0.04 | E40: 0.05 | F40: 0.05 | G40: 0.06 | H40: *to showcase once debt is more managable, SYY will be more aggressive with DIV growth rate
A41: t | B41: 1 | C41: 2 | D41: 3 | E41: 4 | F41: 5 | G41: 6
B42: CF1 | C42: CF2 | D42: CF3 | E42: CF4 | F42: CF5 | G42: CF6
A43: Dividends | B43: =B22*(1+B40) -> 2.2248 | C43: =B43*(1+C40) -> 2.291544 | D43: =C43*(1+D40) -> 2.3832058 | E43: =D43*(1+E40) -> 2.502366 | F43: =E43*(1+F40) -> 2.6274844 | G43: =F43*(1+G40) -> 2.7851334
A44: Terminal value | G44: =G43*(1+B38)/(B36-B38) -> 89.467055 | I44: Fair price | K44: Current price
A45: Total | B45: =SUM(B43:B44) -> 2.2248 | C45: =SUM(C43:C44) -> 2.291544 | D45: =SUM(D43:D44) -> 2.3832058 | E45: =SUM(E43:E44) -> 2.502366 | F45: =SUM(F43:F44) -> 2.6274844 | G45: =SUM(G43:G44) -> 92.252188 | I45: =NPV(B36,B45:G45) -> 68.913188 | J45: VS | K45: 73.24

Sheet Ratios
A1: Sysco Corporation (SYY)
A2: 71.16
A5: Sysco Corporation
A6: SYY 871829107 2868165 NYSE Common stock
A7: Source: FactSet Fundamentals
B8: DEC '25 | C8: DEC '24 | D8: DEC '23 | E8: DEC '22 | F8: DEC '21 | J8: DEC '25 | K8: DEC '24 | L8: DEC '23 | M8: DEC '22 | N8: DEC '21 | Q8: Sysco | R8: USFD | S8: PFGC | T8: UNFI
P9: Market Cap (M) | Q9: 34080.7 | R9: 19828.93 | S9: 13917.88 | T9: 2724.12
P10: Revenue (M) | Q10: 76324.68 | R10: 35597 | S10: 57254.7 | T10: 30272
A11: Profitability | I11: Profitability | P11: Ratios
A12: Gross Margin | B12: 18.35 | C12: 18.31 | D12: 18.28 | E12: 17.92 | F12: 17.8 | I12: Gross Margin | J12: 18.35 | K12: 18.31 | L12: 18.28 | M12: 17.92 | N12: 17.8 | P12: Profitability
P13: P/S | Q13: =Q9/Q10 -> 0.44652267 | R13: =R9/R10 -> 0.55703936 | S13: =S9/S10 -> 0.24308712 | T13: =T9/T10 -> 0.089988108
A14: SG&A to Sales | B14: 14.15 | C14: 14.04 | D14: 14.05 | E14: 14.16 | F14: 14.5 | I14: Operating Margin | J14: 4.2 | K14: 4.28 | L14: 4.23 | M14: 3.76 | N14: 3.31 | P14: Gross Margin | Q14: =J12 -> 18.35 | R14: 17.41 | S14: 10.69 | T14: 12.47
A15: Operating Margin | B15: 4.2 | C15: 4.28 | D15: 4.23 | E15: 3.76 | F15: 3.31 | I15: Net Margin | J15: 2.17 | K15: 2.4 | L15: 2.69 | M15: 1.93 | N15: 1.29 | P15: Operating Margin | Q15: =J14 -> 4.2 | R15: 3.37 | S15: 1.36 | T15: 0.78
A16: Pretax Margin | B16: 2.84 | C16: 3.14 | D16: 3.51 | E16: 2.45 | F16: 1.59 | I16: Return on Assets | J16: 6.85 | K16: 7.72 | L16: 8.89 | M16: 6.53 | N16: 3.58 | P16: Net Margin | Q16: =J15 -> 2.17 | R16: 1.71 | S16: 0.52 | T16: -0.27
A17: Net Margin | B17: 2.17 | C17: 2.4 | D17: 2.69 | E17: 1.93 | F17: 1.29 | I17: Return on Equity | J17: 83.64 | K17: 87.49 | L17: 108.42 | M17: 106.87 | N17: 59.33 | P17: Return on Assets | Q17: =J16 -> 6.85 | R17: 4.81 | S17: 1.93 | T17: -1.13
A18: Free Cash Flow Margin | B18: 2.12 | C18: 2.25 | D18: 3.08 | E18: 1.57 | F18: 1.41 | I18: Return on Invested Capital | J18: 11.86 | K18: 13.09 | L18: 15.09 | M18: 11.41 | N18: 5.83 | P18: Return on Equity | Q18: =J17 -> 83.64 | R18: 15.3 | S18: 7.75 | T18: -5.4
A19: Free Cash Flow Conversion Ratio | B19: 40.9 | C19: 41.78 | D19: 66.59 | E19: 12.73 | F19: -10.71 | I19: Operating Efficiency | P19: Return on Invested Capital | Q19: =J18 -> 11.86 | R19: 7.02 | S19: 2.86 | T19: 11.43
A20: Capex To Sales | B20: 1.06 | C20: 1.02 | D20: 1.07 | E20: 1.03 | F20: 0.8 | I20: Days of Sales Outstanding | J20: 24.04 | K20: 24.05 | L20: 24.09 | M20: 22.95 | N20: 21.7 | P20: Operating Efficiency
A21: Return on Assets | B21: 6.85 | C21: 7.72 | D21: 8.89 | E21: 6.53 | F21: 3.58 | I21: Days of Payables Outstanding | J21: 31.8 | K21: 31.95 | L21: 32.12 | M21: 31.26 | N21: 30.72 | P21: Days of Sales Outstanding | Q21: =J20 -> 24.04 | R21: 20.5 | S21: 15.24 | T21: 11.91
A22: Return on Equity | B22: 83.64 | C22: 87.49 | D22: 108.42 | E22: 106.87 | F22: 59.33 | I22: Net Operating Cycle | J22: 20.12 | K22: 19.2 | L22: 19.01 | M22: 18.21 | N22: 17.36 | P22: Days of Payables Outstanding | Q22: =J21 -> 31.8 | R22: 26.15 | S22: 19.27 | T22: 24.25
A23: Return on Common Equity | B23: 83.64 | C23: 87.49 | D23: 108.42 | E23: 106.87 | F23: 59.33 | I23: Leverage | P23: Net Operating Cycle | Q23: =J22 -> 20.12 | R23: 13.05 | S23: 21.39 | T23: 16.4
A24: Return on Total Capital | B24: 21.01 | C24: 22.14 | D24: 22.88 | E24: 20.98 | F24: 13.82 | I24: Total Debt/Total Assets (%) | J24: 55.07 | K24: 54.07 | L24: 52.42 | M24: 53.38 | N24: 55.27 | P24: Leverage
A25: Return on Invested Capital | B25: 11.86 | C25: 13.09 | D25: 15.09 | E25: 11.41 | F25: 5.83 | P25: Total Debt/Total Assets (%) | Q25: =J24 -> 55.07 | R25: 39.99 | S25: 43.32 | T25: 45.08
A26: Cash Flow Return on Invested Capital | B26: 17.3 | C26: 17.82 | D26: 23.34 | E26: 15.41 | F26: 9.98 | P26: Coverage
A27: Valuation | P27: (EBITDA-Capex)/Interest Expense | Q27: =B103 -> 6.32 | R27: 5.88 | S27: 2.94 | T27: 2.62
A28: Enterprise Value/EBIT | B28: 14.3 | C28: 13.75 | D28: 14.61 | E28: 19.4 | F28: 24.21 | P28: Net Debt/(EBITDA-Capex) | Q28: =B89 -> 3.73 | R28: 4.11 | S28: 6.76 | T28: 8.81
A29: Enterprise Value/EBITDA | B29: 10.88 | C29: 10.53 | D29: 11.36 | E29: 14.7 | F29: 16.92
A30: Enterprise Value/Sales | B30: 0.6 | C30: 0.59 | D30: 0.62 | E30: 0.73 | F30: 0.8
A31: Total Debt/Enterprise Value | B31: 0.3 | C31: 0.29 | D31: 0.27 | E31: 0.22 | F31: 0.24
A32: Per Share
A33: Sales per Share | B33: 171.94 | C33: 163.49 | D33: 153.21 | E33: 144.23 | F33: 118.04
A34: EBIT (Operating Income) per Share | B34: 7.22 | C34: 6.99 | D34: 6.48 | E34: 5.42 | F34: 3.9
A35: EPS (recurring) | B35: 4.44 | C35: 4.23 | D35: 4.29 | E35: 2.98 | F35: 2.38
A36: EPS (basic) | B36: 3.73 | C36: 3.91 | D36: 4.11 | E36: 2.79 | F36: 1.53
A37: EPS (diluted) | B37: 3.72 | C37: 3.89 | D37: 4.1 | E37: 2.77 | F37: 1.52
A38: Dividends per Share | B38: 2.13 | C38: 2.03 | D38: 1.99 | E38: 1.94 | F38: 1.86
A39: Dividend Payout Ratio (%) | B39: 57.29 | C39: 52.15 | D39: 48.55 | E39: 69.92 | F39: 122.06
A40: Book Value per Share | B40: 4.77 | C40: 4.11 | D40: 4.77 | E40: 2.83 | F40: 2.41
A41: Tangible Book Value per Share | B41: -8.44 | C41: -8.68 | D41: -7.99 | E41: -7.99 | F41: -8.09
A42: Cash Flow per Share | B42: 5.46 | C42: 5.34 | D42: 6.36 | E42: 3.76 | F42: 2.61
A43: Free Cash Flow per Share | B43: 3.64 | C43: 3.68 | D43: 4.72 | E43: 2.27 | F43: 1.66
A44: Diluted Shares Outstanding (M) | B44: 480.66 | C44: 492.8 | D44: 505.93 | E44: 510.15 | F44: 514.57
... A46: Total Shares Outstanding (M) | B46: 478.93 | C46: 489.47 | D46: 503.7 | E46: 507.33 | F46: 507.14
A47: Asset Turnover Analysis
A48: Cash & ST Investments | B48: 82.03 | C48: 91.81 | D48: 106 | E48: 78.5 | F48: 17.01
A49: Receivables | B49: 15.18 | C49: 15.18 | D49: 15.15 | E49: 15.9 | F49: 16.82
A50: Inventories | B50: 13.09 | C50: 13.47 | D50: 13.5 | E50: 13.76 | F50: 13.84
A51: Current Assets | B51: 6.91 | C51: 7.06 | D51: 7.14 | E51: 7.19 | F51: 5.51
A52: Fixed Assets | B52: 11.91 | C52: 12.79 | D52: 13.78 | E52: 14.28 | F52: 12.09
A53: Total Assets | B53: 3.15 | C53: 3.22 | D53: 3.31 | E53: 3.38 | F53: 2.77
A54: DuPont Analysis
A55: Asset Turnover (x) | B55: 3.15 | C55: 3.22 | D55: 3.31 | E55: 3.38 | F55: 2.77
A56: x Pretax Margin (%) | B56: 2.84 | C56: 3.14 | D56: 3.51 | E56: 2.45 | F56: 1.59
A57: = Pretax Return on Assets (%) | B57: 8.95 | C57: 10.12 | D57: 11.62 | E57: 8.28 | F57: 4.39
A58: x Tax Rate Complement (1-Tax Rate) (%) | B58: 76.47 | C58: 76.31 | D58: 76.55 | E58: 78.86 | F58: 81.46
A59: = Return on Assets (%) | B59: 6.85 | C59: 7.72 | D59: 8.89 | E59: 6.53 | F59: 3.58
A60: x Equity Multiplier (Assets/Equity) | B60: 12.22 | C60: 11.33 | D60: 12.19 | E60: 16.37 | F60: 16.59
A61: = Return on Equity (%) | B61: 83.64 | C61: 87.49 | D61: 108.42 | E61: 106.87 | F61: 59.33
A62: x Earnings Retention (1-Payout) (%) | B62: 42.71 | C62: 47.85 | D62: 51.45 | E62: 30.08 | F62: -22.06
A63: = Reinvestment Rate (%) | B63: 36.4 | C63: 41.98 | D63: 56.17 | E63: 33.43 | F63: -11.69
A64: Note: EBIT Return on Assets (%) | B64: 13.22 | C64: 13.77 | D64: 14.01 | E64: 12.71 | F64: 9.14
A65: Note: Interest as % Assets | B65: 2.14 | C65: 2.52 | D65: 2.1 | E65: 2.21 | F65: 2.13
A66: Operating Efficiency
A67: Revenue/Employee (actual) | B67: 1101947 | C67: 1067159 | D67: 1047463 | E67: 1029093 | F67: 941678
A68: Net Income/Employee (actual) | B68: 23960 | C68: 25599 | D68: 28135 | E68: 19862 | F68: 12178
A69: Assets/Employee (actual) | B69: 362413 | C69: 335338 | D69: 334332 | E69: 308912 | F69: 332198
A70: Receivables Turnover | B70: 15.18 | C70: 15.18 | D70: 15.15 | E70: 15.9 | F70: 16.82
A71: Inventory Turnover | B71: 13.09 | C71: 13.47 | D71: 13.5 | E71: 13.76 | F71: 13.84
A72: Payables Turnover | B72: 11.48 | C72: 11.42 | D72: 11.37 | E72: 11.67 | F72: 11.88
A73: Asset Turnover | B73: 3.15 | C73: 3.22 | D73: 3.31 | E73: 3.38 | F73: 2.77
A74: Working Capital Turnover | B74: 29.18 | C74: 41.36 | D74: 25.37 | E74: 36.65 | F74: 24.59
A75: Operating Cycle - Days
A76: Days of Inventory on Hand | B76: 27.88 | C76: 27.1 | D76: 27.04 | E76: 26.52 | F76: 26.38
A77: + Days of Sales Outstanding | B77: 24.04 | C77: 24.05 | D77: 24.09 | E77: 22.95 | F77: 21.7
A78: = Operating Cycle | B78: 51.92 | C78: 51.15 | D78: 51.12 | E78: 49.48 | F78: 48.08
A79: - Days of Payables Outstanding | B79: 31.8 | C79: 31.95 | D79: 32.12 | E79: 31.26 | F79: 30.72
A80: = Net Operating Cycle | B80: 20.12 | C80: 19.2 | D80: 19.01 | E80: 18.21 | F80: 17.36
A81: Liquidity
A82: Current Ratio (x) | B82: 1.3 | C82: 1.2 | D82: 1.37 | E82: 1.24 | F82: 1.33
A83: Quick Ratio (x) | B83: 0.75 | C83: 0.68 | D83: 0.8 | E83: 0.68 | F83: 0.78
A84: Cash Ratio | B84: 0.13 | C84: 0.08 | D84: 0.12 | E84: 0.06 | F84: 0.18
A85: Cash & ST Inv/Current Assets | B85: 9.84 | C85: 6.9 | D85: 8.51 | E85: 4.81 | F85: 13.66
A86: CFO/Current Liabilities | B86: 27.37 | C86: 27.54 | D86: 39.01 | E86: 22.86 | F86: 17.7
A87: Coverage
A88: Net Debt/EBITDA | B88: 2.71 | C88: 2.63 | D88: 2.64 | E88: 2.89 | F88: 3.38
A89: Net Debt/(EBITDA-Capex) | B89: 3.73 | C89: 3.5 | D89: 3.54 | E89: 3.91 | F89: 4.39
A90: Total Debt/EBITDA | B90: 2.98 | C90: 2.8 | D90: 2.87 | E90: 3.03 | F90: 3.86
A91: EBIT/Interest Expense (Int. Coverage) | B91: 5.95 | C91: 5.41 | D91: 6.32 | E91: 5.68 | F91: 4.39
A92: EBITDA/Interest Expense | B92: 7.82 | C92: 7.06 | D92: 8.13 | E92: 7.49 | F92: 6.28
A93: Fixed-charge Coverage Ratio | B93: 5.95 | C93: 5.41 | D93: 6.32 | E93: 5.68 | F93: 4.39
A94: CFO/Interest Expense | B94: 4.5 | C94: 4.13 | D94: 6.2 | E94: 3.94 | F94: 2.94
A95: Cash Dividend Coverage Ratio | B95: 3.07 | C95: 3.12 | D95: 3.24 | E95: 2.7 | F95: 2.14
A96: LT Debt/EBITDA | B96: 3 | C96: 2.74 | D96: 3.03 | E96: 3.01 | F96: 3.92
A97: Net Debt/FFO | B97: 4.41 | C97: 4.11 | D97: 3.7 | E97: 4.29 | F97: 5.19
A98: LT Debt/FFO | B98: 4.39 | C98: 3.94 | D98: 3.93 | E98: 4.18 | F98: 5.58
A99: FCF/Total Debt | B99: 0.12 | C99: 0.13 | D99: 0.18 | E99: 0.1 | F99: 0.07
... A103: EBITDA-Capex/Interest Expense | B103: 6.32 | C103: 5.78 | D103: 6.53 | E103: 5.93 | F103: 5.21
A104: Leverage
A105: LT Debt/Total Equity | B105: 599.04 | C105: 612.86 | D105: 531 | E105: 764.57 | F105: 921.53
A106: LT Debt/Total Capital | B106: 79.27 | C106: 78.6 | D106: 83.04 | E106: 83.04 | F106: 86.13
...

Sheet Comparables
C3: EPS | D3: EBITDA | E3: EBIT | F3: Sysco Comparable Valuation
B4: Company | C4: P/E | D4: EV/EBITDA | E4: EV/EBIT | G4: EV/EBIT | H4: EV/EBITDA | I4: P/E
B5: Comparable Markets | F5: 2025 | G5: ='Income Statement'!B58 -> 3470 | H5: ='Income Statement'!B57 -> 4560 | I5: ='Income Statement'!B50*'Income Statement'!B51 -> 1787.1998 | J5: annual report says adjusted EPS of 4.46 which is higher
B6: US Food Holding Corp (USFD) | C6: ='Comparable Co Statements '!A2/'Comparable Co Statements '!B34 -> 30.581633 | D6: ='Comparable Co Statements '!B26 -> 12.44 | E6: ='Comparable Co Statements '!B25 -> 16.76 | F6: Implied Enterprise Value | G6: =G5*E10 -> 71724.9 | H6: =H5*D10 -> 56726.4
B7: Performance Food Group Company (PFGC) | C7: ='Comparable Co Statements '!H2/'Comparable Co Statements '!I34 -> 38.186364 | D7: ='Comparable Co Statements '!I26 -> 12.85 | E7: ='Comparable Co Statements '!I25 -> 24.05 | F7: Debt | G7: ='Balance Sheet'!B46+'Balance Sheet'!B53 -> 14494 | H7: =G7 -> 14494
B8: United Natural Food Inc (UNFI) | C8: ='Comparable Co Statements '!P2/'Comparable Co Statements '!P34 -> 0 | D8: ='Comparable Co Statements '!P26 -> 9.09 | E8: ='Comparable Co Statements '!P25 -> 20.67
B9: Mean | C9: =AVERAGE(C6:C8) -> 22.922665 | D9: =AVERAGE(D6:D8) -> 11.46 | E9: =AVERAGE(E6:E8) -> 20.493333 | F9: Cash | G9: ='Balance Sheet'!B85 -> 41 | H9: ='Balance Sheet'!B85 -> 41 | J9: why is cash for fisical vs calendar year so different
B10: Median | C10: =MEDIAN(C6:C8) -> 30.581633 | D10: =MEDIAN(D6:D8) -> 12.44 | E10: =MEDIAN(E6:E8) -> 20.67 | F10: Implied equity value | G10: =G6-G7+G9 -> 57271.9 | H10: =H6-H7+H9 -> 42273.4 | I10: =I5*C10 -> 54655.487
B11: Target | F11: Number of shares (million) | G11: ='Income Statement'!B51 -> 480.66263 | H11: =G11 -> 480.66263 | I11: =H11 -> 480.66263
B12: Sysco (SYY) | C12: ='Income Statement'!A2/'Income Statement'!B50 -> 19.181324 | D12: =#REF! -> #REF! | E12: =#REF! -> #REF! | F12: Value per share | G12: =G10/G11 -> 119.15197 | H12: =H10/H11 -> 87.948173 | I12: =I10/I11 -> 113.70863

Sheet Sales Charts
C2: Fiscal Year Sales (in millions)
B3: Segment | C3: 2025 | D3: 2024 | E3: 2023
B4: United States | C4: 66073 | D4: 63931 | E4: 62404
B5: Canada | C5: 6113 | D5: 5993 | E5: 5828
B6: United Kingdom | C6: 4081 | D6: 3760 | E6: 3340
B7: France | C7: 1714 | D7: 1712 | E7: 1591
B8: Other | C8: 3389 | D8: 3448 | E8: 3162
B9: Total | C9: =SUM(C4:C8) -> 81370 | D9: =SUM(D4:D8) -> 78844 | E9: =SUM(E4:E8) -> 76325
H10: FY 2028
B12: Segment | C12: 2025 Total Sales by Segment
B13: United States | C13: =C4/$C$9 -> 0.81200688
B14: Canada | C14: =C5/$C$9 -> 0.075125968
B15: United Kingdom | C15: =C6/$C$9 -> 0.050153619
B16: France | C16: =C7/$C$9 -> 0.021064274
B17: Other | C17: =C8/$C$9 -> 0.041649256

Sheet All financial statements 21-25
A1: Sysco Corporation (SYY)
A2: $71.16
A4: Sysco Corporation
A5: SYY 871829107 2868165 NYSE Common stock
A6: Source: FactSet Fundamentals
A7: INCOME STATEMENT
B8: JUN '21 | C8: JUN '22 | D8: JUN '23 | E8: JUN '24 | F8: JUN '25
A10: Sales | B10: 51297.843 | C10: 68636.146 | D10: 76324.675 | E10: 78844 | F10: 81370
A11: Cost of Goods Sold (COGS) incl. D&A | B11: 42573.402 | C11: 56421.622 | D11: 62474.678 | E11: 65092 | F11: 67332
A12: COGS excluding D&A | B12: 41720.996 | C12: 55539.97 | D12: 61585.505 | E12: 64098 | F12: 66246
A13: Depreciation & Amortization Expense | B13: 852.406 | C13: 881.652 | D13: 889.173 | E13: 994 | F13: 1086
A14: Depreciation | B14: 748.906 | C14: 748.752 | D14: 762.873 | E14: 852 | F14: 939
A15: Amortization of Intangibles | B15: 103.5 | C15: 132.9 | D15: 126.3 | E15: 142 | F15: 147
A16: Gross Income | B16: 8724.441 | C16: 12214.524 | D16: 13849.997 | E16: 13752 | F16: 14038
A17: SG&A Expense | B17: 7133.31 | C17: 9784.725 | D17: 10708.566 | E17: 10270 | F17: 10526
A18: Other SG&A | B18: 7133.31 | C18: 9784.725 | D18: 10708.566 | E18: 10270 | F18: 10526
A19: EBIT (Operating Income) | B19: 1591.131 | C19: 2429.799 | D19: 3141.431 | E19: 3482 | F19: 3512
A20: Nonoperating Income - Net | B20: -4.29 | C20: 71.821 | D20: -267.023 | E20: -42 | F20: -33
A21: Other Income (Expense) | B21: -4.29 | C21: 71.821 | D21: -267.023 | E21: -42 | F21: -33
... A24: Unusual Expense - Net | B24: 497.074 | C24: 284.583 | D24: 88.753 | E24: 297 | F24: 476
A25: Impairments | B25: 0 | F25: 92
A26: Goodwill | B26: 0 | C26: 0 | D26: 0 | E26: 0 | F26: 92
A27: Restructuring Expense | B27: 133.727 | C27: 142.705 | D27: 73.854 | E27: 279 | F27: 343
A28: Unrealized Valuation Gain/Loss | B28: -69.45 | C28: -26.275 | D28: -14.899 | E28: -18 | F28: -41
A29: Hedges/Derivatives | B29: -69.45 | C29: -26.275 | D29: -14.899 | E29: -18 | F29: -41
A30: Excpl Chrgs - Others | B30: 293.897 | C30: 115.603 | D30: 0
A31: Restructuring of Debt | B31: 293.897 | C31: 115.603 | D31: 0
A32: Pretax Income | B32: 584.728 | C32: 1746.773 | D32: 2285.355 | E32: 2565 | F32: 2415
A33: EFFECTIVE TAX RATE | B33: =B34/B32 -> 0.1034994 | C33: =C34/C32 -> 0.22212674 | D33: =D34/D32 -> 0.225449 | E33: =E34/E32 -> 0.23781676 | F33: =F34/F32 -> 0.24306418
A34: Income Taxes | B34: 60.519 | C34: 388.005 | D34: 515.231 | E34: 610 | F34: 587
A35: Income Taxes - Current Domestic | B35: 218.383 | C35: 452.459 | D35: 531.665 | E35: 584 | F35: 602
A36: Income Taxes - Deferred Domestic | B36: -157.864 | C36: -64.454 | D36: -16.434 | E36: 26 | F36: -15
A37: Consolidated Net Income | B37: 524.209 | C37: 1358.768 | D37: 1770.124 | E37: 1955 | F37: 1828
A38: Net Income | B38: 524.209 | C38: 1358.768 | D38: 1770.124 | E38: 1955 | F38: 1828
A39: Net Income available to Common | B39: 524.209 | C39: 1358.768 | D39: 1770.124 | E39: 1955 | F39: 1828
A40: Per Share
A41: EPS (recurring) | B41: 1.698281 | C41: 3.031048 | D41: 3.594624 | E41: 4.299179 | F41: 4.412182
A42: EPS (basic) | B42: 1.0265 | C42: 2.661 | D42: 3.4889 | E42: 3.9003 | F42: 3.7448
A43: Basic Shares Outstanding | B43: 510.6964 | C43: 510.63065 | D43: 507.36291 | E43: 501.23842 | F43: 488.14433
A44: Total Shares Outstanding | B44: 511.35789 | C44: 508.64336 | D44: 505.11207 | E44: 491.75822 | F44: 477.49624
A45: EPS (diluted) | B45: 1.0208 | C45: 2.6435 | D45: 3.4727 | E45: 3.8859 | F45: 3.7319
A46: Diluted Shares Outstanding | B46: 513.55509 | C46: 514.00583 | D46: 509.71976 | E46: 503.09609 | F46: 489.82565
A47: Total Shares Outstanding | B47: 511.35789 | C47: 508.64336 | D47: 505.11207 | E47: 491.75822 | F47: 477.49624
A48: Earnings Persistence | B48: 88.249 | C48: 81.757 | D48: 90.737 | E48: 84.371 | F48: 90.015
A49: Dividends per Share | B49: 1.82 | C49: 1.9 | D49: 1.97 | E49: 2.01 | F49: 2.07
A50: Payout Ratio | B50: 178.29154 | C50: 71.874409 | D50: 56.728194 | E50: 51.725469 | F50: 55.467724
A51: EBITDA
A52: EBITDA | B52: 2443.537 | C52: 3311.451 | D52: 4030.604 | E52: 4476 | F52: 4598
A53: EBIT | B53: 1591.131 | C53: 2429.799 | D53: 3141.431 | E53: 3482 | F53: 3512
A54: Depreciation & Amortization Expense | B54: 852.406 | C54: 881.652 | D54: 889.173 | E54: 994 | F54: 1086
A55: All figures in millions of U.S. Dollar except per share items.
A57: BALANCE SHEET
B58: JUN '21 | C58: JUN '22 | D58: JUN '23 | E58: JUN '24 | F58: JUN '25
A59: Assets
A60: Cash & Short-Term Investments | B60: 3007.123 | C60: 867.086 | D60: 745.201 | E60: 696 | F60: 1071
A61: Cash Only | B61: 3007.123 | C61: 867.086 | D61: 745.201 | E61: 696 | F61: 1071
A62: Short-Term Receivables | B62: 3790.269 | C62: 4874.846 | D62: 5097.785 | E62: 5346 | F62: 5506
A63: Accounts Receivables, Net | B63: 3781.51 | C63: 4838.912 | D63: 5091.97 | E63: 5324 | F63: 5502
A64: Accounts Receivables, Gross | B64: 3899.205 | C64: 4909.702 | D64: 5137.569 | E64: 5378 | F64: 5519
A65: Bad Debt/Doubtful Accounts | B65: -117.695 | C65: -70.79 | D65: -45.599 | E65: -54 | F65: -17
A66: Other Receivables | B66: 8.759 | C66: 35.934 | D66: 5.815 | E66: 22 | F66: 4
A67: Inventories | B67: 3695.219 | C67: 4437.498 | D67: 4480.812 | E67: 4678 | F67: 5053
A68: Finished Goods | B68: 3695.219 | C68: 4437.498 | D68: 4480.812 | E68: 4678 | F68: 5053
A69: Other Current Assets | B69: 240.956 | C69: 303.789 | D69: 284.566 | E69: 323 | F69: 338
A70: Miscellaneous Current Assets | B70: 240.956 | C70: 303.789 | D70: 284.566 | E70: 323 | F70: 338
A71: Total Current Assets | B71: 10733.567 | C71: 10483.219 | D71: 10608.364 | E71: 11043 | F71: 11968
... A86: Other Assets | B86: 528.817 | C86: 485.86 | D86: 419.299 | E86: 412 | F86: 420
A87: Deferred Charges | B87: 124.453
A88: Tangible Other Assets | B88: 404.364 | C88: 485.86 | D88: 419.299 | E88: 412 | F88: 420
A89: Total Assets | B89: 21413.539 | C89: 22085.688 | D89: 22821.145 | E89: 24917 | F89: 26774
A90: Liabilities & Shareholders' Equity
A91: Current
A92: ST Debt & Curr. Portion LT Debt | B92: 597.582 | C92: 686.301 | D92: 161.601 | E92: 594 | F92: 1085
A93: Accounts Payable | B93: 4884.781 | C93: 5752.958 | D93: 6025.757 | E93: 6290 | F93: 6512
A94: Income Tax Payable | B94: 22.644 | C94: 40.042 | D94: 101.894 | E94: 131 | F94: 51
A95: Other Current Liabilities | B95: 1814.837 | C95: 2270.753 | D95: 2251.181 | E95: 2226 | F95: 2268
A96: Miscellaneous Current Liabilities | B96: 1814.837 | C96: 2270.753 | D96: 2251.181 | E96: 2226 | F96: 2268
A97: Total Current Liabilities | B97: 7319.844 | C97: 8750.054 | D97: 8540.433 | E97: 9241 | F97: 9916
A98: Long-Term
A99: Long-Term Debt | B99: 11222.665 | C99: 10703.348 | D99: 11004.266 | E99: 12351 | F99: 13409
A100: Long-Term Debt excl Lease Obligations | B100: 10536.902 | C100: 9879.706 | D100: 10088.11 | E100: 11206 | F100: 11973
A101: Capital and Operating Lease Obligations | B101: 685.763 | C101: 823.642 | D101: 916.156 | E101: 1145 | F101: 1436
A102: Provision for Risks & Charges | B102: 552.311 | C102: 400.826 | D102: 415.155 | E102: 498 | F102: 509
A103: Deferred Tax Liabilities | B103: 147.066 | C103: 250.171 | D103: 302.904 | E103: 345 | F103: 345
A104: Other Liabilities | B104: 584.169 | C104: 567.081 | D104: 516.553 | E104: 591 | F104: 738
A105: Other Liabilities (excl. Deferred Income) | B105: 584.169 | C105: 567.081 | D105: 516.553 | E105: 591 | F105: 738
A106: Total Liabilities | B106: 19826.055 | C106: 20671.48 | D106: 20779.311 | E106: 23026 | F106: 24917
A107: Equity
A108: Common Equity | B108: 1552.896 | C108: 1382.26 | D108: 2008.622 | E108: 1860 | F108: 1830
A109: Common Stock Par/Carry Value | B109: 765.175 | C109: 765.175 | D109: 765.175 | E109: 765 | F109: 765
A110: Additional Paid-In Capital/Capital Surplus | B110: 1619.995 | C110: 1766.305 | D110: 1814.681 | E110: 1908 | F110: 1986
A111: Retained Earnings | B111: 10151.706 | C111: 10539.722 | D111: 11310.664 | E111: 12260 | F111: 13061
A112: Cumulative Translation Adjustment/Unrealized For. Exch. Gain | B112: -40.092 | C112: -501.517 | D112: -374.29 | E112: -407 | F112: -120
A113: Unrealized Gain/Loss Marketable Securities | B113: 4.415 | C113: -4.972 | D113: -6.793 | E113: -5 | F113: -1
A114: Other Appropriated Reserves | B114: -1113.087 | C114: -975.565 | D114: -871.507 | E114: -927 | F114: -977
A115: Treasury Stock | B115: -9835.216 | C115: -10206.888 | D115: -10629.308 | E115: -11734 | F115: -12884
A116: Total Shareholders' Equity | B116: 1552.896 | C116: 1382.26 | D116: 2008.622 | E116: 1860 | F116: 1830
A117: Accumulated Minority Interest | B117: 34.588 | C117: 31.948 | D117: 33.212 | E117: 31 | F117: 27
A118: Total Equity | B118: 1587.484 | C118: 1414.208 | D118: 2041.834 | E118: 1891 | F118: 1857
A119: Total Liabilities & Shareholders' Equity | B119: 21413.539 | C119: 22085.688 | D119: 22821.145 | E119: 24917 | F119: 26774
...

Sheet Statement of Cash Flows
A1: Sysco Corporation (SYY)
A2: 71.38
A5: Sysco Corporation
A6: SYY 871829107 2868165 NYSE Common stock
A7: Source: FactSet Fundamentals
B8: DEC '25 | C8: JUN '25 | D8: JUN '24 | E8: JUN '23 | F8: JUN '22 | G8: JUN '21 | H8: JUN '20 | I8: JUN '19 | J8: JUN '18 | K8: JUN '17 | L8: JUN '16 | M8: JUN '15 | N8: JUN '14 | O8: JUN '13 | P8: JUN '12 | Q8: JUN '11 | R8: JUN '10 | S8: JUN '09 | T8: JUN '08 | U8: JUN '07 | V8: JUN '06 | W8: JUN '05 | X8: JUN '04 | Y8: JUN '03 | Z8: JUN '02 | AA8: JUN '01 | AB8: JUN '00 | AC8: JUN '99 | AD8: JUN '98 | AE8: JUN '97 | AF8: JUN '96
B9: LTM
J10: Restate | K10: Restate
A11: Operating Activities
A12: Net Income / Starting Line | B12: 1798 | C12: 1828 | D12: 1955 | E12: 1770.1 | F12: 1358.8 | G12: 524.2 | H12: 215.5 | I12: 1674.3 | J12: 1430.8 | K12: 1142.5 | L12: 949.6 | M12: 686.8 | N12: 931.5 | O12: 992.4 | P12: 1121.6 | Q12: 1152 | R12: 1180 | S12: 1055.9 | T12: 1106.2 | U12: 1001.1 | V12: 855.3 | W12: 961.5 | X12: 907.2 | Y12: 778.3 | Z12: 679.8 | AA12: 596.9 | AB12: 453.6 | AC12: 362.3 | AD12: 324.8 | AE12: 302.5 | AF12: 276.9
A13: Depreciation, Depletion & Amortization | B13: 1092 | C13: 1086 | D13: 997 | E13: 888.7 | F13: 880.9 | G13: 851.8 | H13: 914.1 | I13: 763.9 | J13: 765.5 | K13: 902 | L13: 662.7 | M13: 553 | N13: 556.1 | O13: 512.5 | P13: 416.9 | Q13: 402.6 | R13: 390 | S13: 382.3 | T13: 372.5 | U13: 362.6 | V13: 345.1 | W13: 316.7 | X13: 283.6 | Y13: 273.1 | Z13: 278.3 | AA13: 248.2 | AB13: 220.7 | AC13: 205 | AD13: 181.2 | AE13: 160.3 | AF13: 144.7
A14: Depreciation and Depletion | X14: 273 | Y14: 273.1 | Z14: 278.3 | AA14: 248.2 | AB14: 220.7 | AC14: 205 | AD14: 181.2 | AE14: 160.3 | AF14: 144.7
A15: Amortization of Intangible Assets | X15: 10.6 | AF15: 0
A16: Deferred Taxes & Investment Tax Credit | B16: -4 | C16: -13 | D16: 27 | E16: -16.4 | F16: -64.5 | G16: -157.9 | H16: -191.3 | I16: -126.7 | J16: 187.9 | K16: -51.8 | L16: 93.9 | M16: -4.7 | N16: -30.7 | O16: -28.1 | P16: -177.9 | Q16: -165.2 | R16: -121.9 | S16: -294.2 | T16: 643.5 | U16: 546 | V16: 482.1 | W16: 554.9 | X16: 608.2 | Y16: 481.3 | Z16: 263.5 | AA16: 6.2 | AB16: -25.5 | AC16: 5.7 | AD16: -15.1 | AE16: 11.1 | AF16: 16.1
A17: Deferred Taxes | B17: -4 | C17: -13 | D17: 27 | E17: -16.4 | F17: -64.5 | G17: -157.9 | H17: -191.3 | I17: -126.7 | J17: 187.9 | K17: -51.8 | L17: 93.9 | M17: -4.7 | N17: -30.7 | O17: -28.1 | P17: -177.9 | Q17: -165.2 | R17: -121.9 | S17: -294.2 | T17: 643.5 | U17: 546 | V17: 482.1 | W17: 554.9 | X17: 608.2 | Y17: 481.3 | Z17: 263.5 | AA17: 6.2 | AB17: -25.5 | AC17: 5.7 | AD17: -15.1 | AE17: 11.1 | AF17: 16.1
A18: Other Funds | B18: 229 | C18: 185 | D18: 168 | E18: 459.8 | F18: 232 | G18: 269.3 | H18: 727.7 | I18: 119.8 | J18: 200.9 | K18: 143.1 | L18: 356 | M18: 95.5 | N18: 111.6 | O18: 107.9 | P18: 102.7 | Q18: 92.4 | R18: 103.8 | S18: 127.1 | T18: 110.1 | U18: 119.9 | V18: 137.4 | W18: 18.6 | X18: 27.4 | Y18: 27.1 | Z18: 25.9 | AA18: 21.7 | AB18: 27.1 | AC18: 26.2 | AD18: 23 | AE18: 21.6 | AF18: 1.9
A19: Funds from Operations | B19: 3115 | C19: 3086 | D19: 3147 | E19: 3102.1 | F19: 2407.3 | G19: 1487.5 | H19: 1666 | I19: 2431.2 | J19: 2585 | K19: 2135.8 | L19: 2062.2 | M19: 1330.6 | N19: 1568.6 | O19: 1584.7 | P19: 1463.3 | Q19: 1481.8 | R19: 1551.9 | S19: 1271.2 | T19: 2232.2 | U19: 2029.5 | V19: 1819.9 | W19: 1851.6 | X19: 1826.3 | Y19: 1559.9 | Z19: 1247.4 | AA19: 873.1 | AB19: 675.8 | AC19: 599.1 | AD19: 513.9 | AE19: 495.5 | AF19: 439.6
A20: Changes in Working Capital | B20: -492 | C20: -576 | D20: -158 | E20: -234.5 | F20: -616 | G20: 416.4 | H20: -47.3 | I20: -20 | J20: -429.6 | K20: 103.6 | L20: -129.1 | M20: 224.9 | N20: -75.7 | O20: -73.1 | P20: -59.2 | Q20: -390.3 | R20: -666.5 | S20: 311.1 | T20: -636.1 | U20: -626.5 | V20: -696.1 | W20: -659.8 | X20: -636.8 | Y20: -187.1 | Z20: -162.5 | AA20: 82.1 | AB20: 32.9 | AC20: -13.8 | AD20: -156.2 | AE20: 2.6 | AF20: -89.2
A21: Receivables | B21: -224 | C21: -206 | D21: -110 | E21: -270.6 | F21: -971.2 | G21: -662.3 | H21: 915.7 | I21: -203.5 | J21: -37.5 | K21: 20.5 | L21: -27.3 | M21: -11.7 | N21: -236.3 | O21: -193.8 | P21: -106.8 | Q21: -252.6 | R21: -166.4 | S21: 188.7 | T21: -128 | U21: -134.2 | V21: -162.6 | W21: -72.8 | X21: -177.1 | Y21: -218.2 | Z21: -32.4 | AA21: -83.9 | AB21: -118.6 | AC21: -145 | AD21: -162.3 | AE21: -40.2 | AF21: -123.7
A22: Inventories | B22: -124 | C22: -330 | D22: -70 | E22: -22.2 | F22: -708.6 | G22: -551.4 | H22: 114.6 | I22: -114.7 | J22: -89.7 | K22: -113.6 | L22: 66.9 | M22: -125.2 | N22: -195.8 | O22: -180.3 | P22: -99.2 | Q22: -254.7 | R22: -106.2 | S22: 177.6 | T22: -110.9 | U22: -95.9 | V22: -119.4 | W22: -35 | X22: -162.5 | Y22: -70 | Z22: -17.8 | AA22: -54.1 | AB22: -56.9 | AC22: -61.5 | AD22: -48.5 | AE22: -6.9 | AF22: -56.1
A23: Accounts Payable | B23: 99 | C23: 143 | D23: 104 | E23: 195.6 | F23: 810.5 | G23: 1459.2 | H23: -834.1 | I23: 246.4 | J23: 76.9 | K23: 322.8 | L23: 23.9 | M23: 72.5 | N23: 392.7 | O23: 207.2 | P23: 30.3 | Q23: 187.4 | R23: 154.8 | S23: -192.7 | T23: 54.5 | U23: 85.4 | V23: 49.8 | W23: 28.1 | X23: 95.9 | Y23: 237.4 | Z23: -0.4 | AA23: 33.4 | AB23: 105.8 | AC23: 164.1 | AD23: 14.1 | AE23: 43.1 | AF23: 70.7
A24: Income Taxes Payable | B24: -94 | C24: -62 | D24: 13 | E24: 92 | F24: -9.8 | G24: 119 | H24: -102.7 | I24: 4.9 | J24: -10.7 | K24: -74.6 | L24: 231.5 | M24: -32.8 | N24: -18.7 | O24: -38 | P24: 71.3 | Q24: -44.2 | R24: -296.5 | S24: 325.5 | T24: -509.8 | U24: -492 | V24: -545.6 | W24: -438.8 | X24: -392.2 | Y24: -33.1 | Z24: -81.7 | AA24: 106 | AB24: 16.3 | AC24: -19.4 | AD24: 7.8 | AE24: -5.6 | AF24: 13
A25: Other Accruals | B25: 42 | C25: -14 | D25: -12 | E25: 22.4 | F25: 423.4 | G25: 167.2 | H25: -139.9 | I25: 137.5 | J25: 47.1 | K25: -4.5 | L25: -178.3 | M25: 464.4 | N25: 55.8 | O25: 76.5 | P25: 41.4 | Q25: -43.3 | R25: 58 | S25: -120.3 | T25: -22.7 | U25: 132.9 | V25: 29.2 | W25: -32.7 | X25: 26.5 | Y25: -85.3 | Z25: -23.4 | AA25: 86.6 | AB25: 128.2 | AC25: 82 | AD25: 50.9 | AE25: 27.5 | AF25: 6.6
A26: Other Assets/Liabilities | B26: -191 | C26: -107 | D26: -83 | E26: -251.6 | F26: -160.3 | G26: -115.3 | H26: -0.9 | I26: -90.8 | J26: -415.8 | K26: -46.9 | L26: -245.8 | M26: -142.2 | N26: -73.5 | O26: 55.2 | P26: 3.9 | Q26: 17.3 | R26: -310.2 | S26: -67.7 | T26: 80.9 | U26: -122.8 | V26: 52.6 | W26: -108.6 | X26: -27.4 | Y26: -17.9 | Z26: -6.8 | AA26: -5.8 | AB26: -41.8 | AC26: -34.1 | AD26: -18.2 | AE26: -15.3 | AF26: 0.2
A27: Net Operating Cash Flow | B27: 2623 | C27: 2510 | D27: 2989 | E27: 2867.6 | F27: 1791.3 | G27: 1903.8 | H27: 1618.7 | I27: 2411.2 | J27: 2155.4 | K27: 2239.4 | L27: 1933.1 | M27: 1555.5 | N27: 1492.8 | O27: 1511.6 | P27: 1404.2 | Q27: 1091.5 | R27: 885.4 | S27: 1582.3 | T27: 1596.1 | U27: 1402.9 | V27: 1123.8 | W27: 1191.8 | X27: 1189.5 | Y27: 1372.8 | Z27: 1085 | AA27: 955.2 | AB27: 708.7 | AC27: 585.3 | AD27: 357.8 | AE27: 498.1 | AF27: 350.4
A28: Investing Activities
A29: Capital Expenditures | B29: -873 | C29: -906 | D29: -832 | E29: -793.3 | F29: -632.8 | G29: -470.7 | H29: -720.4 | I29: -692.4 | J29: -687.8 | K29: -686.4 | L29: -527.3 | M29: -542.8 | N29: -523.2 | O29: -511.9 | P29: -784.5 | Q29: -636.4 | R29: -594.6 | S29: -464.6 | T29: -516 | U29: -603.2 | V29: -514.8 | W29: -390.2 | X29: -530.1 | Y29: -435.6 | Z29: -416.4 | AA29: -341.1 | AB29: -266.4 | AC29: -286.7 | AD29: -259.4 | AE29: -210.9 | AF29: -235.9
A30: Capital Expenditures (Fixed Assets) | B30: -873 | C30: -906 | D30: -832 | E30: -793.3 | F30: -632.8 | G30: -470.7 | H30: -720.4 | I30: -692.4 | J30: -687.8 | K30: -686.4 | L30: -527.3 | M30: -542.8 | N30: -523.2 | O30: -511.9 | P30: -784.5 | Q30: -636.4 | R30: -594.6 | S30: -464.6 | T30: -516 | U30: -603.2 | V30: -514.8 | W30: -390.2 | X30: -530.1 | Y30: -435.6 | Z30: -416.4 | AA30: -341.1 | AB30: -266.4 | AC30: -286.7 | AD30: -259.4 | AE30: -210.9 | AF30: -235.9
A31: Net Assets from Acquisitions | B31: -133 | C31: -40 | D31: -1210 | E31: -37.4 | F31: -1281.1 | G31: 0 | H31: -142.8 | I31: -106.6 | J31: -248.1 | K31: -2921.8 | L31: -219.2 | M31: -115.9 | N31: -79.3 | O31: -397.4 | P31: -110.6 | Q31: -101.1 | R31: -29.3 | S31: -218.1 | T31: -55.3 | U31: -59.3 | V31: -114.4 | W31: -115.6 | X31: -79.2 | Y31: -209 | Z31: -234.6 | AA31: -10.4 | AB31: -211.9 | AC31: 0 | AD31: -84.5 | AE31: -5.3 | AF31: 0
A32: Sale of Fixed Assets & Businesses | B32: 150 | C32: 214 | D32: 79 | E32: 42.1 | F32: 24.1 | G32: 59.1 | H32: 28.7 | I32: 170.8 | J32: 22.3 | K32: 23.7 | L32: 23.5 | M32: 24.5 | N32: 25.8 | O32: 15.5 | P32: 8.2 | Q32: 19.1 | R32: 21.7 | S32: 25.2 | T32: 13.3 | U32: 16 | V32: 22.7 | W32: 25.5 | X32: 15.9 | Y32: 14.6 | Z32: 20.7 | AA32: 12.8 | AB32: 18.9 | AC32: 25 | AD32: 8.3 | AE32: 2.8 | AF32: 11
A33: Purchase/Sale of Investments | B33: 8 | C33: -3 | D33: -4 | E33: -4.6 | F33: -2.7 | G33: -17.2 | H33: 9.1 | I33: -116.4 | J33: 0 | K33: 0 | L33: 168.3 | M33: -20.1 | N33: -0.1 | O33: -18.1 | P33: -16.7 | Q33: 39 | R33: -54.1 | S33: -1.3 | T33: 2.3 | U33: -2.2 | V33: -2.2 | W33: 66.9 | X33: 0 | Y33: 0 | Z33: 0 | AA33: 0 | AB33: 0 | AC33: 0 | AD33: 0 | AE33: 0 | AF33: 0
A34: Purchase of Investments | B34: 16 | C34: 32 | D34: 33 | E34: 16.2 | F34: 19.3 | G34: 53.1 | H34: 11.4 | I34: 116.4 | J34: 0 | K34: 0 | L34: 0 | M34: 20.1 | N34: 0.1 | O34: 18.1 | P34: 16.7 | Q34: 0 | R34: 115.7 | S34: 1.3 | T34: 0 | U34: 2.2 | V34: 2.2 | W34: 0 | X34: 0 | Y34: 0 | Z34: 0 | AA34: 0 | AB34: 0 | AC34: 0 | AD34: 0 | AE34: 0 | AF34: 0
A35: Sale/Maturity of Investments | B35: 24 | C35: 29 | D35: 29 | E35: 11.6 | F35: 16.6 | G35: 36 | H35: 20.5 | I35: 0 | J35: 0 | K35: 0 | L35: 168.3 | M35: 0 | N35: 0 | O35: 0 | P35: 0 | Q35: 39 | R35: 61.6 | S35: 0 | T35: 2.3 | U35: 0 | V35: 0 | W35: 66.9 | X35: 0 | Y35: 0 | Z35: 0 | AA35: 0 | AB35: 0 | AC35: 0 | AD35: 0 | AE35: 0 | AF35: 0
A36: Other Funds | B36: 35 | C36: 18 | D36: 5 | E36: 8.5 | F36: 14.3 | G36: 0 | H36: 69.1 | I36: 1.8 | J36: 3.3 | K36: 0 | L36: -46 | M36: 0 | N36: 0 | O36: 0 | P36: 0 | Q36: 0 | R36: 0 | S36: 0 | T36: 0 | U36: 0 | V36: 0 | W36: 0 | X36: -90.3 | Y36: -51.8 | Z36: 0 | AA36: 0 | AB36: 0 | AC36: 0 | AD36: 0 | AE36: 0 | AF36: 0
A37: Other Uses | B37: 0 | C37: 0 | D37: 0 | E37: 0 | F37: 0 | G37: 0 | H37: 0 | I37: 0 | J37: 0 | K37: 0 | L37: -103.5 | M37: 0 | N37: 0 | O37: 0 | P37: 0 | Q37: 0 | R37: 0 | S37: 0 | T37: 0 | U37: 0 | V37: 0 | W37: 0 | X37: -90.3 | Y37: -51.8 | Z37: 0 | AA37: 0 | AB37: 0 | AC37: 0 | AD37: 0 | AE37: 0 | AF37: 0
A38: Other Sources | B38: 35 | C38: 18 | D38: 5 | E38: 8.5 | F38: 14.3 | G38: 0 | H38: 69.1 | I38: 1.8 | J38: 3.3 | K38: 0 | L38: 57.5 | M38: 0 | N38: 0 | O38: 0 | P38: 0 | Q38: 0 | R38: 0 | S38: 0 | T38: 0 | U38: 0 | V38: 0 | W38: 0 | X38: 0 | Y38: 0 | Z38: 0 | AA38: 0 | AB38: 0 | AC38: 0 | AD38: 0 | AE38: 0 | AF38: 0
A39: Net Investing Cash Flow | B39: -813 | C39: -717 | D39: -1962 | E39: -784.6 | F39: -1878.2 | G39: -428.7 | H39: -756.3 | I39: -742.9 | J39: -910.4 | K39: -3584.5 | L39: -600.8 | M39: -654.3 | N39: -576.8 | O39: -911.9 | P39: -903.6 | Q39: -679.6 | R39: -656.3 | S39: -658.7 | T39: -555.6 | U39: -648.7 | V39: -608.7 | W39: -413.4 | X39: -683.8 | Y39: -681.8 | Z39: -630.3 | AA39: -338.8 | AB39: -459.4 | AC39: -261.7 | AD39: -335.5 | AE39: -213.4 | AF39: -224.9
A40: Financing Activities
A41: Cash Dividends Paid | B41: -1015 | C41: -1000 | D41: -1008 | E41: -996 | F41: -958.9 | G41: -917.6 | H41: -856.3 | I41: -775.4 | J41: -722.2 | K41: -698.6 | L41: -698.9 | M41: -695.3 | N41: -667.2 | O41: -648.3 | P41: -622.9 | Q41: -597.1 | R41: -579.8 | S41: -548.2 | T41: -497.5 | U41: -445.4 | V41: -397.5 | W41: -357.3 | X41: -309.5 | Y41: -261.9 | Z41: -213.3 | AA41: -173.7 | AB41: -145.4 | AC41: -126.7 | AD41: -110.9 | AE41: -99.6 | AF41: -87.7
A42: Common Dividends | B42: -1015 | C42: -1000 | D42: -1008 | E42: -996 | F42: -958.9 | G42: -917.6 | H42: -856.3 | I42: -775.4 | J42: -722.2 | K42: -698.6 | L42: -698.9 | M42: -695.3 | N42: -667.2 | O42: -648.3 | P42: -622.9 | Q42: -597.1 | R42: -579.8 | S42: -548.2 | T42: -497.5 | U42: -445.4 | V42: -397.5 | W42: -357.3 | X42: -309.5 | Y42: -261.9 | Z42: -213.3 | AA42: -173.7 | AB42: -145.4 | AC42: -126.7 | AD42: -110.9 | AE42: -99.6 | AF42: -87.7
A43: Change in Capital Stock | B43: -847 | C43: -1140 | D43: -1112 | E43: -420.9 | F43: -371.7 | G43: 130.4 | H43: -617.1 | I43: -768.9 | J43: -710.2 | K43: -1681.3 | L43: -1667 | M43: 240.2 | N43: -76.8 | O43: -93 | P43: -172.9 | Q43: 41.1 | R43: -84.4 | S43: -327.1 | T43: -400.9 | U43: -329.1 | V43: -416.1 | W43: -389.7 | X43: -440.9 | Y43: -377.2 | Z43: -387.2 | AA43: -352.7 | AB43: -134 | AC43: -165.2 | AD43: -229.5 | AE43: -277.2 | AF43: -206.7
A44: Repurchase of Common & Preferred Stk. | B44: -950 | C44: -1250 | D44: -1232 | E44: -500.1 | F44: -499.8 | G44: 0 | H44: -844.7 | I44: -1022 | J44: -978.9 | K44: -1886.1 | L44: -1949.4 | M44: 0 | N44: -332.4 | O44: -721.6 | P44: -272.3 | Q44: -291.6 | R44: -179.2 | S44: -438.8 | T44: -529.2 | U44: -550.9 | V44: -544.1 | W44: -597.7 | X44: -608.5 | Y44: -478.5 | Z44: -473.6 | AA44: -428.2 | AB44: -186.3 | AC44: -204 | AD44: -263.4 | AE44: -305.3 | AF44: -232.1
A45: Sale of Common & Preferred Stock | B45: 103 | C45: 110 | D45: 120 | E45: 79.2 | F45: 128.2 | G45: 130.4 | H45: 227.6 | I45: 253.1 | J45: 268.8 | K45: 204.8 | L45: 282.5 | M45: 240.2 | N45: 255.6 | O45: 628.7 | P45: 99.4 | Q45: 332.7 | R45: 94.8 | S45: 111.8 | T45: 128.2 | U45: 221.7 | V45: 128.1 | W45: 208 | X45: 167.7 | Y45: 101.3 | Z45: 86.3 | AA45: 75.5 | AB45: 52.3 | AC45: 38.8 | AD45: 33.9 | AE45: 28.1 | AF45: 25.4
A46: Proceeds from Sale of Stock | B46: 0 | C46: 0 | D46: 0 | E46: 0 | F46: 0 | G46: 0 | H46: 0 | I46: 0 | J46: 0 | K46: 0 | L46: 0 | M46: 0 | N46: 255.6 | O46: 628.7 | P46: 99.4 | Q46: 332.7 | R46: 94.8 | S46: 111.8 | T46: 128.2 | U46: 221.7 | V46: 128.1 | W46: 208 | X46: 167.7 | Y46: 101.3 | Z46: 86.3 | AA46: 75.5 | AB46: 52.3 | AC46: 38.8 | AD46: 33.9 | AE46: 28.1 | AF46: 25.4
A47: Proceeds from Stock Options | B47: 103 | C47: 110 | D47: 120 | E47: 79.2 | F47: 128.2 | G47: 130.4 | H47: 227.6 | I47: 253.1 | J47: 268.8 | K47: 204.8 | L47: 282.5 | M47: 240.2 | N47: 0 | O47: 0 | P47: 0 | Q47: 0 | R47: 0 | S47: 0 | T47: 0 | U47: 0 | V47: 0 | W47: 0 | X47: 0 | AA47: 0 | AB47: 0 | AC47: 0 | AD47: 0 | AE47: 0 | AF47: 0
A48: Issuance/Reduction of Debt, Net | B48: 602 | C48: 750 | D48: 1115 | E48: -580.9 | F48: -642 | G48: -3827.8 | H48: 6281 | I48: -270 | J48: 47.1 | K48: 729.9 | L48: -81.8 | M48: 4526 | N48: -180.4 | O48: -137.5 | P48: 352.3 | Q48: 177.6 | R48: -3.6 | S48: 492.7 | T48: 195.4 | U48: 17.5 | V48: 323.6 | W48: -42.6 | X48: 107.2 | Y48: 73.1 | Z48: 240.5 | AA48: -113.5 | AB48: 39.9 | AC48: 7.3 | AD48: 310.8 | AE48: 101.9 | AF48: 142.7
A49: Change in Current Debt | B49: 637 | C49: 45 | D49: 200 | E49: 0 | F49: 0 | G49: -826.2 | H49: 616.7 | I49: 132.1 | J49: -119.7 | K49: 119.7 | L49: 0 | M49: -130 | N49: 34.5 | O49: 95.5 | P49: -182 | Q49: 182 | R49: 0 | S49: 0 | T49: -550.7 | U49: 121.9 | V49: 240 | W49: -9.8 | X49: 0 | Y49: 0 | Z49: 0 | AA49: 0 | AB49: 0 | AC49: 0 | AD49: 0 | AE49: 0 | AF49: 0
A50: Change in Long-Term Debt | B50: -35 | C50: 705 | D50: 915 | E50: -580.9 | F50: -642 | G50: -3001.6 | H50: 5664.3 | I50: -402.1 | J50: 166.8 | K50: 610.2 | L50: -81.8 | M50: 4656 | N50: -214.9 | O50: -233 | P50: 534.3 | Q50: -4.3 | R50: -3.6 | S50: 492.7 | T50: 746.2 | U50: -104.4 | V50: 83.6 | W50: -32.8 | X50: 107.2 | Y50: 73.1 | Z50: 240.5 | AA50: -113.5 | AB50: 39.9 | AC50: 7.3 | AD50: 310.8 | AE50: 101.9 | AF50: 142.7
A51: Issuance of Long-Term Debt | B51: 1253 | C51: 1254 | D51: 1362 | E51: 249 | F51: 1248.2 | G51: 1.5 | H51: 6783.6 | I51: 388.2 | J51: 1000.6 | K51: 753.8 | L51: 5095 | M51: 5010.1 | N51: 14.7 | O51: 61.5 | P51: 740 | Q51: 4.4 | R51: 7.1 | S51: 502.9 | T51: 753.8 | U51: 5.3 | V51: 497 | W51: 0 | X51: 185.1 | Y51: 85.2 | Z51: 384.1 | AA51: 0 | AB51: 51.8 | AC51: 117.3 | AD51: 310.8 | AE51: 101.9 | AF51: 146.8
A52: Reduction in Long-Term Debt | B52: -1288 | C52: -549 | D52: -447 | E52: -829.8 | F52: -1890.3 | G52: -3003.1 | H52: -1119.2 | I52: -790.3 | J52: -833.8 | K52: -143.7 | L52: -5176.8 | M52: -354 | N52: -229.5 | O52: -294.5 | P52: -205.6 | Q52: -8.7 | R52: -10.7 | S52: -10.2 | T52: -7.6 | U52: -109.7 | V52: -413.4 | W52: -32.8 | X52: -77.8 | Y52: -12.1 | Z52: -143.6 | AA52: -113.5 | AB52: -11.9 | AC52: -110 | AD52: 0 | AE52: 0 | AF52: -4.1
A53: Other Funds | B53: -49 | C53: -22 | D53: -33 | E53: -58.2 | F53: -14.3 | G53: -13.2 | H53: -87.8 | I53: -23 | J53: -25.3 | K53: -32.5 | L53: 42.9 | M53: -173.4 | N53: 8.5 | O53: 4.6 | P53: 0.7 | Q53: 0.4 | R53: 0.8 | S53: 2.9 | T53: 4.4 | U53: 8.8 | V53: -14.6 | W53: 5.3 | X53: 1.3 | Y53: 15.4 | Z53: 0 | AA53: 0 | AB53: 0 | AC53: 0 | AD53: 0 | AE53: 0 | AF53: 0
A54: Other Uses | B54: -49 | C54: -22 | D54: -33 | E54: -58.2 | F54: -37.4 | G54: -13.2 | H54: -87.8 | I54: -23 | J54: -25.3 | K54: -32.5 | L54: -6.1 | M54: -188.8 | N54: 0 | O54: 0 | P54: 0 | Q54: 0 | R54: 0 | S54: 0 | T54: 0 | U54: 0 | V54: -21.2 | W54: 0 | X54: 0 | Y54: 0 | Z54: 0 | AA54: 0 | AB54: 0 | AC54: 0 | AD54: 0 | AE54: 0 | AF54: 0
A55: Other Sources | B55: 0 | C55: 0 | D55: 0 | E55: 0 | F55: 23.1 | G55: 0 | H55: 0 | I55: 0 | J55: 0 | K55: 0 | L55: 49 | M55: 15.5 | N55: 8.5 | O55: 4.6 | P55: 0.7 | Q55: 0.4 | R55: 0.8 | S55: 2.9 | T55: 4.4 | U55: 8.8 | V55: 6.6 | W55: 5.3 | X55: 1.3 | Y55: 15.4 | Z55: 0 | AA55: 0 | AB55: 0 | AC55: 0 | AD55: 0 | AE55: 0 | AF55: 0
A56: Net Financing Cash Flow | B56: -1309 | C56: -1412 | D56: -1038 | E56: -2056 | F56: -1986.9 | G56: -4628.2 | H56: 4719.8 | I56: -1837.3 | J56: -1410.5 | K56: -1682.6 | L56: -2404.7 | M56: 3897.6 | N56: -915.9 | O56: -874.2 | P56: -442.6 | Q56: -377.9 | R56: -667 | S56: -379.6 | T56: -698.6 | U56: -748.3 | V56: -504.6 | W56: -784.3 | X56: -641.9 | Y56: -550.5 | Z56: -360 | AA56: -639.9 | AB56: -239.5 | AC56: -284.6 | AD56: -29.6 | AE56: -274.8 | AF56: -151.7
A57: All Activities
A58: Exchange Rate Effect | B58: 42 | C58: 22 | D58: -10 | E58: 7.6 | F58: -31.9 | G58: 94.6 | H58: -18.8 | I58: -14.7 | J58: 11.8 | K58: -22.1 | L58: -138.3 | M58: -81.7 | N58: 0.6 | O58: -2.1 | P58: -8.8 | Q58: 20.3 | R58: 4.7 | S58: -8.5 | T58: 1.7 | U58: 0 | V58: -0.3 | W58: -2.2 | X58: -1.6 | Y58: -1.5
A59: Net Change in Cash | B59: 543 | C59: 403 | D59: -21 | E59: 34.7 | F59: -2105.7 | G59: -3058.5 | H59: 5563.3 | I59: -183.6 | J59: -153.7 | K59: -3049.8 | L59: -1210.7 | M59: 4717 | N59: 0.8 | O59: -276.6 | P59: 49.1 | Q59: 54.3 | R59: -433.2 | S59: 535.5 | T59: 343.7 | U59: 6 | V59: 10.2 | W59: -8 | X59: -137.7 | Y59: 139 | Z59: 94.7 | AA59: -23.4 | AB59: 9.8 | AC59: 39 | AD59: -7.4 | AE59: 9.9 | AF59: -26.1
A60: Free Cash Flow | B60: 1750 | C60: 1604 | D60: 2157 | E60: 2074.3 | F60: 1158.5 | G60: 1433.2 | H60: 898.3 | I60: 1718.8 | J60: 1467.6 | K60: 1553 | L60: 1405.8 | M60: 1012.7 | N60: 969.6 | O60: 999.7 | P60: 619.7 | Q60: 455.1 | R60: 290.8 | S60: 1117.8 | T60: 1080.2 | U60: 799.7 | V60: 609.1 | W60: 801.6 | X60: 659.4 | Y60: 937.2 | Z60: 668.6 | AA60: 614.1 | AB60: 442.3 | AC60: 298.6 | AD60: 98.4 | AE60: 287.2 | AF60: 114.5
A61: Free Cash Flow per Share | B61: 3.6 | C61: 3.3 | D61: 4.3 | E61: 4.1 | F61: 2.3 | G61: 2.8 | H61: 1.7 | I61: 3.3 | J61: 2.8 | K61: 2.8 | L61: 2.4 | M61: 1.7 | N61: 1.6 | O61: 1.7 | P61: 1.1 | Q61: 0.8 | R61: 0.5 | S61: 1.9 | T61: 1.8 | U61: 1.3 | V61: 1 | W61: 1.2 | X61: 1 | Y61: 1.4 | Z61: 1 | AA61: 0.9 | AB61: 0.7 | AC61: 0.4 | AD61: 0.1 | AE61: 0.4 | AF61: 0.2
A62: Free Cash Flow Yield (%) | B62: 4.9 | C62: 4.37 | D62: 6.01 | E62: 5.48 | F62: 2.61 | G62: 3.64 | H62: 3.34 | I62: 4.64 | J62: 4.06 | K62: 5.63 | L62: 4.8 | M62: 4.42 | N62: 4.34 | O62: 4.94 | P62: 3.53 | Q62: 2.46 | R62: 1.73 | S62: 8.16 | T62: 6.26 | U62: 3.87 | V62: 3.17 | W62: 3.39 | X62: 2.86 | Y62: 4.79 | Z62: 3.65 | AA62: 3.34 | AB62: 3.14 | AC62: 2.88 | AD62: 1.12 | AE62: 4.38 | AF62: 1.83
A63: All figures in millions of U.S. Dollar except per share items.

Sheet Income Statement
A1: Sysco Corporation (SYY)
A2: $71.32
A5: Sysco Corporation
A6: SYY 871829107 2868165 NYSE Common stock
A7: Source: FactSet Fundamentals
B8: DEC '25 | C8: JUN '25 | D8: JUN '24 | E8: JUN '23 | F8: JUN '22 | G8: JUN '21 | H8: JUN '20 | I8: JUN '19 | J8: JUN '18 | K8: JUN '17 | L8: JUN '16 | M8: JUN '15 | N8: JUN '14 | O8: JUN '13 | P8: JUN '12 | Q8: JUN '11 | R8: JUN '10 | S8: JUN '09 | T8: JUN '08 | U8: JUN '07 | V8: JUN '06 | W8: JUN '05 | X8: JUN '04 | Y8: JUN '03 | Z8: JUN '02 | AA8: JUN '01 | AB8: JUN '00 | AC8: JUN '99 | AD8: JUN '98 | AE8: JUN '97 | AF8: JUN '96
B9: LTM
J10: Restate | K10: Restate
A11: Sales | B11: 82646 | C11: 81370 | D11: 78844 | E11: 76324.675 | F11: 68636.146 | G11: 51297.843 | H11: 52893.31 | I11: 60113.922 | J11: 58727.324 | K11: 55371.139 | L11: 50366.919 | M11: 48680.752 | N11: 46516.712 | O11: 44411.233 | P11: 42380.939 | Q11: 39323.489 | R11: 37243.495 | S11: 36853.33 | T11: 37522.111 | U11: 35042.075 | V11: 32628.438 | W11: 30281.914 | X11: 29335.403 | Y11: 26140 | Z11: 23351 | AA11: 21785 | AB11: 19303.268 | AC11: 17422.815 | AD11: 15327.536 | AE11: 14454.589 | AF11: 13395.13
A12: Cost of Goods Sold (COGS) incl. D&A | B12: 67484 | C12: 67332 | D12: 65092 | E12: 62474.678 | F12: 56421.622 | G12: 42573.402 | H12: 43700.472 | I12: 49362.044 | J12: 48258.509 | K12: 45579.032 | L12: 41935.147 | M12: 40625.036 | N12: 38829.477 | O12: 37017.142 | P12: 35089.262 | Q12: 32376.341 | R12: 30497.709 | S12: 30178.061 | T12: 30679.823 | U12: 28284.603 | V12: 26337.107 | W12: 24498.2 | X12: 23661.514 | Y12: 20980.412 | Z12: 18722.251 | AA12: 17513 | AB12: 15649.551 | AC12: 14207.86 | AD12: 12499.636 | AE12: 11835.959 | AF12: 10983.796
A13: COGS excluding D&A | B13: 66394 | C13: 66246 | D13: 64098 | E13: 61585.505 | F13: 55539.97 | G13: 41720.996 | H13: 42791.596 | I13: 48613.144 | J13: 47529.009 | K13: 44700.732 | L13: 41289.147 | M13: 40089.236 | N13: 38293.477 | O13: 36511.542 | P13: 34679.462 | Q13: 31980.441 | R13: 30115.109 | S13: 29801.253 | T13: 30313.389 | U13: 27930.178 | V13: 26005.665 | W13: 24192.52 | X13: 23377.919 | Y13: 20707 | Z13: 18444 | AA13: 17265 | AB13: 15428.89 | AC13: 14002.855 | AD13: 12318.402 | AE13: 11675.667 | AF13: 10839.087
A14: Depreciation & Amortization Expense | B14: 1090 | C14: 1086 | D14: 994 | E14: 889.173 | F14: 881.652 | G14: 852.406 | H14: 908.876 | I14: 748.9 | J14: 729.5 | K14: 878.3 | L14: 646 | M14: 535.8 | N14: 536 | O14: 505.6 | P14: 409.8 | Q14: 395.9 | R14: 382.6 | S14: 376.808 | T14: 366.434 | U14: 354.425 | V14: 331.442 | W14: 305.68 | X14: 283.595 | Y14: 273.412 | Z14: 278.251 | AA14: 248 | AB14: 220.661 | AC14: 205.005 | AD14: 181.234 | AE14: 160.292 | AF14: 144.709
A15: Depreciation | C15: 939 | D15: 852 | E15: 762.873 | F15: 748.752 | G15: 748.906 | H15: 813.576 | I15: 656.6 | J15: 614.8 | K15: 765.4 | L15: 608.7 | M15: 495.8 | N15: 493.8 | O15: 473.5 | P15: 384.9 | Q15: 374 | R15: 361.7 | S15: 361.062 | T15: 352.569 | U15: 341.714 | V15: 320.669 | W15: 298.111 | X15: 273.03 | Y15: 263.48 | Z15: 243.498 | AA15: 236
A16: Amortization of Intangibles | C16: 147 | D16: 142 | E16: 126.3 | F16: 132.9 | G16: 103.5 | H16: 95.3 | I16: 92.3 | J16: 114.7 | K16: 112.9 | L16: 37.3 | M16: 40 | N16: 42.2 | O16: 32.1 | P16: 24.9 | Q16: 21.9 | R16: 20.9 | S16: 15.746 | T16: 13.865 | U16: 12.711 | V16: 10.773 | W16: 7.569 | X16: 10.565 | Y16: 9.932 | Z16: 34.753 | AA16: 12
A17: Gross Income | B17: 15162 | C17: 14038 | D17: 13752 | E17: 13849.997 | F17: 12214.524 | G17: 8724.441 | H17: 9192.838 | I17: 10751.878 | J17: 10468.815 | K17: 9792.107 | L17: 8431.772 | M17: 8055.716 | N17: 7687.235 | O17: 7394.091 | P17: 7291.677 | Q17: 6947.148 | R17: 6745.786 | S17: 6675.269 | T17: 6842.288 | U17: 6757.472 | V17: 6291.331 | W17: 5783.714 | X17: 5673.889 | Y17: 5159.588 | Z17: 4628.749 | AA17: 4272 | AB17: 3653.717 | AC17: 3214.955 | AD17: 2827.9 | AE17: 2618.63 | AF17: 2411.334
A18: SG&A Expense | B18: 11692 | C18: 10526 | D18: 10270 | E18: 10708.566 | F18: 9784.725 | G18: 7133.31 | H18: 7677.992 | I18: 8259.317 | J18: 8079.518 | K18: 7579.736 | L18: 6422.572 | M18: 6263.886 | N18: 5951.727 | O18: 5352.23 | P18: 5205.225 | Q18: 5015.646 | R18: 4769.918 | S18: 4803.058 | T18: 4962.339 | U18: 5048.99 | V18: 4796.301 | W18: 4194.184 | X18: 4141.23 | Y18: 3836 | Z18: 3468 | AA18: 3233 | AB18: 2843.755 | AD18: 2236.932 | AE18: 2076.335 | AF18: 1917.376
A19: Other SG&A | B19: 11692 | C19: 10526 | D19: 10270 | E19: 10708.566 | F19: 9784.725 | G19: 7133.31 | H19: 7677.992 | I19: 8259.317 | J19: 8079.518 | K19: 7579.736 | L19: 6422.572 | M19: 6263.886 | N19: 5951.727 | O19: 5352.23 | P19: 5205.225 | Q19: 5015.646 | R19: 4769.918 | S19: 4803.058 | T19: 4962.339 | U19: 5048.99 | V19: 4796.301 | W19: 4194.184 | X19: 4141.23 | Y19: 3836 | Z19: 3468 | AA19: 3233 | AB19: 2843.755 | AD19: 2236.932 | AE19: 2076.335 | AF19: 1917.376
A20: Other Operating Expense | B20: 0 | C20: 0 | D20: 0 | E20: 0 | F20: 0 | G20: 0 | H20: 0 | I20: 0 | J20: 0 | K20: 0 | L20: 0 | M20: 0 | N20: 0 | O20: 0 | P20: 0 | Q20: 0 | R20: 0 | S20: 0 | T20: 0 | U20: 0 | V20: 0 | W20: 0 | X20: 0 | Y20: -0.412 | Z20: -0.251 | AA20: 0 | AB20: 0 | AC20: 2547.266 | AD20: 0 | AE20: 0 | AF20: 0
A21: EBIT (Operating Income) | B21: 3470 | C21: 3512 | D21: 3482 | E21: 3141.431 | F21: 2429.799 | G21: 1591.131 | H21: 1514.846 | I21: 2492.561 | J21: 2389.297 | K21: 2212.371 | L21: 2009.2 | M21: 1791.83 | N21: 1735.508 | O21: 2041.861 | P21: 2086.452 | Q21: 1931.502 | R21: 1975.868 | S21: 1872.211 | T21: 1879.949 | U21: 1708.482 | V21: 1495.03 | W21: 1589.53 | X21: 1532.659 | Y21: 1324 | Z21: 1161 | AA21: 1039 | AB21: 809.962 | AC21: 667.689 | AD21: 590.968 | AE21: 542.295 | AF21: 493.958
A22: Nonoperating Income - Net | B22: -55 | C22: -33 | D22: -42 | E22: -267.023 | F22: 71.821 | G22: -4.29 | H22: -77.829 | I22: 33.306 | J22: 41.911 | K22: 4.442 | L22: -122.89 | M22: 25.287 | N22: 11.618 | O22: 17.472 | P22: 6.766 | Q22: 14.219 | R22: -0.802 | S22: 14.945 | T22: 22.93 | U22: 17.735 | V22: 9.016 | W22: 10.906 | X22: 12.365 | Y22: 8 | Z22: 3 | AA22: 0 | AB22: 11.478 | AC22: -0.963 | AD22: -0.053 | AE22: 0.162 | AF22: 1.004
A23: Other Income (Expense) | B23: -55 | C23: -33 | D23: -42 | E23: -267.023 | F23: 71.821 | G23: -4.29 | H23: -77.829 | I23: 33.306 | J23: 41.911 | K23: 4.442 | L23: -122.89 | M23: 25.287 | N23: 11.618 | O23: 17.472 | P23: 6.766 | Q23: 14.219 | R23: -0.802 | S23: 14.945 | T23: 22.93 | U23: 17.735 | V23: 9.016 | W23: 10.906 | X23: 12.365 | Y23: 8 | Z23: 3 | AA23: 0 | AB23: 11.478 | AC23: -0.963 | AD23: -0.053 | AE23: 0.162 | AF23: 1.004
A24: Interest Expense | B24: 583 | C24: 588 | D24: 578 | E24: 500.3 | F24: 470.264 | G24: 505.039 | H24: 339.958 | I24: 273.909 | J24: 314.026 | K24: 291.383 | L24: 220.176 | M24: 130.04 | N24: 133.995 | O24: 132.361 | P24: 120.604 | Q24: 127.293 | R24: 136.034 | S24: 116.322 | T24: 111.541 | U24: 105.002 | V24: 109.1 | W24: 75 | X24: 69.88 | Y24: 72 | Z24: 63 | AA24: 72 | AB24: 70.832 | AC24: 72.839 | AD24: 58.422 | AE24: 46.502 | AF24: 41.019
A25: Gross Interest Expense | B25: 583 | C25: 588 | D25: 578 | E25: 500.3 | F25: 470.264 | G25: 505.039 | H25: 339.958 | I25: 273.909 | J25: 314.026 | K25: 293.421 | L25: 222.208 | M25: 130.906 | N25: 135.092 | O25: 136.603 | P25: 141.404 | Q25: 141.193 | R25: 146.034 | S25: 119.853 | T25: 118.346 | U25: 108.957 | V25: 111.953 | W25: 79.316 | X25: 77.375 | Y25: 77 | Z25: 67 | AA25: 75 | AB25: 71.796 | AC25: 74.651 | AD25: 60.517 | AE25: 48.717 | AF25: 43.802
A26: Interest Capitalized | B26: 0 | C26: 0 | D26: 0 | E26: 0 | F26: 0 | G26: 0 | H26: 0 | I26: 0 | J26: 0 | K26: 2.038 | L26: 2.032 | M26: 0.866 | N26: 1.097 | O26: 4.242 | P26: 20.8 | Q26: 13.9 | R26: 10 | S26: 3.531 | T26: 6.805 | U26: 3.955 | V26: 2.853 | W26: 4.316 | X26: 7.495 | Y26: 5 | Z26: 4 | AA26: 3 | AB26: 0.964 | AC26: 1.812 | AD26: 2.095 | AE26: 2.215 | AF26: 2.783
A27: Unusual Expense - Net | B27: 482 | C27: 476 | D27: 297 | E27: 88.753 | F27: 284.583 | G27: 497.074 | H27: 803.675 | I27: 246.122 | J27: 160.958 | K27: 159.2 | L27: 233.127 | M27: 678.93 | N27: 137.507 | O27: 379.517 | P27: 188.612 | Q27: -9.026 | R27: -10.557 | S27: 0 | T27: 0 | U27: 0 | V27: 0 | W27: 0 | X27: 0 | Y27: 0 | Z27: 0 | AA27: 0 | AB27: 0
A28: Impairments | C28: 92 | G28: 0 | H28: 203.206
A29: Goodwill | B29: 92 | C29: 92 | D29: 0 | E29: 0 | F29: 0 | G29: 0 | H29: 203.206 | I29: 0 | J29: 0 | K29: 0 | L29: 0 | M29: 0 | N29: 0 | O29: 0 | P29: 0 | Q29: 0 | R29: 0 | S29: 0 | T29: 0 | U29: 0 | V29: 0 | W29: 0 | X29: 0 | Y29: 0 | Z29: 0 | AA29: 0 | AB29: 0
A30: Exceptional Provisions | H30: 323.403 | L30: 0 | M30: 0 | N30: 20 | S30: 0 | T30: 0 | U30: 0 | V30: 0 | W30: 0
A31: Restructuring Expense | B31: 321 | C31: 343 | D31: 279 | E31: 73.854 | F31: 142.705 | G31: 133.727 | H31: 220.3 | I31: 171.1 | J31: 91 | K31: 159.2 | L31: 158.7 | M31: 700.89 | N31: 104.545 | O31: 383.383 | P31: 199.541 | Q31: 0 | R31: 0 | S31: 0 | T31: 0 | U31: 0 | V31: 0 | W31: 0 | X31: 0 | Y31: 0 | Z31: 0 | AA31: 0 | AB31: 0 | AC31: 0 | AD31: 0 | AE31: 0 | AF31: 0
A32: Unrealized Valuation Gain/Loss | B32: -69 | C32: -41 | D32: -18 | E32: -14.899 | F32: -26.275 | G32: -69.45 | H32: -56.766 | I32: -75.022 | J32: -69.958 | K32: 0 | L32: 12.033 | M32: 21.96 | N32: 10.879 | O32: 3.866 | P32: 7.208 | Q32: 9.026 | R32: 10.557
A33: Hedges/Derivatives | B33: -69 | C33: -41 | D33: -18 | E33: -14.899 | F33: -26.275 | G33: -69.45 | H33: -56.766 | I33: -75.022 | J33: -69.958 | K33: 0 | L33: 12.033 | M33: 21.96 | N33: 10.879 | O33: 3.866 | P33: 7.208 | Q33: 9.026 | R33: 10.557
A34: Excpl Chrgs - Others | E34: 0 | F34: 115.603 | G34: 293.897 | L34: 86.46 | M34: 0 | N34: 23.841 | P34: -3.721
A35: Restructuring of Debt | E35: 0 | F35: 115.603 | G35: 293.897 | L35: 86.46
A36: Calamitous Events | M36: 0 | N36: 23.841 | P36: -3.721
A37: Pretax Income | B37: 2350 | C37: 2415 | D37: 2565 | E37: 2285.355 | F37: 1746.773 | G37: 584.728 | H37: 293.384 | I37: 2005.836 | J37: 1956.224 | K37: 1766.23 | L37: 1433.007 | M37: 1008.147 | N37: 1475.624 | O37: 1547.455 | P37: 1784.002 | Q37: 1827.454 | R37: 1849.589 | S37: 1770.834 | T37: 1791.338 | U37: 1621.215 | V37: 1394.946 | W37: 1525.436 | X37: 1475.144 | Y37: 1260 | Z37: 1101 | AA37: 967 | AB37: 737.608 | AC37: 593.887 | AD37: 532.493 | AE37: 495.955 | AF37: 453.943
A38: Income Taxes | B38: 553 | C38: 587 | D38: 610 | E38: 515.231 | F38: 388.005 | G38: 60.519 | H38: 77.909 | I38: 331.565 | J38: 525.458 | K38: 623.727 | L38: 483.385 | M38: 321.374 | N38: 544.091 | O38: 555.028 | P38: 662.417 | Q38: 675.424 | R38: 669.606 | S38: 714.886 | T38: 685.187 | U38: 620.139 | V38: 548.906 | W38: 563.979 | X38: 567.93 | Y38: 482 | Z38: 421 | AA38: 370 | AB38: 283.979 | AC38: 231.616 | AD38: 207.672 | AE38: 193.422 | AF38: 177.038
A39: Income Taxes - Current Domestic | C39: 602 | D39: 584 | E39: 531.665 | F39: 452.459 | G39: 218.383 | H39: 269.226 | I39: 458.284 | J39: 337.55 | K39: 675.573 | L39: 385.183 | M39: 327.639 | N39: 574.76 | O39: 582.889 | P39: 840.745 | Q39: 840.173 | R39: 791.12 | S39: 1010.595 | T39: 664.171 | U39: 539.997 | V39: 486.642 | W39: 485.499 | X39: 94.173 | Y39: 1 | Z39: 158 | AA39: 364 | AB39: 283.979 | AC39: 231.616 | AD39: 207.672 | AE39: 193.422 | AF39: 177.038
A40: Income Taxes - Current Foreign | C40: 0 | D40: 0 | E40: 0 | F40: 0 | G40: 0 | H40: 0 | I40: 0 | J40: 0 | K40: 0 | L40: 0 | M40: 0 | N40: 0 | O40: 0 | P40: 0 | Q40: 0 | R40: 0 | S40: 0 | T40: 21.016 | U40: 80.142 | V40: 62.264 | W40: 78.48 | X40: 0 | Y40: 0 | Z40: 0 | AA40: 0 | AB40: 0 | AC40: 0 | AD40: 0 | AE40: 0 | AF40: 0
A41: Income Taxes - Deferred Domestic | C41: -15 | D41: 26 | E41: -16.434 | F41: -64.454 | G41: -157.864 | H41: -191.317 | I41: -126.719 | J41: 187.908 | K41: -51.846 | L41: 98.202 | M41: -6.265 | N41: -30.669 | O41: -27.861 | P41: -178.328 | Q41: -164.749 | R41: -121.514 | S41: -295.709 | T41: 0 | U41: 0 | V41: 0 | W41: 0 | X41: 473.757 | Y41: 481 | Z41: 263 | AA41: 6
A42: Consolidated Net Income | B42: 1797 | C42: 1828 | D42: 1955 | E42: 1770.124 | F42: 1358.768 | G42: 524.209 | H42: 215.475 | I42: 1674.271 | J42: 1430.766 | K42: 1142.503 | L42: 949.622 | M42: 686.773 | N42: 931.533 | O42: 992.427 | P42: 1121.585 | Q42: 1152.03 | R42: 1179.983 | S42: 1055.948 | T42: 1106.151 | U42: 1001.076 | V42: 846.04 | W42: 961.457 | X42: 907.214 | Y42: 778 | Z42: 680 | AA42: 597 | AB42: 453.629 | AC42: 362.271 | AD42: 324.821 | AE42: 302.533 | AF42: 276.905
A43: Net Income | B43: 1797 | C43: 1828 | D43: 1955 | E43: 1770.124 | F43: 1358.768 | G43: 524.209 | H43: 215.475 | I43: 1674.271 | J43: 1430.766 | K43: 1142.503 | L43: 949.622 | M43: 686.773 | N43: 931.533 | O43: 992.427 | P43: 1121.585 | Q43: 1152.03 | R43: 1179.983 | S43: 1055.948 | T43: 1106.151 | U43: 1001.076 | V43: 846.04 | W43: 961.457 | X43: 907.214 | Y43: 778 | Z43: 680 | AA43: 597 | AB43: 453.629 | AC43: 362.271 | AD43: 324.821 | AE43: 302.533 | AF43: 276.905
A44: Net Income available to Common | B44: 1797 | C44: 1828 | D44: 1955 | E44: 1770.124 | F44: 1358.768 | G44: 524.209 | H44: 215.475 | I44: 1674.271 | J44: 1430.766 | K44: 1142.503 | L44: 949.622 | M44: 686.773 | N44: 931.533 | O44: 992.427 | P44: 1121.585 | Q44: 1152.03 | R44: 1179.983 | S44: 1055.948 | T44: 1106.151 | U44: 1001.076 | V44: 846.04 | W44: 961.457 | X44: 907.214 | Y44: 778 | Z44: 680 | AA44: 597 | AB44: 453.629 | AC44: 362.271 | AD44: 324.821 | AE44: 302.533 | AF44: 276.905
A45: Per Share
A46: EPS (recurring) | B46: 4.440537 | C46: 4.412182 | D46: 4.299179 | E46: 3.594624 | F46: 3.031048 | G46: 1.698281 | H46: 1.513635 | I46: 3.52813 | J46: 2.917154 | K46: 2.285944 | L46: 1.927308 | M46: 1.946931 | N46: 1.741375 | O46: 2.122729 | P46: 2.128407 | Q46: 1.946201 | R46: 1.975426 | S46: 1.771519 | T46: 1.810481 | U46: 1.598226 | V46: 1.345482 | W46: 1.472015 | X46: 1.370581 | Y46: 1.176052 | Z46: 1.009732 | AA46: 0.880597 | AB46: 0.677507 | AC46: 0.537819 | AD46: 0.472893 | AE46: 0.42674 | AF46: 0.379116
A47: EPS (basic) | B47: 3.7292 | C47: 3.7448 | D47: 3.9003 | E47: 3.4889 | F47: 2.661 | G47: 1.0265 | H47: 0.42 | I47: 3.24 | J47: 2.74 | K47: 2.1 | L47: 1.66 | M47: 1.16 | N47: 1.59 | O47: 1.68 | P47: 1.91 | Q47: 1.96 | R47: 1.99 | S47: 1.77 | T47: 1.83 | U47: 1.62 | V47: 1.36 | W47: 1.51 | X47: 1.41 | Y47: 1.2 | Z47: 1.03 | AA47: 0.9 | AB47: 0.34 | AC47: 0.6 | AD47: 0.5 | AE47: 0.4275 | AF47: 0.38
A48: Basic Shares Outstanding | B48: 479.3463 | C48: 488.14433 | D48: 501.23842 | E48: 507.36291 | F48: 510.63065 | G48: 510.6964 | H48: 510.12107 | I48: 516.89058 | J48: 522.92691 | K48: 543.49682 | L48: 573.05741 | M48: 592.07231 | N48: 585.98808 | O48: 589.39781 | P48: 587.72634 | Q48: 586.52614 | R48: 592.15722 | S48: 595.12758 | T48: 605.90554 | U48: 618.33275 | V48: 621.38277 | W48: 636.06827 | X48: 642.68861 | Y48: 650.60065 | Z48: 661.80843 | AA48: 665.55123 | AB48: 659.16495 | AC48: 665.82709 | AD48: 680.76095 | AE48: 708.94034 | AF48: 730.39559
A49: Total Shares Outstanding | B49: 478.9271 | C49: 477.49624 | D49: 491.75822 | E49: 505.11207 | F49: 508.64336 | G49: 511.35789 | H49: 508.25907 | I49: 512.87697 | J49: 520.64165 | K49: 530.0392 | L49: 559.59742 | M49: 594.31767 | N49: 586.12471 | O49: 586.10647 | P49: 585.94652 | Q49: 591.57755 | R49: 588.40611 | S49: 590.0265 | T49: 601.23254 | U49: 611.84038 | V49: 618.89558 | W49: 628.56753 | X49: 636.53503 | Y49: 643.65757 | Z49: 653.5403 | AA49: 665.13766 | AB49: 662.96957 | AC49: 659.34477 | AD49: 670.01832 | AE49: 689.75307 | AF49: 721.65122
A50: EPS (diluted) | B50: 3.7182 | C50: 3.7319 | D50: 3.8859 | E50: 3.4727 | F50: 2.6435 | G50: 1.0208 | H50: 0.42 | I50: 3.2 | J50: 2.7 | K50: 2.08 | L50: 1.64 | M50: 1.15 | N50: 1.58 | O50: 1.67 | P50: 1.9 | Q50: 1.96 | R50: 1.99 | S50: 1.77 | T50: 1.81 | U50: 1.6 | V50: 1.35 | W50: 1.47 | X50: 1.37 | Y50: 1.18 | Z50: 1.01 | AA50: 0.88 | AB50: 0.335 | AC50: 0.54 | AD50: 0.4775 | AE50: 0.4275 | AF50: 0.38
A51: Diluted Shares Outstanding | B51: 480.66263 | C51: 489.82565 | D51: 503.09609 | E51: 509.71976 | F51: 514.00583 | G51: 513.55509 | H51: 514.02597 | I51: 523.38112 | J51: 529.08985 | K51: 548.54503 | L51: 577.39141 | M51: 596.84903 | N51: 590.21622 | O51: 592.67511 | P51: 588.99144 | Q51: 588.69155 | R51: 593.59004 | S51: 596.0692 | T51: 610.97078 | U51: 626.3668 | V51: 628.80065 | W51: 653.15712 | X51: 661.91923 | Y51: 661.53538 | Z51: 673.44578 | AA51: 677.94935 | AB51: 669.55586 | AC51: 673.59334 | AD51: 686.88036 | AE51: 708.94034 | AF51: 730.39559
A52: Total Shares Outstanding | B52: 478.9271 | C52: 477.49624 | D52: 491.75822 | E52: 505.11207 | F52: 508.64336 | G52: 511.35789 | H52: 508.25907 | I52: 512.87697 | J52: 520.64165 | K52: 530.0392 | L52: 559.59742 | M52: 594.31767 | N52: 586.12471 | O52: 586.10647 | P52: 585.94652 | Q52: 591.57755 | R52: 588.40611 | S52: 590.0265 | T52: 601.23254 | U52: 611.84038 | V52: 618.89558 | W52: 628.56753 | X52: 636.53503 | Y52: 643.65757 | Z52: 653.5403 | AA52: 665.13766 | AB52: 662.96957 | AC52: 659.34477 | AD52: 670.01832 | AE52: 689.75307 | AF52: 721.65122
A53: Earnings Persistence | C53: 90.015 | D53: 84.371 | E53: 90.737 | F53: 81.757 | G53: 88.249 | H53: 90.944 | I53: 95.904 | J53: 90.574 | K53: 72.267 | L53: 88.256 | M53: 92.562 | N53: 96.604 | O53: 86.665 | P53: 87.209 | Q53: 81.136 | R53: 79.306 | S53: 94.122 | T53: 95.484 | U53: 88.691 | V53: 83.452 | W53: 89.463 | X53: 81.196 | Y53: 92.073 | Z53: 88.004 | AA53: 87.288 | AB53: 83.089 | AE53: 94.81
A54: Dividends per Share | B54: 2.13 | C54: 2.07 | D54: 2.01 | E54: 1.97 | F54: 1.9 | G54: 1.82 | H54: 1.74 | I54: 1.53 | J54: 1.41 | K54: 1.3 | L54: 1.23 | M54: 1.19 | N54: 1.15 | O54: 1.11 | P54: 1.07 | Q54: 1.03 | R54: 0.99 | S54: 0.94 | T54: 0.85 | U54: 0.74 | V54: 0.66 | W54: 0.58 | X54: 0.5 | Y54: 0.42 | Z54: 0.34 | AA54: 0.27 | AB54: 0.23 | AC54: 0.195 | AD54: 0.17 | AE54: 0.145 | AF54: 0.125
A55: Payout Ratio | B55: 57.285783 | C55: 55.467724 | D55: 51.725469 | E55: 56.728194 | F55: 71.874409 | G55: 178.29154 | H55: 414.28571 | I55: 47.8125 | J55: 52.222222 | K55: 62.5 | L55: 75 | M55: 103.47826 | N55: 72.78481 | O55: 66.467066 | P55: 56.315789 | Q55: 52.55102 | R55: 49.748744 | S55: 53.107345 | T55: 46.961326 | U55: 46.25 | V55: 48.888889 | W55: 39.455782 | X55: 36.49635 | Y55: 35.59322 | Z55: 33.663366 | AA55: 30.681818 | AB55: 33.823529 | AC55: 36.111111 | AD55: 35.789474 | AE55: 33.918129 | AF55: 32.894737
A56: EBITDA
A57: EBITDA | B57: 4560 | C57: 4598 | D57: 4476 | E57: 4030.604 | F57: 3311.451 | G57: 2443.537 | H57: 2423.722 | I57: 3241.461 | J57: 3118.797 | K57: 3090.671 | L57: 2655.2 | M57: 2327.63 | N57: 2271.508 | O57: 2547.461 | P57: 2496.252 | Q57: 2327.402 | R57: 2358.468 | S57: 2249.019 | T57: 2246.383 | U57: 2062.907 | V57: 1826.472 | W57: 1895.21 | X57: 1816.254 | Y57: 1597.412 | Z57: 1439.251 | AA57: 1287 | AB57: 1030.623 | AC57: 872.694 | AD57: 772.202 | AE57: 702.587 | AF57: 638.667
A58: EBIT | B58: 3470 | C58: 3512 | D58: 3482 | E58: 3141.431 | F58: 2429.799 | G58: 1591.131 | H58: 1514.846 | I58: 2492.561 | J58: 2389.297 | K58: 2212.371 | L58: 2009.2 | M58: 1791.83 | N58: 1735.508 | O58: 2041.861 | P58: 2086.452 | Q58: 1931.502 | R58: 1975.868 | S58: 1872.211 | T58: 1879.949 | U58: 1708.482 | V58: 1495.03 | W58: 1589.53 | X58: 1532.659 | Y58: 1324 | Z58: 1161 | AA58: 1039 | AB58: 809.962 | AC58: 667.689 | AD58: 590.968 | AE58: 542.295 | AF58: 493.958
A59: Depreciation & Amortization Expense | B59: 1090 | C59: 1086 | D59: 994 | E59: 889.173 | F59: 881.652 | G59: 852.406 | H59: 908.876 | I59: 748.9 | J59: 729.5 | K59: 878.3 | L59: 646 | M59: 535.8 | N59: 536 | O59: 505.6 | P59: 409.8 | Q59: 395.9 | R59: 382.6 | S59: 376.808 | T59: 366.434 | U59: 354.425 | V59: 331.442 | W59: 305.68 | X59: 283.595 | Y59: 273.412 | Z59: 278.251 | AA59: 248 | AB59: 220.661 | AC59: 205.005 | AD59: 181.234 | AE59: 160.292 | AF59: 144.709
A60: All figures in millions of U.S. Dollar except per share items.

Sheet Balance Sheet
A1: Sysco Corporation (SYY)
A2: $71.53
A5: Sysco Corporation
A6: SYY 871829107 2868165 NYSE Common stock
A7: Source: FactSet Fundamentals
B8: JUN '25 | C8: JUN '24 | D8: JUN '23 | E8: JUN '22 | F8: JUN '21 | G8: JUN '20 | H8: JUN '19 | I8: JUN '18 | J8: JUN '17 | K8: JUN '16 | L8: JUN '15 | M8: JUN '14 | N8: JUN '13 | O8: JUN '12 | P8: JUN '11 | Q8: JUN '10 | R8: JUN '09 | S8: JUN '08 | T8: JUN '07 | U8: JUN '06 | V8: JUN '05 | W8: JUN '04 | X8: JUN '03 | Y8: JUN '02 | Z8: JUN '01 | AA8: JUN '00 | AB8: JUN '99 | AC8: JUN '98 | AD8: JUN '97 | AE8: JUN '96
I9: Restate | J9: Restate
A10: Assets
A11: Cash & Short-Term Investments | B11: 1071 | C11: 696 | D11: 745.201 | E11: 867.086 | F11: 3007.123 | G11: 6059.427 | H11: 513.46 | I11: 552.325 | J11: 869.502 | K11: 3919.3 | L11: 5130.044 | M11: 413.046 | N11: 412.285 | O11: 688.867 | P11: 639.765 | Q11: 608.954 | R11: 1087.084 | S11: 551.552 | T11: 207.872 | U11: 201.897 | V11: 191.678 | W11: 199.706 | X11: 337.447 | Y11: 230.439 | Z11: 135.743 | AA11: 159.128 | AB11: 149.303 | AC11: 110.288 | AD11: 117.696 | AE11: 107.759
A12: Cash Only | B12: 1071 | C12: 696 | D12: 745.201 | E12: 867.086 | F12: 3007.123 | G12: 6059.427 | H12: 513.46 | I12: 552.325 | J12: 869.502 | K12: 3919.3 | L12: 5130.044 | M12: 413.046 | N12: 412.285 | O12: 688.867 | P12: 639.765 | Q12: 585.443 | R12: 1087.084 | S12: 551.552 | T12: 207.872 | U12: 201.897 | V12: 191.678 | W12: 199.706 | X12: 337.447 | Y12: 230.439 | Z12: 135.743 | AA12: 159.128 | AB12: 149.303 | AC12: 110.288 | AD12: 117.696 | AE12: 107.759
A13: Total Short Term Investments | B13: 0 | C13: 0 | D13: 0 | E13: 0 | F13: 0 | G13: 0 | H13: 0 | I13: 0 | J13: 0 | K13: 0 | L13: 0 | M13: 0 | N13: 0 | O13: 0 | P13: 0 | Q13: 23.511 | R13: 0 | S13: 0 | T13: 0 | U13: 0 | V13: 0 | W13: 0 | X13: 0 | Y13: 0 | Z13: 0 | AA13: 0 | AB13: 0 | AC13: 0 | AD13: 0 | AE13: 0
A14: Short-Term Receivables | B14: 5506 | C14: 5346 | D14: 5097.785 | E14: 4874.846 | F14: 3790.269 | G14: 3001.557 | H14: 4201.429 | I14: 4137.835 | J14: 4029.153 | K14: 3380.971 | L14: 3353.381 | M14: 3398.713 | N14: 3183.114 | O14: 2966.624 | P14: 2898.283 | Q14: 2617.352 | R14: 2468.511 | S14: 2723.189 | T14: 2610.885 | U14: 2483.72 | V14: 2284.033 | W14: 2189.127 | X14: 2009.627 | Y14: 1760.827 | Z14: 1658.044 | AA14: 1519.038 | AB14: 1334.371 | AC14: 1215.61 | AD14: 1065.002 | AE14: 1039.759
A15: Accounts Receivables, Net | B15: 5502 | C15: 5324 | D15: 5091.97 | E15: 4838.912 | F15: 3781.51 | G15: 2893.551 | H15: 4181.696 | I15: 4073.723 | J15: 4012.393 | K15: 3380.971 | L15: 3353.381 | M15: 3398.713 | N15: 3183.114 | O15: 2966.624 | P15: 2898.283 | Q15: 2617.352 | R15: 2468.511 | S15: 2723.189 | T15: 2610.885 | U15: 2483.72 | V15: 2284.033 | W15: 2189.127 | X15: 2009.627 | Y15: 1760.827 | Z15: 1658.044 | AA15: 1519.038 | AC15: 1215.61 | AD15: 1065.002 | AE15: 1039.759
A16: Accounts Receivables, Gross | B16: 5519 | C16: 5378 | D16: 5137.569 | E16: 4909.702 | F16: 3899.205 | G16: 3228.361 | H16: 4209.872 | I16: 4099.491 | J16: 4043.452 | K16: 3418.851 | L16: 3395.101 | M16: 3448.615 | N16: 3230.459 | O16: 3009.543 | P16: 2940.719 | Q16: 2653.925 | R16: 2504.589 | S16: 2754.919 | T16: 2642.726 | U16: 2512.82 | V16: 2313.637 | W16: 2223.302 | X16: 2044.632 | Y16: 1791.165 | Z16: 1686.028 | AA16: 1546.666 | AB16: 21.095 | AC16: 1235.691 | AD16: 1082.242 | AE16: 1056.139
A17: Bad Debt/Doubtful Accounts | B17: -17 | C17: -54 | D17: -45.599 | E17: -70.79 | F17: -117.695 | G17: -334.81 | H17: -28.176 | I17: -25.768 | J17: -31.059 | K17: -37.88 | L17: -41.72 | M17: -49.902 | N17: -47.345 | O17: -42.919 | P17: -42.436 | Q17: -36.573 | R17: -36.078 | S17: -31.73 | T17: -31.841 | U17: -29.1 | V17: -29.604 | W17: -34.175 | X17: -35.005 | Y17: -30.338 | Z17: -27.984 | AA17: -27.628 | AB17: -21.095 | AC17: -20.081 | AD17: -17.24 | AE17: -16.38
A18: Other Receivables | B18: 4 | C18: 22 | D18: 5.815 | E18: 35.934 | F18: 8.759 | G18: 108.006 | H18: 19.733 | I18: 64.112 | J18: 16.76 | K18: 0 | L18: 0 | M18: 0 | N18: 0 | O18: 0 | P18: 0 | Q18: 0 | R18: 0 | S18: 0 | T18: 0 | U18: 0 | V18: 0 | W18: 0 | X18: 0 | Y18: 0 | Z18: 0 | AA18: 0 | AC18: 0 | AD18: 0 | AE18: 0
A19: Inventories | B19: 5053 | C19: 4678 | D19: 4480.812 | E19: 4437.498 | F19: 3695.219 | G19: 3095.085 | H19: 3216.034 | I19: 3125.413 | J19: 2995.598 | K19: 2639.174 | L19: 2691.823 | M19: 2602.018 | N19: 2396.188 | O19: 2178.83 | P19: 2073.766 | Q19: 1771.539 | R19: 1650.666 | S19: 1836.478 | T19: 1714.187 | U19: 1608.233 | V19: 1466.161 | W19: 1404.41 | X19: 1230.08 | Y19: 1117.869 | Z19: 1061.893 | AA19: 937.899 | AB19: 851.965 | AC19: 790.501 | AD19: 733.782 | AE19: 723.937
A20: Finished Goods | B20: 5053 | C20: 4678 | D20: 4480.812 | E20: 4437.498 | F20: 3695.219 | G20: 3095.085 | H20: 3216.034 | I20: 3125.413 | J20: 2995.598 | K20: 2639.174 | L20: 2691.823 | M20: 2602.018 | N20: 2396.188 | O20: 2178.83 | P20: 2073.766 | Q20: 1771.539 | R20: 1650.666 | S20: 1836.478 | T20: 1714.187 | U20: 1608.233 | V20: 1466.161 | W20: 1404.41 | X20: 1230.08 | Y20: 1117.869 | Z20: 1061.893 | AA20: 937.899 | AB20: 851.965
A21: Other Current Assets | B21: 338 | C21: 323 | D21: 284.566 | E21: 303.789 | F21: 240.956 | G21: 192.163 | H21: 210.582 | I21: 187.88 | J21: 139.185 | K21: 114.454 | L21: 319.056 | M21: 268.195 | N21: 215.84 | O21: 250.487 | P21: 121.068 | Q21: 78.413 | R21: 64.418 | S21: 63.814 | T21: 142.602 | U21: 105.844 | V21: 59.914 | W21: 58.168 | X21: 52.38 | Y21: 76.154 | Z21: 129.202 | AA21: 117.15 | AB21: 73.128 | AC21: 63.668 | AD21: 47.937 | AE21: 50.872
A22: Prepaid Expenses | K22: 0 | L22: 90.763 | M22: 43.225 | N22: 17.704 | O22: 35.271 | P22: 48.572 | Q22: 7.421 | S22: 0 | T22: 19.318 | U22: 105.844 | V22: 59.914 | W22: 58.168 | X22: 52.38 | Y22: 41.966 | Z22: 40.456 | AA22: 45.109 | AB22: 29.775 | AC22: 26.595 | AD22: 21.429 | AE22: 18.443
A23: Miscellaneous Current Assets | B23: 338 | C23: 323 | D23: 284.566 | E23: 303.789 | F23: 240.956 | G23: 192.163 | H23: 210.582 | I23: 187.88 | J23: 139.185 | K23: 114.454 | L23: 228.293 | M23: 224.97 | N23: 198.136 | O23: 215.216 | P23: 72.496 | Q23: 70.992 | R23: 64.418 | S23: 63.814 | T23: 123.284 | W23: 0 | X23: 0 | Y23: 34.188 | Z23: 88.746 | AA23: 72.041 | AB23: 43.353 | AC23: 37.073 | AD23: 26.508 | AE23: 32.429
A24: Total Current Assets | B24: 11968 | C24: 11043 | D24: 10608.364 | E24: 10483.219 | F24: 10733.567 | G24: 12348.232 | H24: 8141.505 | I24: 8003.453 | J24: 8033.438 | K24: 10053.899 | L24: 11494.304 | M24: 6681.972 | N24: 6207.427 | O24: 6084.808 | P24: 5732.882 | Q24: 5076.258 | R24: 5270.679 | S24: 5175.033 | T24: 4675.546 | U24: 4399.694 | V24: 4001.786 | W24: 3851.411 | X24: 3629.534 | Y24: 3185.289 | Z24: 2984.882 | AA24: 2733.215 | AB24: 2408.767 | AC24: 2180.067 | AD24: 1964.417 | AE24: 1922.327
A25: Net Property, Plant & Equipment | B25: 7215 | C25: 6420 | D25: 5646.815 | E25: 5179.717 | F25: 5035.226 | G25: 5062.183 | H25: 4501.705 | I25: 4521.66 | J25: 4377.302 | K25: 3880.442 | L25: 3982.143 | M25: 3985.618 | N25: 3978.071 | O25: 3883.75 | P25: 3512.389 | Q25: 3203.823 | R25: 2979.2 | S25: 2889.79 | T25: 2721.233 | U25: 2464.9 | V25: 2268.301 | W25: 2166.809 | X25: 1922.66 | Y25: 1697.782 | Z25: 1518.593 | AA25: 1344.693 | AB25: 1227.669 | AC25: 1151.054 | AD25: 1058.432 | AE25: 990.642
A26: Property, Plant & Equipment - Gross | B26: 15095 | C26: 13946 | D26: 12796.125 | E26: 11934.736 | F26: 11382.634 | G26: 10772.097 | H26: 9954.229 | I26: 10200.85 | J26: 9699.133 | K26: 8585.25 | L26: 8390.448 | M26: 8083.875 | N26: 7755.997 | O26: 7341.051 | P26: 6748.227 | Q26: 6159.986 | R26: 5767.413 | S26: 5464.483 | T26: 5084.338 | U26: 4638.94 | V26: 4245.95 | W26: 3982.824 | X26: 3603.137 | Y26: 3216.943 | Z26: 2895.698 | AA26: 2559.518 | AB26: 2317.044 | AC26: 2142.962 | AD26: 1932.186 | AE26: 1754.144
A27: Buildings | B27: 6217 | C27: 5976 | D27: 5768.715 | E27: 5335.446 | F27: 4984.355 | G27: 4854.307 | H27: 4545.099 | I27: 4268.687 | J27: 4072.339 | K27: 3962.454 | L27: 3877.817 | M27: 3816.387 | N27: 3632.568 | O27: 3510.627 | P27: 3227.34 | Q27: 2982.524 | R27: 2818.3 | S27: 2652.091 | T27: 2428.184 | U27: 2140.786 | V27: 1916.454 | W27: 1774.87 | X27: 1567.768 | Y27: 1390.712 | Z27: 1202.701 | AA27: 1050.417 | AB27: 957.389 | AC27: 895.915 | AD27: 828.591 | AE27: 754.733
A28: Land & Improvements | B28: 492 | C28: 490 | D28: 493.051 | E28: 489.556 | F28: 492.504 | G28: 493.694 | H28: 498.18 | I28: 495.909 | J28: 477.577 | K28: 448.981 | L28: 441.939 | M28: 431.694 | N28: 435.447 | O28: 352.812 | P28: 348.168 | Q28: 322.626 | R28: 307.328 | S28: 270.157 | T28: 239.206 | U28: 220.542 | V28: 208.189 | W28: 186.628 | X28: 174.959 | Y28: 131.188 | Z28: 120.836 | AA28: 110.546 | AB28: 93.107 | AC28: 100.855 | AD28: 97.384 | AE28: 82.247
A29: Machinery & Equipment | W29: 2021.326 | X29: 1860.41 | Y29: 1695.043 | Z29: 1572.161 | AA29: 1398.555 | AB29: 1266.548 | AC29: 1146.192 | AD29: 1006.211 | AE29: 917.164
A30: Computer Software and Equipment | B30: 2085 | C30: 1769 | D30: 1587.229 | E30: 1499.514 | F30: 1419.497 | G30: 1258.98 | H30: 1213.942 | I30: 1628.121 | J30: 1554.122 | K30: 1183.548 | L30: 1234.138 | M30: 1109.379 | N30: 1054.754 | O30: 1028.594 | P30: 897.712 | Q30: 701.305 | R30: 569.669
A31: Other Property, Plant & Equipment | B31: 5170 | C31: 4788 | D31: 4215.364 | E31: 3886.923 | F31: 3777.115 | G31: 3561.5 | H31: 3697.008 | I31: 3808.133 | J31: 3595.095 | K31: 2990.267 | L31: 2836.554 | M31: 2726.415 | N31: 2633.228 | O31: 2449.018 | P31: 2275.007 | Q31: 2153.531 | R31: 2072.116 | S31: 2542.235 | T31: 2416.948 | U31: 2277.612 | V31: 2121.307
A32: Operating Lease Right-of-Use Assets | B32: 1131 | C32: 923 | D32: 731.766 | E32: 723.297 | F32: 709.163 | G32: 603.616
A33: Accumulated Depreciation | B33: 7880 | C33: 7526 | D33: 7149.31 | E33: 6755.019 | F33: 6347.408 | G33: 5709.914 | H33: 5452.524 | I33: 5679.19 | J33: 5321.831 | K33: 4704.808 | L33: 4408.305 | M33: 4098.257 | N33: 3777.926 | O33: 3457.301 | P33: 3235.838 | Q33: 2956.163 | R33: 2788.213 | S33: 2574.693 | T33: 2363.105 | U33: 2174.04 | V33: 1977.649 | W33: 1816.015 | X33: 1680.477 | Y33: 1519.161 | Z33: 1377.105 | AA33: 1214.825 | AB33: 1089.375 | AC33: 991.908 | AD33: 873.754 | AE33: 763.502
A34: Total Long-Term Investments | B34: 363 | C34: 256 | D34: 220.933 | E34: 64.29 | F34: 73.194 | G34: 126.712 | H34: 83.523 | I34: 177.682 | J34: 0 | K34: 36.805 | L34: 180.871 | M34: 150.24 | N34: 145.328 | O34: 133.447 | P34: 123.998 | Q34: 135.533 | R34: 93.858 | S34: 92.587 | T34: 101.929 | U34: 102.274 | V34: 101.731 | W34: 0 | X34: 83.807 | Y34: 0 | Z34: 0 | AA34: 0 | AB34: 0 | AC34: 0 | AD34: 0 | AE34: 0
A35: Other Long-Term Investments | B35: 363 | C35: 256 | D35: 220.933 | E35: 64.29 | F35: 73.194 | G35: 126.712 | H35: 83.523 | I35: 177.682 | J35: 0 | K35: 36.805 | L35: 180.871 | M35: 150.24 | N35: 145.328 | O35: 133.447 | P35: 123.998 | Q35: 135.533 | R35: 93.858 | S35: 92.587 | T35: 101.929 | U35: 102.274 | V35: 101.731 | W35: 0 | X35: 83.807 | Y35: 0 | Z35: 0 | AA35: 0 | AB35: 0 | AC35: 0 | AD35: 0 | AE35: 0
A36: Intangible Assets | B36: 6311 | C36: 6341 | D36: 5505.284 | E36: 5494.998 | F36: 4690.212 | G36: 4512.641 | H36: 4753.527 | I36: 4935.297 | J36: 4953.639 | K36: 2329.122 | L36: 2114.626 | M36: 2127.899 | N36: 2089.954 | O36: 1779.182 | P36: 1743.227 | Q36: 1656.213 | R36: 1631.884 | S36: 1500.752 | T36: 1446.679 | U36: 1398.242 | V36: 1284.459 | W36: 1218.7 | X36: 1113.96 | Y36: 922.222 | Z36: 768.837 | AA36: 503.039 | AB36: 302.1 | AC36: 307.959 | AD36: 247.423 | AE36: 250.473
A37: Goodwill | B37: 5231 | C37: 5153 | D37: 4645.754 | E37: 4542.315 | F37: 3944.139 | G37: 3732.469 | H37: 3896.226 | I37: 3955.485 | J37: 3916.128 | K37: 2121.661 | L37: 1959.817 | M37: 1950.672 | N37: 1884.235 | O37: 1665.611 | P37: 1633.289 | Q37: 1549.815 | R37: 1510.795 | S37: 1413.224 | T37: 1355.313 | U37: 1302.591 | V37: 1212.603 | W37: 1218.7 | X37: 1113.96 | Y37: 922.222 | Z37: 768.837 | AA37: 503.039 | AB37: 302.1 | AC37: 307.959 | AD37: 247.423 | AE37: 250.473
A38: Other Intangible Assets | B38: 1080 | C38: 1188 | D38: 859.53 | E38: 952.683 | F38: 746.073 | G38: 780.172 | H38: 857.301 | I38: 979.812 | J38: 1037.511 | K38: 207.461 | L38: 154.809 | M38: 177.227 | N38: 205.719 | O38: 113.571 | P38: 109.938 | Q38: 106.398 | R38: 121.089 | S38: 87.528 | T38: 91.366 | U38: 95.651 | V38: 71.856 | W38: 0 | X38: 0 | Y38: 0 | Z38: 0 | AA38: 0 | AB38: 0 | AC38: 0 | AD38: 0 | AE38: 0
A39: Deferred Tax Assets | B39: 497 | C39: 445 | D39: 420.45 | E39: 377.604 | F39: 352.523 | G39: 194.115 | H39: 80.76 | I39: 83.666 | J39: 142.472 | K39: 207.32 | AB39: 0
A40: Other Assets | B40: 420 | C40: 412 | D40: 419.299 | E40: 485.86 | F40: 528.817 | G40: 384.383 | H40: 405.502 | I40: 348.646 | J40: 249.804 | K40: 214.216 | L40: 217.337 | M40: 222.221 | N40: 243.167 | O40: 213.785 | P40: 273.059 | Q40: 241.874 | R40: 240.998 | S40: 424.131 | T40: 573.544 | U40: 626.915 | V40: 611.625 | W40: 610.712 | X40: 186.56 | Y40: 184.46 | Z40: 196.209 | AA40: 233.008 | AB40: 158.046 | AC40: 141.109 | AD40: 166.339 | AE40: 161.963
A41: Deferred Charges | F41: 124.453 | I41: 63.945 | R41: 26.746 | S41: 215.159 | T41: 352.39 | U41: 388.65 | V41: 389.766 | W41: 243.996 | AE41: 0
A42: Tangible Other Assets | B42: 420 | C42: 412 | D42: 419.299 | E42: 485.86 | F42: 404.364 | G42: 384.383 | H42: 405.502 | I42: 284.701 | J42: 249.804 | K42: 214.216 | L42: 217.337 | M42: 222.221 | N42: 243.167 | O42: 213.785 | P42: 273.059 | Q42: 241.874 | R42: 214.252 | S42: 208.972 | T42: 221.154 | U42: 238.265 | V42: 221.859 | W42: 366.716 | X42: 186.56 | Y42: 184.46 | Z42: 196.209 | AA42: 233.008 | AB42: 158.046 | AC42: 141.109 | AD42: 166.339 | AE42: 161.963
A43: Total Assets | B43: 26774 | C43: 24917 | D43: 22821.145 | E43: 22085.688 | F43: 21413.539 | G43: 22628.266 | H43: 17966.522 | I43: 18070.404 | J43: 17756.655 | K43: 16721.804 | L43: 17989.281 | M43: 13167.95 | N43: 12663.947 | O43: 12094.972 | P43: 11385.555 | Q43: 10313.701 | R43: 10216.619 | S43: 10082.293 | T43: 9518.931 | U43: 8992.025 | V43: 8267.902 | W43: 7847.632 | X43: 6936.521 | Y43: 5989.753 | Z43: 5468.521 | AA43: 4813.955 | AB43: 4096.582 | AC43: 3780.189 | AD43: 3436.611 | AE43: 3325.405
A44: Liabilities & Shareholders' Equity
A45: Current
A46: ST Debt & Curr. Portion LT Debt | B46: 1085 | C46: 594 | D46: 161.601 | E46: 686.301 | F46: 597.582 | G46: 1651.561 | H46: 41.279 | I46: 786.505 | J46: 534.013 | K46: 98.472 | L46: 5050.052 | M46: 375.752 | N46: 248.933 | O46: 254.65 | P46: 389.006 | Q46: 7.97 | R46: 9.163 | S46: 4.896 | T46: 22.468 | U46: 135.565 | V46: 474.931 | W46: 236.667 | X46: 122.769 | Y46: 80.114 | Z46: 53.907 | AA46: 51.067 | AB46: 33.864 | AC46: 157.253 | AD46: 27.552 | AE46: 22.324
A47: Accounts Payable | B47: 6512 | C47: 6290 | D47: 6025.757 | E47: 5752.958 | F47: 4884.781 | G47: 3447.065 | H47: 4314.62 | I47: 4136.482 | J47: 3971.112 | K47: 2935.982 | L47: 2881.953 | M47: 2831.028 | N47: 2463.494 | O47: 2209.469 | P47: 2183.417 | Q47: 1953.092 | R47: 1856.887 | S47: 2048.759 | T47: 1981.19 | U47: 1891.357 | V47: 1795.824 | W47: 1742.578 | X47: 1637.505 | Y47: 1349.33 | Z47: 1271.817 | AA47: 1186.721 | AB47: 1013.302 | AC47: 849.159 | AD47: 827.593 | AE47: 779.124
A48: Income Tax Payable | B48: 51 | C48: 131 | D48: 101.894 | E48: 40.042 | F48: 22.644 | G48: 2.938 | H48: 17.343 | I48: 56.793 | J48: 14.54 | K48: 110.69 | N48: 0 | O48: 50.316 | P48: 146.083 | Q48: 178.022 | R48: 486.348 | S48: 527.796 | T48: 488.849 | U48: 453.7 | V48: 444.533 | W48: 422.419 | X48: 316.404 | Y48: 41.596 | Z48: 123.332 | AA48: 17.914 | AB48: 6.103 | AC48: 25.523 | AD48: 17.741 | AE48: 23.33
A49: Other Current Liabilities | B49: 2268 | C49: 2226 | D49: 2251.181 | E49: 2270.753 | F49: 1814.837 | G49: 1616.289 | H49: 1729.941 | I49: 1608.966 | J49: 1576.221 | K49: 1289.312 | L49: 1467.61 | M49: 1160.85 | N49: 1036.855 | O49: 909.144 | P49: 856.569 | Q49: 870.114 | R49: 797.756 | S49: 917.892 | T49: 922.582 | U49: 745.781 | V49: 742.282 | W49: 724.97 | X49: 624.451 | Y49: 768.317 | Z49: 640.839 | AA49: 527.233 | AB49: 374.271 | AC49: 292.255 | AD49: 240.928 | AE49: 212.746
A50: Miscellaneous Current Liabilities | B50: 2268 | C50: 2226 | D50: 2251.181 | E50: 2270.753 | F50: 1814.837 | G50: 1616.289 | H50: 1729.941 | I50: 1608.966 | J50: 1576.221 | K50: 1289.312 | L50: 1467.61 | M50: 1160.85 | N50: 1036.855 | O50: 909.144 | P50: 856.569 | Q50: 870.114 | R50: 797.756 | S50: 917.892 | T50: 922.582 | U50: 745.781 | V50: 742.282 | W50: 724.97 | X50: 624.451 | Y50: 768.317 | Z50: 640.839 | AA50: 527.233 | AB50: 374.271 | AC50: 292.255 | AD50: 240.928 | AE50: 212.746
A51: Total Current Liabilities | B51: 9916 | C51: 9241 | D51: 8540.433 | E51: 8750.054 | F51: 7319.844 | G51: 6717.853 | H51: 6103.183 | I51: 6588.746 | J51: 6095.886 | K51: 4434.456 | L51: 9399.615 | M51: 4367.63 | N51: 3749.282 | O51: 3423.579 | P51: 3575.075 | Q51: 3009.198 | R51: 3150.154 | S51: 3499.343 | T51: 3415.089 | U51: 3226.403 | V51: 3457.57 | W51: 3126.634 | X51: 2701.129 | Y51: 2239.357 | Z51: 2089.895 | AA51: 1782.935 | AB51: 1427.54 | AC51: 1324.19 | AD51: 1113.814 | AE51: 1037.524
A52: Long-Term
A53: Long-Term Debt | B53: 13409 | C53: 12351 | D53: 11004.266 | E53: 10703.348 | F53: 11222.665 | G53: 13425.981 | H53: 8122.058 | I53: 7540.765 | J53: 7660.877 | K53: 7336.93 | L53: 2271.825 | M53: 2384.167 | N53: 2639.986 | O53: 2763.688 | P53: 2279.517 | Q53: 2472.662 | R53: 2467.486 | S53: 1975.435 | T53: 1758.227 | U53: 1627.127 | V53: 956.177 | W53: 1231.493 | X53: 1249.467 | Y53: 1176.307 | Z53: 961.421 | AA53: 1023.642 | AB53: 997.717 | AC53: 867.017 | AD53: 685.62 | AE53: 581.734
A54: Long-Term Debt excl Lease Obligations | B54: 11973 | C54: 11206 | D54: 10088.11 | E54: 9879.706 | F54: 10536.902 | G54: 12833.543 | H54: 8122.058 | I54: 7540.765 | J54: 7660.877 | K54: 7336.93 | L54: 2271.825 | M54: 2384.167 | N54: 2639.986 | O54: 2763.688 | P54: 2279.517 | Q54: 2472.662 | R54: 2467.486 | S54: 1975.435 | T54: 1758.227 | U54: 1627.127 | V54: 956.177 | W54: 1200.36 | X54: 1215.939 | Y54: 1171.608 | Z54: 961.421 | AA54: 1023.642 | AB54: 997.717 | AC54: 867.017 | AD54: 685.62 | AE54: 581.734
A55: Capital and Operating Lease Obligations | B55: 1436 | C55: 1145 | D55: 916.156 | E55: 823.642 | F55: 685.763 | G55: 592.438 | H55: 0 | I55: 0 | J55: 0 | K55: 0 | L55: 0 | M55: 0 | N55: 0 | O55: 0 | P55: 0 | Q55: 0 | R55: 0 | S55: 0 | T55: 0 | U55: 0 | V55: 0 | W55: 31.133 | X55: 33.528 | Y55: 4.699 | Z55: 0 | AA55: 0 | AB55: 0 | AC55: 0 | AD55: 0 | AE55: 0
A56: Provision for Risks & Charges | B56: 509 | C56: 498 | D56: 415.155 | E56: 400.826 | F56: 552.311 | G56: 724.414 | H56: 662.508 | I56: 548.927 | J56: 1011.917 | K56: 1140.255 | L56: 648.056 | M56: 708.477 | N56: 545.832 | O56: 907.295 | P56: 398.397 | Q56: 531.886 | R56: 322.658 | S56: 315.328 | T56: 323.658 | U56: 0 | V56: 0 | W56: 0 | X56: 289.998 | Y56: 0 | Z56: 0 | AA56: 0 | AE56: 0
A57: Deferred Tax Liabilities | B57: 345 | C57: 345 | D57: 302.904 | E57: 250.171 | F57: 147.066 | G57: 86.601 | H57: 172.232 | I57: 319.124 | J57: 161.715 | K57: 26.942 | L57: 81.591 | M57: 121.58 | N57: 266.222 | O57: 115.166 | P57: 204.223 | Q57: 271.512 | R57: 526.377 | S57: 540.33 | T57: 626.695 | U57: 723.349 | V57: 724.929 | W57: 686.705 | X57: 498.396 | Y57: 441.57 | Z57: 269.685 | AA57: 245.81 | AB57: 244.129
A58: Other Liabilities | B58: 738 | C58: 591 | D58: 516.553 | E58: 567.081 | F58: 584.169 | G58: 480.539 | H58: 368.512 | I58: 528.236 | J58: 361.905 | K58: 228.227 | L58: 286.666 | M58: 319.401 | N58: 270.815 | O58: 200.204 | P58: 223.101 | Q58: 200.917 | R58: 300.242 | S58: 342.871 | T58: 116.862 | U58: 362.862 | V58: 370.387 | W58: 238.294 | X58: 0 | Y58: 0 | Z58: 0 | AA58: 0 | AB58: 0 | AC58: 232.193 | AD58: 236.705 | AE58: 231.469
A59: Other Liabilities (excl. Deferred Income) | B59: 738 | C59: 591 | D59: 516.553 | E59: 567.081 | F59: 584.169 | G59: 480.539 | H59: 368.512 | I59: 528.236 | J59: 361.905 | K59: 228.227 | L59: 286.666 | M59: 319.401 | N59: 270.815 | O59: 200.204 | P59: 223.101 | Q59: 200.917 | R59: 300.242 | S59: 342.871 | T59: 116.862 | U59: 362.862 | V59: 370.387 | W59: 238.294 | X59: 0 | Y59: 0 | Z59: 0 | AA59: 0 | AB59: 0 | AC59: 232.193 | AD59: 236.705 | AE59: 231.469
A60: Total Liabilities | B60: 24917 | C60: 23026 | D60: 20779.311 | E60: 20671.48 | F60: 19826.055 | G60: 21435.388 | H60: 15428.493 | I60: 15525.798 | J60: 15292.3 | K60: 13166.81 | L60: 12687.753 | M60: 7901.255 | N60: 7472.137 | O60: 7409.932 | P60: 6680.313 | Q60: 6486.175 | R60: 6766.917 | S60: 6673.307 | T60: 6240.531 | U60: 5939.741 | V60: 5509.063 | W60: 5283.126 | X60: 4738.99 | Y60: 3857.234 | Z60: 3321.001 | AA60: 3052.387 | AB60: 2669.386 | AC60: 2423.4 | AD60: 2036.139 | AE60: 1850.727
A61: Equity
A62: Common Equity | B62: 1830 | C62: 1860 | D62: 2008.622 | E62: 1382.26 | F62: 1552.896 | G62: 1158.613 | H62: 2502.603 | I62: 2506.957 | J62: 2381.516 | K62: 3479.608 | L62: 5260.224 | M62: 5266.695 | N62: 5191.81 | O62: 4685.04 | P62: 4705.242 | Q62: 3827.526 | R62: 3449.702 | S62: 3408.986 | T62: 3278.4 | U62: 3052.284 | V62: 2758.839 | W62: 2564.506 | X62: 2197.531 | Y62: 2132.519 | Z62: 2147.52 | AA62: 1761.568 | AB62: 1427.196 | AC62: 1356.789 | AD62: 1400.472 | AE62: 1474.678
A63: Common Stock Par/Carry Value | B63: 765 | C63: 765 | D63: 765.175 | E63: 765.175 | F63: 765.175 | G63: 765.175 | H63: 765.175 | I63: 765.175 | J63: 765.175 | K63: 765.175 | L63: 765.175 | M63: 765.175 | N63: 765.175 | O63: 765.175 | P63: 765.175 | Q63: 765.175 | R63: 765.175 | S63: 765.175 | T63: 765.175 | U63: 765.175 | V63: 765.175 | W63: 765.175 | X63: 765.175 | Y63: 765.175 | Z63: 765.175 | AA63: 382.587 | AB63: 382.587 | AC63: 382.587 | AD63: 191.294 | AE63: 191.294
A64: Additional Paid-In Capital/Capital Surplus | B64: 1986 | C64: 1908 | D64: 1814.681 | E64: 1766.305 | F64: 1619.995 | G64: 1506.901 | H64: 1457.419 | I64: 1383.619 | J64: 1327.366 | K64: 1281.14 | L64: 1213.999 | M64: 1139.218 | N64: 1059.624 | O64: 939.179 | P64: 887.754 | Q64: 816.833 | R64: 760.352 | S64: 712.208 | T64: 637.154 | U64: 525.684 | V64: 389.053 | W64: 332.041 | X64: 249.235 | Y64: 217.891 | Z64: 186.818 | AA64: 76.967 | AB64: 0.872 | AD64: 32.258 | AE64: 35.179
A65: Retained Earnings | B65: 13061 | C65: 12260 | D65: 11310.664 | E65: 10539.722 | F65: 10151.706 | G65: 10563.008 | H65: 11229.679 | I65: 10348.628 | J65: 9447.755 | K65: 9006.138 | L65: 8751.985 | M65: 8770.751 | N65: 8512.786 | O65: 8175.23 | P65: 7681.669 | Q65: 7134.139 | R65: 6539.89 | S65: 6041.429 | T65: 5544.078 | U65: 4999.44 | V65: 4552.379 | W65: 3959.714 | X65: 3373.853 | Y65: 2869.417 | Z65: 2462.145 | AA65: 2332.238 | AB65: 2032.068 | AC65: 1796.488 | AD65: 1771.548 | AE65: 1568.589
A66: Cumulative Translation Adjustment/Unrealized For. Exch. Gain | B66: -120 | C66: -407 | D66: -374.29 | E66: -501.517 | F66: -40.092 | G66: -402.384 | H66: -290.169 | I66: -171.043 | J66: -148.056 | K66: -136.813 | L66: -97.733 | M66: 134.452 | N66: 137.558 | O66: 170.749 | P66: 251.752 | Q66: 129.535 | R66: 79.562 | S66: 164.014 | T66: 133.5 | U66: 108.448 | V66: 60.73
A67: Unrealized Gain/Loss Marketable Securities | B67: -1 | C67: -5 | D67: -6.793 | E67: -4.972 | F67: 4.415 | G67: 7.095 | H67: 2.827 | I67: 0 | J67: 0 | K67: 0 | L67: 0 | M67: 0 | N67: 0 | O67: 0 | P67: 0 | Q67: 0 | R67: 0 | S67: 0 | T67: 0 | U67: 0 | V67: 0 | W67: 0 | X67: 0 | Y67: 0 | Z67: 0 | AA67: 0 | AB67: 0 | AC67: 0 | AD67: 0 | AE67: 0
A68: Other Appropriated Reserves | B68: -977 | C68: -927 | D68: -871.507 | E68: -975.565 | F68: -1113.087 | G68: -1315.592 | H68: -1312.387 | I68: -1238.226 | J68: -1114.681 | K68: -1221.305 | L68: -825.464 | M68: -777.115 | N68: -584.495 | O68: -833.615 | P68: -511.71 | Q68: -609.786 | R68: -357.548 | S68: -232.782 | T68: -137.561 | U68: -23.83 | V68: -74.407 | Y68: -65.435 | Z68: -5.624
A69: Treasury Stock | B69: -12884 | C69: -11734 | D69: -10629.308 | E69: -10206.888 | F69: -9835.216 | G69: -9965.59 | H69: -9349.941 | I69: -8581.196 | J69: -7896.043 | K69: -6214.727 | L69: -4547.738 | M69: -4765.786 | N69: -4698.838 | O69: -4531.678 | P69: -4369.398 | Q69: -4408.37 | R69: -4337.729 | S69: -4041.058 | T69: -3663.946 | U69: -3322.633 | V69: -2934.091 | W69: -2510.064 | X69: -2038.351 | Y69: -1654.529 | Z69: -1260.994 | AA69: -1030.224 | AB69: -988.331 | AC69: -822.286 | AD69: -594.628 | AE69: -320.384
A70: Total Shareholders' Equity | B70: 1830 | C70: 1860 | D70: 2008.622 | E70: 1382.26 | F70: 1552.896 | G70: 1158.613 | H70: 2502.603 | I70: 2506.957 | J70: 2381.516 | K70: 3479.608 | L70: 5260.224 | M70: 5266.695 | N70: 5191.81 | O70: 4685.04 | P70: 4705.242 | Q70: 3827.526 | R70: 3449.702 | S70: 3408.986 | T70: 3278.4 | U70: 3052.284 | V70: 2758.839 | W70: 2564.506 | X70: 2197.531 | Y70: 2132.519 | Z70: 2147.52 | AA70: 1761.568 | AB70: 1427.196 | AC70: 1356.789 | AD70: 1400.472 | AE70: 1474.678
A71: Accumulated Minority Interest | B71: 27 | C71: 31 | D71: 33.212 | E71: 31.948 | F71: 34.588 | G71: 34.265 | H71: 35.426 | I71: 37.649 | J71: 82.839 | K71: 75.386 | L71: 41.304 | M71: 0 | N71: 0 | O71: 0 | P71: 0 | Q71: 0 | R71: 0 | S71: 0 | T71: 0 | U71: 0 | V71: 0 | W71: 0 | X71: 0 | Y71: 0 | Z71: 0 | AA71: 0 | AB71: 0 | AC71: 0 | AD71: 0 | AE71: 0
A72: Total Equity | B72: 1857 | C72: 1891 | D72: 2041.834 | E72: 1414.208 | F72: 1587.484 | G72: 1192.878 | H72: 2538.029 | I72: 2544.606 | J72: 2464.355 | K72: 3554.994 | L72: 5301.528 | M72: 5266.695 | N72: 5191.81 | O72: 4685.04 | P72: 4705.242 | Q72: 3827.526 | R72: 3449.702 | S72: 3408.986 | T72: 3278.4 | U72: 3052.284 | V72: 2758.839 | W72: 2564.506 | X72: 2197.531 | Y72: 2132.519 | Z72: 2147.52 | AA72: 1761.568 | AB72: 1427.196 | AC72: 1356.789 | AD72: 1400.472 | AE72: 1474.678
A73: Total Liabilities & Shareholders' Equity | B73: 26774 | C73: 24917 | D73: 22821.145 | E73: 22085.688 | F73: 21413.539 | G73: 22628.266 | H73: 17966.522 | I73: 18070.404 | J73: 17756.655 | K73: 16721.804 | L73: 17989.281 | M73: 13167.95 | N73: 12663.947 | O73: 12094.972 | P73: 11385.555 | Q73: 10313.701 | R73: 10216.619 | S73: 10082.293 | T73: 9518.931 | U73: 8992.025 | V73: 8267.902 | W73: 7847.632 | X73: 6936.521 | Y73: 5989.753 | Z73: 5468.521 | AA73: 4813.955 | AB73: 4096.582 | AC73: 3780.189 | AD73: 3436.611 | AE73: 3325.405
A74: Per Share
A75: Book Value per Share | B75: 3.83249 | C75: 3.78235 | D75: 3.97659 | E75: 2.71754 | F75: 3.03681 | G75: 2.27957 | H75: 4.87954 | I75: 4.81513 | J75: 4.49309 | K75: 6.21806 | L75: 8.85086 | M75: 8.98562 | N75: 8.85813 | O75: 7.99568 | P75: 7.95372 | Q75: 6.50491 | R75: 5.84669 | S75: 5.67 | T75: 5.35826 | U75: 4.93182 | V75: 4.38909 | W75: 4.02885 | X75: 3.41413 | Y75: 3.26303 | Z75: 3.22869 | AA75: 2.65709 | AB75: 2.16457 | AC75: 2.025 | AD75: 2.0304 | AE75: 2.04348
A76: Tangible Book Value per Share | B76: -9.384367 | C76: -9.112202 | D76: -6.922547 | E76: -8.085701 | F76: -6.135265 | G76: -6.599052 | H76: -4.388819 | I76: -4.664129 | J76: -4.852703 | K76: 2.055917 | L76: 5.292789 | M76: 5.355167 | N76: 5.292308 | O76: 4.959255 | P76: 5.006977 | Q76: 3.690161 | R76: 3.080909 | S76: 3.17387 | T76: 2.993789 | U76: 2.67257 | V76: 2.345619 | W76: 2.114269 | X76: 1.683459 | Y76: 1.851909 | Z76: 2.072778 | AA76: 1.898321 | AB76: 1.706385 | AC76: 1.565375 | AD76: 1.671684 | AE76: 1.696394
A77: All figures in millions of U.S. Dollar except per share items.
A80: US Foods Holding Corp.
A81: USFD 912008109 BYVFC94 NYSE Common stock
A82: Source: FactSet Fundamentals
B83: DEC '25 | C83: DEC '24 | D83: DEC '23 | E83: DEC '22 | F83: DEC '21
A84: Assets
A85: Cash & Short-Term Investments | B85: 41 | C85: 59 | D85: 269 | E85: 211 | F85: 148
A86: Cash Only | B86: 41 | C86: 59 | D86: 269 | E86: 211 | F86: 148
A87: Short-Term Receivables | B87: 2262 | C87: 2167 | D87: 2045 | E87: 1877 | F87: 1641
A88: Accounts Receivables, Net | B88: 2262 | C88: 2167 | D88: 2045 | E88: 1877 | F88: 1641
A89: Accounts Receivables, Gross | B89: 2299 | C89: 2198 | D89: 2068 | E89: 1915 | F89: 1681
A90: Bad Debt/Doubtful Accounts | B90: -37 | C90: -31 | D90: -23 | E90: -38 | F90: -40
A91: Inventories | B91: 1711 | C91: 1626 | D91: 1600 | E91: 1616 | F91: 1686
A92: Finished Goods | B92: 1711 | C92: 1626 | D92: 1600 | E92: 1616 | F92: 1686
A93: Other Current Assets | B93: 150 | C93: 122 | D93: 117 | E93: 116 | F93: 119
A94: Prepaid Expenses | B94: 90 | C94: 103 | D94: 103 | E94: 95 | F94: 93
A95: Miscellaneous Current Assets | B95: 60 | C95: 19 | D95: 14 | E95: 21 | F95: 26
A96: Total Current Assets | B96: 4164 | C96: 3974 | D96: 4031 | E96: 3820 | F96: 3594
... A116: Total Assets | B116: 14312 | C116: 13794 | D116: 13555 | E116: 12773 | F116: 12521
A117: Liabilities & Shareholders' Equity
A118: Current
A119: ST Debt & Curr. Portion LT Debt | B119: 353 | C119: 367 | D119: 373 | E119: 327 | F119: 314
A120: Accounts Payable | B120: 2447 | C120: 2231 | D120: 2051 | E120: 1855 | F120: 1662
A121: Income Tax Payable | B121: 38
A122: Other Current Liabilities | B122: 753 | C122: 698 | D122: 688 | E122: 614 | F122: 574
A123: Accrued Payroll | B123: 308 | C123: 261 | D123: 265 | E123: 246 | F123: 197
...

Sheet Comparable Co Statements 
A1: US Foods Holding Corp. (USFD) | H1: Performance Food Group Co (PFGC) | O1: United Natural Foods, Inc. (UNFI)
A2: 89.91 | H2: 84.01 | O2: 44.84
A5: US Foods Holding Corp. | H5: Performance Food Group Co | O5: United Natural Foods, Inc.
A6: USFD 912008109 BYVFC94 NYSE Common stock | H6: PFGC 71377A103 BYVYD43 NYSE Common stock | O6: UNFI 911163103 2895163 NYSE Common stock
A7: Source: FactSet Fundamentals | H7: Source: FactSet Fundamentals | O7: Source: FactSet Fundamentals
B8: DEC '25 | C8: DEC '24 | D8: DEC '23 | E8: DEC '22 | F8: DEC '21 | I8: DEC '25 | J8: DEC '24 | K8: DEC '23 | L8: DEC '22 | M8: DEC '21 | P8: DEC '25 | Q8: DEC '24 | R8: DEC '23 | S8: DEC '22 | T8: DEC '21
A9: Profitability | H9: Profitability | O9: Profitability
A10: Gross Margin | B10: 17.41 | C10: 17.25 | D10: 17.27 | E10: 16.13 | F10: 15.79 | H10: Gross Margin | I10: 10.69 | J10: 10.46 | K10: 10.22 | L10: 9.63 | M10: 9.9 | O10: Gross Margin | P10: 12.47 | Q10: 12.4 | R10: 12.33 | S10: 13.23 | T10: 13.7
A11: SG&A to Sales | B11: 14.04 | C11: 14.08 | D11: 14.16 | E11: 14.06 | F11: 14.16 | H11: SG&A to Sales | I11: 9.33 | J11: 8.98 | K11: 8.81 | L11: 8.64 | M11: 9.37 | O11: SG&A to Sales | P11: 11.69 | Q11: 11.82 | R11: 12.12 | S11: 12.24 | T11: 12.29
A12: Operating Margin | B12: 3.37 | C12: 3.17 | D12: 3.11 | E12: 2.06 | F12: 1.62 | H12: Operating Margin | I12: 1.36 | J12: 1.48 | K12: 1.42 | L12: 0.99 | M12: 0.53 | O12: Operating Margin | P12: 0.78 | Q12: 0.58 | R12: 0.21 | S12: 0.99 | T12: 1.42
A13: Pretax Margin | B13: 2.28 | C13: 1.7 | D13: 1.9 | E13: 1.06 | F13: 0.73 | H13: Pretax Margin | I13: 0.7 | J13: 0.87 | K13: 1.02 | L13: 0.67 | M13: 0.12 | O13: Pretax Margin | P13: -0.38 | Q13: -0.33 | R13: -0.48 | S13: 0.89 | T13: 0.98
A14: Net Margin | B14: 1.71 | C14: 1.3 | D14: 1.42 | E14: 0.78 | F14: 0.56 | H14: Net Margin | I14: 0.52 | J14: 0.64 | K14: 0.74 | L14: 0.47 | M14: 0.09 | O14: Net Margin | P14: -0.27 | Q14: -0.27 | R14: -0.34 | S14: 0.7 | T14: 0.82
A15: Free Cash Flow Margin | B15: 2.43 | C15: 2.2 | D15: 2.33 | E15: 1.47 | F15: 0.49 | H15: Free Cash Flow Margin | I15: 1.21 | J15: 0.89 | K15: 1.11 | L15: 0.54 | M15: 0.17 | O15: Free Cash Flow Margin | P15: 1.2 | Q15: 0.4 | R15: 0.27 | S15: 0.46 | T15: 0.62
A16: Free Cash Flow Conversion Ratio | B16: 141.86 | C16: 168.62 | D16: 162.85 | E16: 174.72 | F16: 71.34 | H16: Free Cash Flow Conversion Ratio | I16: 229.7 | J16: 138.29 | K16: 149.72 | L16: 113.49 | M16: 185.64 | O16: Free Cash Flow Conversion Ratio | P16: -441.25 | Q16: -148.45 | R16: -77.81 | S16: 66.45 | T16: 76.13
A17: Capex To Sales | B17: 1.04 | C17: 0.9 | D17: 0.87 | E17: 0.78 | F17: 0.93 | H17: Capex To Sales | I17: 0.75 | J17: 0.75 | K17: 0.55 | L17: 0.44 | M17: 0.44 | O17: Capex To Sales | P17: 0.6 | Q17: 0.99 | R17: 1.05 | S17: 0.96 | T17: 1.18
A18: Return on Assets | B18: 4.81 | C18: 3.61 | D18: 3.84 | E18: 2.1 | F18: 1.31 | H18: Return on Assets | I18: 1.93 | J18: 2.55 | K18: 3.37 | L18: 2.16 | M18: 0.37 | O18: Return on Assets | P18: -1.13 | Q18: -1.11 | R18: -1.33 | S18: 2.63 | T18: 2.93
A19: Return on Equity | B19: 15.3 | C19: 10.65 | D19: 10.95 | E19: 6.05 | F19: 3.94 | H19: Return on Equity | I19: 7.75 | J19: 9.54 | K19: 11.67 | L19: 8 | M19: 1.42 | O19: Return on Equity | P19: -5.4 | Q19: -5.18 | R19: -5.87 | S19: 11.84 | T19: 15.85
A20: Return on Common Equity | B20: 15.3 | C20: 10.65 | D20: 11.46 | E20: 5.93 | F20: 3.33 | H20: Return on Common Equity | I20: 7.75 | J20: 9.54 | K20: 11.67 | L20: 8 | M20: 1.42 | O20: Return on Common Equity | P20: -5.4 | Q20: -5.18 | R20: -5.87 | S20: 11.84 | T20: 15.85
A21: Return on Total Capital | B21: 13.31 | C21: 12.06 | D21: 11.2 | E21: 7.19 | F21: 4.79 | H21: Return on Total Capital | I21: 7.21 | J21: 8.48 | K21: 9.52 | L21: 6.77 | M21: 3.11 | O21: Return on Total Capital | P21: 4.8 | Q21: 3.4 | R21: 1.2 | S21: 5.54 | T21: 7.73
... A23: Cash Flow Return on Invested Capital | B23: 14.21 | C23: 12.25 | D23: 11.96 | E23: 8.09 | F23: 4.33 | H23: Cash Flow Return on Invested Capital | I23: 10.68 | J23: 9.64 | K23: 11.44 | L23: 6.81 | M23: 3.71 | O23: Cash Flow Return on Invested Capital | P23: 11.43 | Q23: 8.48 | R23: 7.75 | S23: 8.3 | T23: 10.26
A24: Valuation | H24: Valuation | O24: Valuation
A25: Enterprise Value/EBIT | B25: 16.76 | C25: 17.42 | D25: 14.53 | E25: 18.88 | F25: 28.45 | H25: Enterprise Value/EBIT | I25: 24.05 | J25: 17.01 | K25: 17.11 | L25: 21.65 | M25: 44.82 | O25: Enterprise Value/EBIT | P25: 20.67 | Q25: 24.3 | R25: 69.47 | S25: 19.79 | T25: 13.41
A26: Enterprise Value/EBITDA | B26: 12.44 | C26: 12.77 | D26: 10.7 | E26: 12.35 | F26: 15.9 | H26: Enterprise Value/EBITDA | I26: 12.85 | J26: 10.03 | K26: 10.43 | L26: 11.49 | M26: 15.75 | O26: Enterprise Value/EBITDA | P26: 9.09 | Q26: 8.72 | R26: 11.93 | S26: 9.92 | T26: 7.84
A27: Enterprise Value/Sales | B27: 0.57 | C27: 0.55 | D27: 0.45 | E27: 0.39 | F27: 0.46 | H27: Enterprise Value/Sales | I27: 0.33 | J27: 0.25 | K27: 0.24 | L27: 0.21 | M27: 0.24 | O27: Enterprise Value/Sales | P27: 0.16 | Q27: 0.14 | R27: 0.15 | S27: 0.2 | T27: 0.19
A28: Total Debt/Enterprise Value | B28: 0.26 | C28: 0.26 | D28: 0.32 | E28: 0.4 | F28: 0.4 | H28: Total Debt/Enterprise Value | I28: 0.37 | J28: 0.52 | K28: 0.36 | L28: 0.4 | M28: 0.53 | O28: Total Debt/Enterprise Value | P28: 0.65 | Q28: 0.85 | R28: 0.82 | S28: 0.6 | T28: 0.69
A29: Per Share | H29: Per Share | O29: Per Share
A30: Sales per Share | B30: 171.41 | C30: 155.23 | D30: 142.39 | E30: 150.69 | F30: 131.05 | H30: Sales per Share | I30: 419.42 | J30: 384.52 | K30: 371.68 | L30: 360.58 | M30: 257.5 | O30: Sales per Share | P30: 509.6 | Q30: 525.91 | R30: 511.52 | S30: 485.78 | T30: 452.26
A31: EBIT (Operating Income) per Share | B31: 5.78 | C31: 4.92 | D31: 4.42 | E31: 3.11 | F31: 2.13 | H31: EBIT (Operating Income) per Share | I31: 5.69 | J31: 5.7 | K31: 5.27 | L31: 3.57 | M31: 1.36 | O31: EBIT (Operating Income) per Share | P31: 3.97 | Q31: 3.04 | R31: 1.08 | S31: 4.8 | T31: 6.42
A32: EPS (recurring) | B32: 3.34 | C32: 2.7 | D32: 2.31 | E32: 1.49 | F32: 0.66 | H32: EPS (recurring) | I32: 2.36 | J32: 2.84 | K32: 2.76 | L32: 1.71 | M32: 0.24 | O32: EPS (recurring) | P32: 1.17 | Q32: 0.41 | R32: -0.78 | S32: 3.65 | T32: 4.26
A33: EPS (basic) | B33: 2.98 | C33: 2.05 | D33: 2.09 | E33: 1.02 | F33: 0.55 | H33: EPS (basic) | I33: 2.22 | J33: 2.51 | K33: 2.78 | L33: 1.73 | M33: 0.27 | O33: EPS (basic) | P33: -1.41 | Q33: -1.45 | R33: -1.77 | S33: 3.53 | T33: 4.05
A34: EPS (diluted) | B34: 2.94 | C34: 2.02 | D34: 2 | E34: 1.01 | F34: 0.54 | H34: EPS (diluted) | I34: 2.2 | J34: 2.48 | K34: 2.75 | L34: 1.71 | M34: 0.26 | O34: EPS (diluted) | P34: -1.42 | Q34: -1.45 | R34: -1.77 | S34: 3.38 | T34: 3.8
A35: Book Value per Share | B35: 19.53 | C35: 19.64 | D35: 19.37 | E35: 17.64 | F35: 16.75 | H35: Book Value per Share | I35: 29.84 | J35: 27.54 | K35: 25.09 | L35: 22.66 | M35: 20.62 | O35: Book Value per Share | P35: 25.47 | Q35: 26.95 | R35: 28.52 | S35: 30.82 | T35: 28.41
A36: Tangible Book Value per Share | B36: -10.29 | C36: -9 | D36: -7.14 | E36: -10.91 | F36: -12.2 | H36: Tangible Book Value per Share | I36: -2.72 | J36: -6.3 | K36: 2.41 | L36: 0.47 | M36: -2.77 | O36: Tangible Book Value per Share | P36: 16.16 | Q36: 16.39 | R36: 16.56 | S36: 17.26 | T36: 13.26
A37: Cash Flow per Share | B37: 5.95 | C37: 4.81 | D37: 4.56 | E37: 3.38 | F37: 1.86 | H37: Cash Flow per Share | I37: 8.21 | J37: 6.32 | K37: 6.18 | L37: 3.51 | M37: 1.57 | O37: Cash Flow per Share | P37: 9.13 | Q37: 7.32 | R37: 6.75 | S37: 6.9 | T37: 8.14
A38: Free Cash Flow per Share | B38: 4.17 | C38: 3.41 | D38: 3.32 | E38: 2.21 | F38: 0.64 | H38: Free Cash Flow per Share | I38: 5.06 | J38: 3.43 | K38: 4.13 | L38: 1.94 | M38: 0.44 | O38: Free Cash Flow per Share | P38: 6.09 | Q38: 2.13 | R38: 1.36 | S38: 2.24 | T38: 2.82
A39: Diluted Shares Outstanding (M) | B39: 230 | C39: 244 | D39: 250 | E39: 226 | F39: 225 | H39: Diluted Shares Outstanding (M) | I39: 156.8 | J39: 156.3 | K39: 155.7 | L39: 156.1 | M39: 154.3 | O39: Diluted Shares Outstanding (M) | P39: 62.03 | Q39: 60 | R39: 59.17 | S39: 61.2 | T39: 61.03
A40: Basic Shares Outstanding (M) | B40: 227 | C40: 241 | D40: 239 | E40: 224 | F40: 222 | H40: Basic Shares Outstanding (M) | I40: 155.8 | J40: 154.6 | K40: 154.2 | L40: 154.1 | M40: 152.9 | O40: Basic Shares Outstanding (M) | P40: 60.83 | Q40: 60 | R40: 59.17 | S40: 59.47 | T40: 57.87
A41: Total Shares Outstanding (M) | B41: 220.5 | C41: 230.5 | D41: 245.2 | E41: 224.5 | F41: 223 | H41: Total Shares Outstanding (M) | I41: 155.8 | J41: 154.6 | K41: 153.9 | L41: 154.3 | M41: 153.3 | O41: Total Shares Outstanding (M) | P41: 60.83 | Q41: 60.3 | R41: 59.4 | S41: 59.7 | T41: 58.17
A42: Asset Turnover Analysis | H42: Asset Turnover Analysis | O42: Asset Turnover Analysis
A43: Cash & ST Investments | B43: 788.48 | C43: 230.96 | D43: 148.32 | E43: 189.73 | F43: 60.42 | H43: Cash & ST Investments | I43: 2544.13 | J43: 4435.47 | K43: 5144.07 | L43: 7170.34 | M43: 186.4 | O43: Cash & ST Investments | P43: 710.39 | Q43: 823.16 | R43: 810.66 | S43: 699.52 | T43: 622.54
A44: Receivables | B44: 17.8 | C44: 17.99 | D44: 18.15 | E44: 19.36 | F44: 20.53 | H44: Receivables | I44: 23.96 | J44: 23.79 | K44: 25.14 | L44: 25.9 | M44: 23.77 | O44: Receivables | P44: 30.65 | Q44: 15.57 | R44: 14.71 | S44: 25.12 | T44: 22.81
A45: Inventories | B45: 19.51 | C45: 19.43 | D45: 18.31 | E45: 17.3 | F45: 16.78 | H45: Inventories | I45: 14.36 | J45: 14.8 | K45: 15.54 | L45: 15.57 | M45: 15.34 | O45: Inventories | P45: 12.7 | Q45: 11.74 | R45: 10.58 | S45: 10.2 | T45: 10
A46: Current Assets | B46: 9.69 | C46: 9.46 | D46: 9.07 | E46: 9.19 | F46: 8.35 | H46: Current Assets | I46: 9.23 | J46: 9.36 | K46: 9.84 | L46: 9.95 | M46: 9.1 | O46: Current Assets | P46: 9.16 | Q46: 8.68 | R46: 7.91 | S46: 7.56 | T46: 7.21
A47: Fixed Assets | B47: 13.88 | C47: 14.46 | D47: 14.22 | E47: 14.36 | F47: 12.78 | H47: Fixed Assets | I47: 12.74 | J47: 14.82 | K47: 18.88 | L47: 20.21 | M47: 16.83 | O47: Fixed Assets | P47: 9.86 | Q47: 9.79 | R47: 10.03 | S47: 10.29 | T47: 9.96
A48: Total Assets | B48: 2.81 | C48: 2.77 | D48: 2.7 | E48: 2.69 | F48: 2.36 | H48: Total Assets | I48: 3.68 | J48: 3.95 | K48: 4.54 | L48: 4.57 | M48: 3.99 | O48: Total Assets | P48: 4.17 | Q48: 4.06 | R48: 3.89 | S48: 3.79 | T48: 3.57
A49: DuPont Analysis | H49: DuPont Analysis | O49: DuPont Analysis
A50: Asset Turnover (x) | B50: 2.81 | C50: 2.77 | D50: 2.7 | E50: 2.69 | F50: 2.36 | H50: Asset Turnover (x) | I50: 3.68 | J50: 3.95 | K50: 4.54 | L50: 4.57 | M50: 3.99 | O50: Asset Turnover (x) | P50: 4.17 | Q50: 4.06 | R50: 3.89 | S50: 3.79 | T50: 3.57
A51: x Pretax Margin (%) | B51: 2.28 | C51: 1.7 | D51: 1.9 | E51: 1.06 | F51: 0.73 | H51: x Pretax Margin (%) | I51: 0.7 | J51: 0.87 | K51: 1.02 | L51: 0.67 | M51: 0.12 | O51: x Pretax Margin (%) | P51: -0.38 | Q51: -0.33 | R51: -0.48 | S51: 0.89 | T51: 0.98
A52: = Pretax Return on Assets (%) | B52: 6.39 | C52: 4.71 | D52: 5.15 | E52: 2.85 | F52: 1.72 | H52: = Pretax Return on Assets (%) | I52: 2.59 | J52: 3.45 | K52: 4.65 | L52: 3.06 | M52: 0.49 | O52: = Pretax Return on Assets (%) | P52: -1.59 | Q52: -1.33 | R52: -1.88 | S52: 3.37 | T52: 3.51
A53: x Tax Rate Complement (1-Tax Rate) (%) | B53: 75.28 | C53: 76.71 | D53: 74.63 | E53: 73.41 | F53: 76.64 | H53: x Tax Rate Complement (1-Tax Rate) (%) | I53: 74.47 | J53: 73.72 | K53: 72.42 | L53: 70.74 | M53: 75.77 | O53: x Tax Rate Complement (1-Tax Rate) (%) | S53: 80.6 | T53: 85.58
A54: = Return on Assets (%) | B54: 4.81 | C54: 3.61 | D54: 3.84 | E54: 2.1 | F54: 1.31 | H54: = Return on Assets (%) | I54: 1.93 | J54: 2.55 | K54: 3.37 | L54: 2.16 | M54: 0.37 | O54: = Return on Assets (%) | P54: -1.13 | Q54: -1.11 | R54: -1.33 | S54: 2.63 | T54: 2.93
A55: x Equity Multiplier (Assets/Equity) | B55: 3.18 | C55: 2.95 | D55: 2.85 | E55: 2.89 | F55: 3 | H55: x Equity Multiplier (Assets/Equity) | I55: 4.01 | J55: 3.75 | K55: 3.47 | L55: 3.7 | M55: 3.82 | O55: x Equity Multiplier (Assets/Equity) | P55: 4.78 | Q55: 4.68 | R55: 4.4 | S55: 4.49 | T55: 5.41
A56: = Return on Equity (%) | B56: 15.3 | C56: 10.65 | D56: 10.95 | E56: 6.05 | F56: 3.94 | H56: = Return on Equity (%) | I56: 7.75 | J56: 9.54 | K56: 11.67 | L56: 8 | M56: 1.42 | O56: = Return on Equity (%) | P56: -5.4 | Q56: -5.18 | R56: -5.87 | S56: 11.84 | T56: 15.85
A57: x Earnings Retention (1-Payout) (%) | B57: 100 | C57: 100 | D57: 100 | E57: 100 | F57: 100 | H57: x Earnings Retention (1-Payout) (%) | I57: 100 | J57: 100 | K57: 100 | L57: 100 | M57: 100 | O57: x Earnings Retention (1-Payout) (%) | S57: 100 | T57: 100
A58: = Reinvestment Rate (%) | B58: 15.3 | C58: 10.65 | D58: 10.8 | E58: 5.2 | F58: 2.91 | H58: = Reinvestment Rate (%) | I58: 7.75 | J58: 9.54 | K58: 11.67 | L58: 8 | M58: 1.42 | O58: = Reinvestment Rate (%) | P58: -5.4 | Q58: -5.18 | R58: -5.87 | S58: 11.84 | T58: 15.85
A59: Note: EBIT Return on Assets (%) | B59: 9.46 | C59: 8.78 | D59: 8.4 | E59: 5.56 | F59: 3.84 | H59: Note: EBIT Return on Assets (%) | I59: 4.99 | J59: 5.86 | K59: 6.43 | L59: 4.52 | M59: 2.11 | O59: Note: EBIT Return on Assets (%) | P59: 3.25 | Q59: 2.35 | R59: 0.82 | S59: 3.75 | T59: 5.07
A60: Note: Interest as % Assets | B60: 2.13 | C60: 2.28 | D60: 2.39 | E60: 2 | F60: 1.66 | H60: Note: Interest as % Assets | I60: 2.17 | J60: 1.63 | K60: 1.75 | L60: 1.61 | M60: 1.35 | O60: Note: Interest as % Assets | P60: 1.92 | Q60: 2.05 | R60: 2.23 | S60: 1.62 | T60: 1.61
A61: Operating Efficiency | H61: Operating Efficiency | O61: Operating Efficiency
A62: Revenue/Employee (actual) | B62: 1314133 | C62: 1262567 | D62: 1186567 | E62: 1174379 | F62: 1053107 | H62: Revenue/Employee (actual) | I62: 1529437 | J62: 1502515 | K62: 1607522 | L62: 1608206 | M62: 1370069 | O62: Revenue/Employee (actual) | P62: 1234857 | Q62: 1160331 | R62: 1044059 | S62: 992712 | T62: 947473
A63: Net Income/Employee (actual) | B63: 22533 | C63: 16467 | D63: 16867 | E63: 9138 | F63: 5857 | H63: Net Income/Employee (actual) | I63: 8026 | J63: 9683 | K63: 11928 | L63: 7606 | M63: 1272 | O63: Net Income/Employee (actual) | P63: -3346 | Q63: -3162 | R63: -3576 | S63: 6901 | T63: 7771
A64: Assets/Employee (actual) | B64: 477067 | C64: 459800 | D64: 451833 | E64: 440448 | F64: 447179 | H64: Assets/Employee (actual) | I64: 428691 | J64: 432775 | K64: 364036 | L64: 354514 | M64: 421390 | O64: Assets/Employee (actual) | P64: 287122 | Q64: 287169 | R64: 266667 | S64: 261220 | T64: 270034
A65: Receivables Turnover | B65: 17.8 | C65: 17.99 | D65: 18.15 | E65: 19.36 | F65: 20.53 | H65: Receivables Turnover | I65: 23.96 | J65: 23.79 | K65: 25.14 | L65: 25.9 | M65: 23.77 | O65: Receivables Turnover | P65: 30.65 | Q65: 15.57 | R65: 14.71 | S65: 25.12 | T65: 22.81
A66: Inventory Turnover | B66: 19.51 | C66: 19.43 | D66: 18.31 | E66: 17.3 | F66: 16.78 | H66: Inventory Turnover | I66: 14.36 | J66: 14.8 | K66: 15.54 | L66: 15.57 | M66: 15.34 | O66: Inventory Turnover | P66: 12.7 | Q66: 11.74 | R66: 10.58 | S66: 10.2 | T66: 10
A67: Payables Turnover | B67: 13.96 | C67: 14.65 | D67: 15.07 | E67: 16.2 | F67: 17.53 | H67: Payables Turnover | I67: 18.94 | J67: 20.38 | K67: 21.46 | L67: 20.98 | M67: 19.86 | O67: Payables Turnover | P67: 15.05 | Q67: 15.25 | R67: 14.52 | S67: 14.29 | T67: 13.92
A68: Asset Turnover | B68: 2.81 | C68: 2.77 | D68: 2.7 | E68: 2.69 | F68: 2.36 | H68: Asset Turnover | I68: 3.68 | J68: 3.95 | K68: 4.54 | L68: 4.57 | M68: 3.99 | O68: Asset Turnover | P68: 4.17 | Q68: 4.06 | R68: 3.89 | S68: 3.79 | T68: 3.57
A69: Working Capital Turnover | B69: 68.8 | C69: 55.87 | D69: 38.73 | E69: 33.26 | F69: 28.24 | H69: Working Capital Turnover | I69: 23.87 | J69: 21.79 | K69: 23.44 | L69: 23.34 | M69: 18.76 | O69: Working Capital Turnover | P69: 36.66 | Q69: 27.95 | R69: 23.46 | S69: 19.89 | T69: 20.99
A70: Operating Cycle - Days | H70: Operating Cycle - Days | O70: Operating Cycle - Days
A71: Days of Inventory on Hand | B71: 18.7 | C71: 18.78 | D71: 19.93 | E71: 21.1 | F71: 21.75 | H71: Days of Inventory on Hand | I71: 25.42 | J71: 24.66 | K71: 23.49 | L71: 23.45 | M71: 23.8 | O71: Days of Inventory on Hand | P71: 28.74 | Q71: 31.09 | R71: 34.51 | S71: 35.77 | T71: 36.5
A72: + Days of Sales Outstanding | B72: 20.5 | C72: 20.29 | D72: 20.11 | E72: 18.85 | F72: 17.78 | H72: + Days of Sales Outstanding | I72: 15.24 | J72: 15.34 | K72: 14.52 | L72: 14.09 | M72: 15.35 | O72: + Days of Sales Outstanding | P72: 11.91 | Q72: 23.45 | R72: 24.82 | S72: 14.53 | T72: 16
A73: = Operating Cycle | B73: 39.21 | C73: 39.08 | D73: 40.04 | E73: 39.95 | F73: 39.53 | H73: = Operating Cycle | I73: 40.66 | J73: 40 | K73: 38 | L73: 37.54 | M73: 39.15 | O73: = Operating Cycle | P73: 40.64 | Q73: 54.54 | R73: 59.32 | S73: 50.3 | T73: 52.5
A74: - Days of Payables Outstanding | B74: 26.15 | C74: 24.91 | D74: 24.22 | E74: 22.53 | F74: 20.82 | H74: - Days of Payables Outstanding | I74: 19.27 | J74: 17.91 | K74: 17.01 | L74: 17.4 | M74: 18.38 | O74: - Days of Payables Outstanding | P74: 24.25 | Q74: 23.93 | R74: 25.14 | S74: 25.55 | T74: 26.22
A75: = Net Operating Cycle | B75: 13.05 | C75: 14.17 | D75: 15.82 | E75: 17.42 | F75: 18.71 | H75: = Net Operating Cycle | I75: 21.39 | J75: 22.09 | K75: 21 | L75: 20.14 | M75: 20.77 | O75: = Net Operating Cycle | P75: 16.4 | Q75: 30.6 | R75: 34.18 | S75: 24.75 | T75: 26.28
A76: Liquidity | H76: Liquidity | O76: Liquidity
A77: Current Ratio (x) | B77: 1.16 | C77: 1.21 | D77: 1.3 | E77: 1.37 | F77: 1.41 | H77: Current Ratio (x) | I77: 1.6 | J77: 1.67 | K77: 1.71 | L77: 1.71 | M77: 1.62 | O77: Current Ratio (x) | P77: 1.35 | Q77: 1.46 | R77: 1.53 | S77: 1.61 | T77: 1.51
A78: Quick Ratio (x) | B78: 0.68 | C78: 0.71 | D78: 0.78 | E78: 0.79 | F78: 0.75 | H78: Quick Ratio (x) | I78: 0.68 | J78: 0.72 | K78: 0.75 | L78: 0.73 | M78: 0.68 | O78: Quick Ratio (x) | P78: 0.51 | Q78: 0.53 | R78: 0.53 | S78: 0.55 | T78: 0.56
A79: Cash Ratio | B79: 0.01 | C79: 0.02 | D79: 0.09 | E79: 0.08 | F79: 0.06 | H79: Cash Ratio | I79: 0.01 | J79: 0 | K79: 0 | L79: 0 | M79: 0 | O79: Cash Ratio | P79: 0.02 | Q79: 0.02 | R79: 0.01 | S79: 0.02 | T79: 0.02
A80: Cash & ST Inv/Current Assets | B80: 0.98 | C80: 1.48 | D80: 6.67 | E80: 5.52 | F80: 4.12 | H80: Cash & ST Inv/Current Assets | I80: 0.56 | J80: 0.16 | K80: 0.28 | L80: 0.11 | M80: 0.17 | O80: Cash & ST Inv/Current Assets | P80: 1.42 | Q80: 1.17 | R80: 0.94 | S80: 1 | T80: 1.16
A81: CFO/Current Liabilities | B81: 38.12 | C81: 35.62 | D81: 36.63 | E81: 27.36 | F81: 16.43 | H81: CFO/Current Liabilities | I81: 27.89 | J81: 23.94 | K81: 27.57 | L81: 16.11 | M81: 7.15 | O81: CFO/Current Liabilities | P81: 22.96 | Q81: 18 | R81: 16.53 | S81: 17.21 | T81: 19.11
A82: Coverage | H82: Coverage | O82: Coverage
A83: Net Debt/EBITDA | B83: 2.97 | C83: 3.1 | D83: 3.08 | E83: 4.48 | F83: 5.89 | H83: Net Debt/EBITDA | I83: 4.15 | J83: 4.53 | K83: 3.08 | L83: 3.95 | M83: 7.18 | O83: Net Debt/EBITDA | P83: 3.13 | Q83: 4.15 | R83: 5.91 | S83: 3.76 | T83: 3.64
A84: Net Debt/(EBITDA-Capex) | B84: 4.11 | C84: 4.14 | D84: 4.14 | E84: 6.3 | F84: 9.14 | H84: Net Debt/(EBITDA-Capex) | I84: 6.76 | J84: 7.42 | K84: 4.89 | L84: 6.01 | M84: 11.68 | O84: Net Debt/(EBITDA-Capex) | P84: 8.81 | Q84: 18.9 | R84: 66.96 | S84: 11.47 | T84: 10.34
A85: Total Debt/EBITDA | B85: 3 | C85: 3.14 | D85: 3.26 | E85: 4.68 | F85: 6.06 | H85: Total Debt/EBITDA | I85: 4.18 | J85: 4.54 | K85: 3.09 | L85: 3.95 | M85: 7.2 | O85: Total Debt/EBITDA | P85: 3.22 | Q85: 4.23 | R85: 6 | S85: 3.83 | T85: 3.71
A86: EBIT/Interest Expense (Int. Coverage) | B86: 4.36 | C86: 3.81 | D86: 3.41 | E86: 2.76 | F86: 2.3 | H86: EBIT/Interest Expense (Int. Coverage) | I86: 2.23 | J86: 3.16 | K86: 3.58 | L86: 2.79 | M86: 1.28 | O86: EBIT/Interest Expense (Int. Coverage) | P86: 1.74 | Q86: 1.14 | R86: 0.37 | S86: 2.31 | T86: 3.09
A87: EBITDA/Interest Expense | B87: 5.88 | C87: 5.2 | D87: 4.63 | E87: 4.22 | F87: 4.12 | H87: EBITDA/Interest Expense | I87: 4.17 | J87: 5.36 | K87: 5.87 | L87: 5.25 | M87: 3.63 | O87: EBITDA/Interest Expense | P87: 3.96 | Q87: 3.18 | R87: 2.16 | S87: 4.62 | T87: 5.29
A88: Fixed-charge Coverage Ratio | B88: 4.36 | C88: 3.81 | D88: 3.32 | E88: 2.3 | F88: 1.81 | H88: Fixed-charge Coverage Ratio | I88: 2.23 | J88: 3.16 | K88: 3.58 | L88: 2.79 | M88: 1.28 | O88: Fixed-charge Coverage Ratio | P88: 1.74 | Q88: 1.14 | R88: 0.37 | S88: 2.31 | T88: 3.09
A89: CFO/Interest Expense | B89: 4.49 | C89: 3.73 | D89: 3.52 | E89: 3 | F89: 2.01 | H89: CFO/Interest Expense | I89: 3.22 | J89: 3.51 | K89: 4.19 | L89: 2.74 | M89: 1.47 | O89: CFO/Interest Expense | P89: 4.01 | Q89: 2.74 | R89: 2.32 | S89: 3.32 | T89: 3.92
A90: LT Debt/EBITDA | B90: 3 | C90: 3.09 | D90: 3.22 | E90: 4.64 | F90: 6.02 | H90: LT Debt/EBITDA | I90: 4.57 | J90: 5.01 | K90: 3.58 | L90: 4.43 | M90: 7.98 | O90: LT Debt/EBITDA | P90: 5.64 | Q90: 7.06 | R90: 9.26 | S90: 5.66 | T90: 5
A91: Net Debt/FFO | B91: 4.17 | C91: 4.65 | D91: 4.82 | E91: 7.06 | F91: 8.21 | H91: Net Debt/FFO | I91: 5.84 | J91: 6.86 | K91: 4.78 | L91: 4.94 | M91: 9.3 | O91: Net Debt/FFO | P91: 11.65 | Q91: 14.21 | R91: 11.3 | S91: 5.17 | T91: 6.58
A92: LT Debt/FFO | B92: 3.94 | C92: 4.38 | D92: 4.72 | E92: 6.9 | F92: 7.95 | H92: LT Debt/FFO | I92: 5.61 | J92: 6.61 | K92: 4.58 | L92: 4.75 | M92: 8.97 | O92: LT Debt/FFO | P92: 11.26 | Q92: 13.7 | R92: 10.79 | S92: 4.96 | T92: 6.17
A93: FCF/Total Debt | B93: 0.17 | C93: 0.15 | D93: 0.16 | E93: 0.09 | F93: 0.03 | H93: FCF/Total Debt | I93: 0.1 | J93: 0.07 | K93: 0.13 | L93: 0.06 | M93: 0.01 | O93: FCF/Total Debt | P93: 0.11 | Q93: 0.03 | R93: 0.02 | S93: 0.04 | T93: 0.05
A94: CFO/Total Debt | B94: 0.24 | C94: 0.22 | D94: 0.22 | E94: 0.14 | F94: 0.08 | H94: CFO/Total Debt | I94: 0.16 | J94: 0.13 | K94: 0.19 | L94: 0.11 | M94: 0.05 | O94: CFO/Total Debt | P94: 0.17 | Q94: 0.12 | R94: 0.11 | S94: 0.12 | T94: 0.14
... A97: EBITDA-Capex/Interest Expense | B97: 4.53 | C97: 4.12 | D97: 3.68 | E97: 3.18 | F97: 2.8 | H97: EBITDA-Capex/Interest Expense | I97: 2.94 | J97: 3.76 | K97: 4.48 | L97: 4.02 | M97: 2.57 | O97: EBITDA-Capex/Interest Expense | P97: 2.62 | Q97: 1.23 | R97: 0.31 | S97: 2.38 | T97: 2.72
A98: Leverage | H98: Leverage | O98: Leverage
A99: LT Debt/Total Equity | B99: 124.68 | C99: 111.9 | D99: 101.68 | E99: 110.88 | F99: 120.87 | H99: LT Debt/Total Equity | I99: 164.24 | J99: 177.59 | K99: 124.59 | L99: 132.86 | M99: 150.92 | O99: LT Debt/Total Equity | P99: 203.7 | Q99: 220.64 | R99: 203.78 | S99: 180.52 | T99: 202.74
A100: LT Debt/Total Capital | B100: 53.54 | C100: 50.86 | D100: 48.53 | E100: 50.83 | F100: 52.96 | H100: LT Debt/Total Capital | I100: 60.43 | J100: 62.39 | K100: 54.06 | L100: 55.74 | M100: 58.76 | O100: LT Debt/Total Capital | P100: 64.91 | Q100: 66.6 | R100: 64.59 | S100: 62.14 | T100: 63.59
A101: LT Debt/Total Assets | B101: 37.52 | C101: 36.73 | D101: 35.63 | E101: 39.02 | F101: 41.21 | H101: LT Debt/Total Assets | I101: 41.42 | J101: 43.67 | K101: 36.71 | L101: 37.44 | M101: 39.04 | O101: LT Debt/Total Assets | P101: 42.95 | Q101: 45.91 | R101: 44.67 | S101: 42.45 | T101: 42.58
A102: Total Debt/Total Assets (%) | B102: 39.99 | C102: 39.39 | D102: 38.38 | E102: 41.58 | F102: 43.72 | H102: Total Debt/Total Assets (%) | I102: 43.32 | J102: 45.41 | K102: 38.45 | L102: 38.99 | M102: 40.56 | O102: Total Debt/Total Assets (%) | P102: 45.08 | Q102: 48.13 | R102: 47.23 | S102: 44.8 | T102: 45.96
A103: Net Debt/Total Equity (%) | B103: 131.92 | C103: 118.71 | D103: 103.87 | E103: 113.46 | F103: 124.76 | H103: Net Debt/Total Equity (%) | I103: 170.92 | J103: 184.4 | K103: 130.05 | L103: 138.18 | M103: 156.51 | O103: Net Debt/Total Equity (%) | P103: 210.78 | Q103: 228.74 | R103: 213.42 | S103: 188.37 | T103: 216.08
A104: Total Debt/Equity (%) | B104: 132.88 | C104: 120.01 | D104: 109.54 | E104: 118.15 | F104: 128.23 | H104: Total Debt/Equity (%) | I104: 171.8 | J104: 184.65 | K104: 130.47 | L104: 138.35 | M104: 156.82 | O104: Total Debt/Equity (%) | P104: 213.83 | Q104: 231.3 | R104: 215.48 | S104: 190.52 | T104: 218.82
A105: Net Debt/Total Capital | B105: 56.65 | C105: 53.96 | D105: 49.57 | E105: 52.01 | F105: 54.66 | H105: Net Debt/Total Capital | I105: 62.88 | J105: 64.78 | K105: 56.43 | L105: 57.97 | M105: 60.94 | O105: Net Debt/Total Capital | P105: 67.16 | Q105: 69.04 | R105: 67.65 | S105: 64.84 | T105: 67.77
...

Sheet Bonds
A1: 2. DEBT AND OTHER FINANCING ARRANGEMENTS
D4: Jun. 28, 2025 | J4: Jun. 29, 2024
D5: (In millions)
A6: Euro Commercial paper, interest at 2.22%, maturing in fiscal 2026 | D6: $ | E6: 205 | J6: $ | K6: —
A7: U.S. Commercial paper, interest at 5.45%, matured in fiscal 2025 | D7: — | J7: 200
A8: Senior notes, interest at 3.65%, matured in fiscal 2025 (1) | D8: — | J8: 365
A9: Senior notes, interest at 3.75%, maturing in fiscal 2026 (1)(2) | D9: 750 | J9: 749
A10: Senior notes, interest at 3.30%, maturing in fiscal 2027 (1)(2) | D10: 999 | J10: 998
A11: Debentures, interest at 7.16%, maturing in fiscal 2027 (2)(3) | D11: 43 | J11: 43
A12: Senior notes, interest at 3.25%, maturing in fiscal 2028 (1)(2) | D12: 748 | J12: 747
A13: Debentures, interest at 6.50%, maturing in fiscal 2029 (2) | D13: 155 | J13: 155
A14: Senior notes, interest at 5.75%, maturing in fiscal 2029 (1)(2) | D14: 497 | J14: 496
A15: Senior notes, interest at 2.40%, maturing in fiscal 2030 (1)(2) | D15: 498 | J15: 497
A16: Senior notes, interest at 5.95%, maturing in fiscal 2030 (1)(2) | D16: 995 | J16: 994
A17: Senior notes, interest at 5.10%, maturing in fiscal 2031 (1)(2) | D17: 695 | J17: —
A18: Senior notes, interest at 2.45%, maturing in fiscal 2032 (1)(2) | D18: 447 | J18: 446
A19: Senior notes, interest at 6.00%, maturing in fiscal 2034 (1)(2) | D19: 507 | J19: 498
A20: Senior notes, interest at 5.40%, maturing in fiscal 2035 (1)(2) | D20: 562 | J20: —
A21: Senior notes, interest at 5.375%, maturing in fiscal 2036 (1)(2) | D21: 383 | J21: 383
A22: Senior notes, interest at 6.625%, maturing in fiscal 2039 (1)(2) | D22: 200 | J22: 200
A23: Senior notes, interest at 6.60%, maturing in fiscal 2040 (1)(2) | D23: 350 | J23: 350
A24: Senior notes, interest at 4.85%, maturing in fiscal 2046 (1)(2) | D24: 497 | J24: 497
A25: Senior notes, interest at 4.50%, maturing in fiscal 2046 (1)(2) | D25: 495 | J25: 495
A26: Senior notes, interest at 4.45%, maturing in fiscal 2048 (1)(2) | D26: 493 | J26: 493
A27: Senior notes, interest at 3.30%, maturing in fiscal 2050 (1)(2) | D27: 495 | J27: 495
A28: Senior notes, interest at 6.60%, maturing in fiscal 2050 (1)(2) | D28: 1,177 | J28: 1,177
A29: Senior notes, interest at 3.15%, maturing in fiscal 2052 (1)(2) | D29: 788 | J29: 788
A30: Plant and equipment financing programs, finance leases, notes payable, and other debt, interest averaging 5.14% and maturing at various dates to fiscal 2052 as of June 28, 2025, and 5.13% and maturing at various dates to fiscal 2052 as of June 29, 2024 | D30: 1,330 | J30: 916
A31: Total debt | D31: 13,309 | J31: 11,982
A32: Less current maturities of long-term debt | D32: -949 | J32: -469
A33: Net long-term debt

Sheet Graphics for Presentation
A2: Principal product catageories | C2: 2025 | D2: 2024 | E2: 2023 | I2: Sysco Corporation – Principal Product Categories (% of Sales)
A3: Fresh and frozen meats | C3: 0.19 | I3: Product Category | J3: FY2025 | K3: FY2024 | L3: FY2023 | M3: FY2022 | N3: FY2021
A4: Canned and dry products | C4: 0.18 | I4: Canned and dry products | J4: 0.19 | K4: 0.19 | L4: 0.19 | M4: 0.17 | N4: 0.16
A5: Frozen fruits, vegetables, bakery and other | C5: 0.15 | I5: Fresh and frozen meats | J5: 0.18 | K5: 0.18 | L5: 0.18 | M5: 0.19 | N5: 0.19
A6: Dairy products | C6: 0.11 | I6: Frozen fruits, vegetables, bakery and other | J6: 0.15 | K6: 0.15 | L6: 0.15 | M6: 0.14 | N6: 0.15
A7: Poultry | C7: 0.1 | I7: Dairy products | J7: 0.11 | K7: 0.1 | L7: 0.11 | M7: 0.1 | N7: 0.1
A8: Fresh produce | C8: 0.08 | I8: Poultry | J8: 0.1 | K8: 0.1 | L8: 0.1 | M8: 0.11 | N8: 0.11
A9: Paper and disposables | C9: 0.07 | I9: Fresh produce | J9: 0.08 | K9: 0.09 | L9: 0.09 | M9: 0.08 | N9: 0.08
A10: Beverage products | C10: 0.04 | I10: Paper and disposables | J10: 0.07 | K10: 0.07 | L10: 0.07 | M10: 0.07 | N10: 0.08
A11: Seafood | C11: 0.03 | I11: Seafood | J11: 0.04 | K11: 0.04 | L11: 0.04 | M11: 0.05 | N11: 0.05
A12: Equipment and smallwares | C12: 0.02 | I12: Beverage products | J12: 0.03 | K12: 0.04 | L12: 0.03 | M12: 0.03 | N12: 0.03
A13: Other | C13: 0.03 | I13: Equipment and smallwares | J13: 0.02 | K13: 0.02 | L13: 0.01 | M13: 0.01 | N13: 0
I14: Other | J14: 0.03 | K14: 0.02 | L14: 0.03 | M14: 0.05 | N14: 0.05
V20: l
A23: Type of Customer | C23: 2025 | D23: 2024 | E23: 2023 | F23: 2022 | G23: 2021
A24: Restaurants | C24: 0.6
A25: Eductaion, government | C25: 0.08
A26: Healthcare | C26: 0.08
A27: Travel and leisure | C27: 0.07
A28: Other | C28: 0.17
A33: Sysco Corporation – Sales by Type of Customer (% of Sales)
A34: Customer Type | B34: FY2025 | C34: FY2024 | D34: FY2023 | E34: FY2022 | F34: FY2021
A35: Restaurants | B35: 0.6 | C35: 0.62 | D35: 0.62 | E35: 0.63 | F35: 0.66
A36: Education, government | B36: 0.08 | C36: 0.07 | D36: 0.08 | E36: 0.08 | F36: 0.09
A37: Healthcare | B37: 0.08 | C37: 0.07 | D37: 0.07 | E37: 0.08 | F37: 0.06
A38: Travel and leisure | B38: 0.07 | C38: 0.06 | D38: 0.08 | E38: 0.07 | F38: 0.05
A39: Other | B39: 0.17 | C39: 0.18 | D39: 0.15 | E39: 0.14 | F39: 0.14
A40: TOTALS
